Workbook

Sheet MarketData
A1: Cross_Currency_Swap_rebalancing: market data and fixings (as of 2019-12-30)
A2: Quotes taken from Input\market.txt for every quote referenced by Input\curveconfig.xml; fixings from Input\fixings.txt.
A4: Evaluation date | B4: =_xll.qlSettingsSetEvaluationDate(DATE(2019,12,30),FALSE) -> TRUE | C4: =_xll.ohRangeRetrieveError(B4)
A6: Curve | B6: Segment | C6: Market quote | D6: Value | E6: Quote object | F6: Error | H6: Fixing date | I6: Index | J6: Value
A7: EUR-EONIA | B7: Deposit | C7: MM/RATE/EUR/0D/1D | D7: -0.00454 | E7: =_xll.qlSimpleQuote(SUBSTITUTE(A7&"_"&C7,"/","_"),D7,0,FALSE,$B$4) -> EUR-EONIA_MM_RATE_EUR_0D_1D#0000 | F7: =_xll.ohRangeRetrieveError(E7) | H7: =DATE(2019,8,1) -> 43678 | I7: FX-ECB-EUR-USD | J7: 1.1037
A8: EUR-EONIA | B8: OIS | C8: IR_SWAP/RATE/EUR/2D/1D/1W | D8: -0.00468 | E8: =_xll.qlSimpleQuote(SUBSTITUTE(A8&"_"&C8,"/","_"),D8,0,FALSE,$B$4) -> EUR-EONIA_IR_SWAP_RATE_EUR_2D_1D_1W#0000 | F8: =_xll.ohRangeRetrieveError(E8) | H8: =DATE(2019,8,3) -> 43680 | I8: USD-LIBOR-6M | J8: 0.0222688
A9: EUR-EONIA | B9: OIS | C9: IR_SWAP/RATE/EUR/2D/1D/2W | D9: -0.0045 | E9: =_xll.qlSimpleQuote(SUBSTITUTE(A9&"_"&C9,"/","_"),D9,0,FALSE,$B$4) -> EUR-EONIA_IR_SWAP_RATE_EUR_2D_1D_2W#0000 | F9: =_xll.ohRangeRetrieveError(E9) | H9: =DATE(2019,8,1) -> 43678 | I9: USD-LIBOR-6M | J9: 0.0222688
A10: EUR-EONIA | B10: OIS | C10: IR_SWAP/RATE/EUR/2D/1D/3W | D10: -0.00467 | E10: =_xll.qlSimpleQuote(SUBSTITUTE(A10&"_"&C10,"/","_"),D10,0,FALSE,$B$4) -> EUR-EONIA_IR_SWAP_RATE_EUR_2D_1D_3W#0000 | F10: =_xll.ohRangeRetrieveError(E10) | H10: =DATE(2019,8,1) -> 43678 | I10: EUR-EURIBOR-6M | J10: -0.00363
A11: EUR-EONIA | B11: OIS | C11: IR_SWAP/RATE/EUR/2D/1D/1M | D11: -0.004482 | E11: =_xll.qlSimpleQuote(SUBSTITUTE(A11&"_"&C11,"/","_"),D11,0,FALSE,$B$4) -> EUR-EONIA_IR_SWAP_RATE_EUR_2D_1D_1M#0000 | F11: =_xll.ohRangeRetrieveError(E11)
A12: EUR-EONIA | B12: OIS | C12: IR_SWAP/RATE/EUR/2D/1D/2M | D12: -0.004472 | E12: =_xll.qlSimpleQuote(SUBSTITUTE(A12&"_"&C12,"/","_"),D12,0,FALSE,$B$4) -> EUR-EONIA_IR_SWAP_RATE_EUR_2D_1D_2M#0000 | F12: =_xll.ohRangeRetrieveError(E12) | H12: The 2019-08-03 USD-LIBOR-6M fixing falls on a Saturday and is not used by the trade.
A13: EUR-EONIA | B13: OIS | C13: IR_SWAP/RATE/EUR/2D/1D/3M | D13: -0.004466 | E13: =_xll.qlSimpleQuote(SUBSTITUTE(A13&"_"&C13,"/","_"),D13,0,FALSE,$B$4) -> EUR-EONIA_IR_SWAP_RATE_EUR_2D_1D_3M#0000 | F13: =_xll.ohRangeRetrieveError(E13)
A14: EUR-EONIA | B14: OIS | C14: IR_SWAP/RATE/EUR/2D/1D/4M | D14: -0.004465 | E14: =_xll.qlSimpleQuote(SUBSTITUTE(A14&"_"&C14,"/","_"),D14,0,FALSE,$B$4) -> EUR-EONIA_IR_SWAP_RATE_EUR_2D_1D_4M#0000 | F14: =_xll.ohRangeRetrieveError(E14)
A15: EUR-EONIA | B15: OIS | C15: IR_SWAP/RATE/EUR/2D/1D/5M | D15: -0.004467 | E15: =_xll.qlSimpleQuote(SUBSTITUTE(A15&"_"&C15,"/","_"),D15,0,FALSE,$B$4) -> EUR-EONIA_IR_SWAP_RATE_EUR_2D_1D_5M#0000 | F15: =_xll.ohRangeRetrieveError(E15)
A16: EUR-EONIA | B16: OIS | C16: IR_SWAP/RATE/EUR/2D/1D/6M | D16: -0.00451 | E16: =_xll.qlSimpleQuote(SUBSTITUTE(A16&"_"&C16,"/","_"),D16,0,FALSE,$B$4) -> EUR-EONIA_IR_SWAP_RATE_EUR_2D_1D_6M#0000 | F16: =_xll.ohRangeRetrieveError(E16)
A17: EUR-EONIA | B17: OIS | C17: IR_SWAP/RATE/EUR/2D/1D/7M | D17: -0.004479 | E17: =_xll.qlSimpleQuote(SUBSTITUTE(A17&"_"&C17,"/","_"),D17,0,FALSE,$B$4) -> EUR-EONIA_IR_SWAP_RATE_EUR_2D_1D_7M#0000 | F17: =_xll.ohRangeRetrieveError(E17)
A18: EUR-EONIA | B18: OIS | C18: IR_SWAP/RATE/EUR/2D/1D/8M | D18: -0.004484 | E18: =_xll.qlSimpleQuote(SUBSTITUTE(A18&"_"&C18,"/","_"),D18,0,FALSE,$B$4) -> EUR-EONIA_IR_SWAP_RATE_EUR_2D_1D_8M#0000 | F18: =_xll.ohRangeRetrieveError(E18)
A19: EUR-EONIA | B19: OIS | C19: IR_SWAP/RATE/EUR/2D/1D/9M | D19: -0.004488 | E19: =_xll.qlSimpleQuote(SUBSTITUTE(A19&"_"&C19,"/","_"),D19,0,FALSE,$B$4) -> EUR-EONIA_IR_SWAP_RATE_EUR_2D_1D_9M#0000 | F19: =_xll.ohRangeRetrieveError(E19)
A20: EUR-EONIA | B20: OIS | C20: IR_SWAP/RATE/EUR/2D/1D/10M | D20: -0.004493 | E20: =_xll.qlSimpleQuote(SUBSTITUTE(A20&"_"&C20,"/","_"),D20,0,FALSE,$B$4) -> EUR-EONIA_IR_SWAP_RATE_EUR_2D_1D_10M#0000 | F20: =_xll.ohRangeRetrieveError(E20)
A21: EUR-EONIA | B21: OIS | C21: IR_SWAP/RATE/EUR/2D/1D/11M | D21: -0.004494 | E21: =_xll.qlSimpleQuote(SUBSTITUTE(A21&"_"&C21,"/","_"),D21,0,FALSE,$B$4) -> EUR-EONIA_IR_SWAP_RATE_EUR_2D_1D_11M#0000 | F21: =_xll.ohRangeRetrieveError(E21)
A22: EUR-EONIA | B22: OIS | C22: IR_SWAP/RATE/EUR/2D/1D/1Y | D22: -0.004495 | E22: =_xll.qlSimpleQuote(SUBSTITUTE(A22&"_"&C22,"/","_"),D22,0,FALSE,$B$4) -> EUR-EONIA_IR_SWAP_RATE_EUR_2D_1D_1Y#0000 | F22: =_xll.ohRangeRetrieveError(E22)
A23: EUR-EONIA | B23: OIS | C23: IR_SWAP/RATE/EUR/2D/1D/15M | D23: -0.004485 | E23: =_xll.qlSimpleQuote(SUBSTITUTE(A23&"_"&C23,"/","_"),D23,0,FALSE,$B$4) -> EUR-EONIA_IR_SWAP_RATE_EUR_2D_1D_15M#0000 | F23: =_xll.ohRangeRetrieveError(E23)
A24: EUR-EONIA | B24: OIS | C24: IR_SWAP/RATE/EUR/2D/1D/18M | D24: -0.00448 | E24: =_xll.qlSimpleQuote(SUBSTITUTE(A24&"_"&C24,"/","_"),D24,0,FALSE,$B$4) -> EUR-EONIA_IR_SWAP_RATE_EUR_2D_1D_18M#0000 | F24: =_xll.ohRangeRetrieveError(E24)
... A209: USD-LIBOR-6M | B209: Tenor Basis Swap | C209: BASIS_SWAP/BASIS_SPREAD/3M/6M/USD/30Y | D209: 0.0008754 | E209: =_xll.qlSimpleQuote(SUBSTITUTE(A209&"_"&C209,"/","_"),D209,0,FALSE,$B$4) -> USD-LIBOR-6M_BASIS_SWAP_BASIS_SPREAD_3M_6M_USD_30Y#0000 | F209: =_xll.ohRangeRetrieveError(E209)
A211: Quote objects | B211: =COUNTA(E7:E209) -> 203
A212: Errors | B212: =SUMPRODUCT(--(F7:F209<>"")) -> 0

Sheet Indexes
A1: Cross_Currency_Swap_rebalancing: curve handles, indexes and fixings
A2: Indexes forecast on relinkable curve handles, which are linked to the bootstrapped curves in later sheets.
A4: Curve handle | B4: Object | C4: Error
A5: USD-FedFunds | B5: =_xll.qlRelinkableHandleYieldTermStructure("H_USD-FedFunds","",FALSE,MarketData!$B$4) -> H_USD-FedFunds#0000 | C5: =_xll.ohRangeRetrieveError(B5)
A6: EUR-EONIA | B6: =_xll.qlRelinkableHandleYieldTermStructure("H_EUR-EONIA","",FALSE,MarketData!$B$4) -> H_EUR-EONIA#0000 | C6: =_xll.ohRangeRetrieveError(B6)
A7: USD-LIBOR-3M | B7: =_xll.qlRelinkableHandleYieldTermStructure("H_USD-LIBOR-3M","",FALSE,MarketData!$B$4) -> H_USD-LIBOR-3M#0000 | C7: =_xll.ohRangeRetrieveError(B7)
A8: USD-LIBOR-6M | B8: =_xll.qlRelinkableHandleYieldTermStructure("H_USD-LIBOR-6M","",FALSE,MarketData!$B$4) -> H_USD-LIBOR-6M#0000 | C8: =_xll.ohRangeRetrieveError(B8)
A9: EUR-EURIBOR-6M | B9: =_xll.qlRelinkableHandleYieldTermStructure("H_EUR-EURIBOR-6M","",FALSE,MarketData!$B$4) -> H_EUR-EURIBOR-6M#0000 | C9: =_xll.ohRangeRetrieveError(B9)
A10: EUR-EURIBOR-3M | B10: =_xll.qlRelinkableHandleYieldTermStructure("H_EUR-EURIBOR-3M","",FALSE,MarketData!$B$4) -> H_EUR-EURIBOR-3M#0000 | C10: =_xll.ohRangeRetrieveError(B10)
A11: EUR-IN-USD | B11: =_xll.qlRelinkableHandleYieldTermStructure("H_EUR-IN-USD","",FALSE,MarketData!$B$4) -> H_EUR-IN-USD#0000 | C11: =_xll.ohRangeRetrieveError(B11)
A13: Index (ORE name) | B13: Object | C13: Error | D13: Name | E13: Fixing calendar | F13: Fixing days | G13: Day counter | H13: Value date of 2019-08-01
A14: USD-FedFunds | B14: =_xll.qlOvernightIndex("USD-FedFunds","FedFunds",0,"USD","UnitedStates::FederalReserve","Actual/360",$B$5,FALSE,MarketData!$B$4) -> USD-FedFunds#0000 | C14: =_xll.ohRangeRetrieveError(B14) | D14: =_xll.qlIndexName(B14) -> FedFundsON Actual/360 | E14: =_xll.qlIndexFixingCalendar(B14) -> Federal Reserve Bankwire System | F14: =_xll.qlInterestRateIndexFixingDays(B14) -> 0 | G14: =_xll.qlInterestRateIndexDayCounter(B14) -> Actual/360 | H14: =_xll.qlInterestRateIndexValueDate(B14,DATE(2019,8,1)) -> 43678
A15: EUR-EONIA | B15: =_xll.qlEonia("EUR-EONIA",$B$6,FALSE,MarketData!$B$4) -> EUR-EONIA#0000 | C15: =_xll.ohRangeRetrieveError(B15) | D15: =_xll.qlIndexName(B15) -> EoniaON Actual/360 | E15: =_xll.qlIndexFixingCalendar(B15) -> TARGET | F15: =_xll.qlInterestRateIndexFixingDays(B15) -> 0 | G15: =_xll.qlInterestRateIndexDayCounter(B15) -> Actual/360 | H15: =_xll.qlInterestRateIndexValueDate(B15,DATE(2019,8,1)) -> 43678
A16: USD-LIBOR-3M | B16: =_xll.qlLibor("USD-LIBOR-3M","USD","3M",$B$7,FALSE,MarketData!$B$4) -> USD-LIBOR-3M#0000 | C16: =_xll.ohRangeRetrieveError(B16) | D16: =_xll.qlIndexName(B16) -> USDLibor3M Actual/360 | E16: =_xll.qlIndexFixingCalendar(B16) -> London stock exchange | F16: =_xll.qlInterestRateIndexFixingDays(B16) -> 2 | G16: =_xll.qlInterestRateIndexDayCounter(B16) -> Actual/360 | H16: =_xll.qlInterestRateIndexValueDate(B16,DATE(2019,8,1)) -> 43682
A17: USD-LIBOR-6M | B17: =_xll.qlLibor("USD-LIBOR-6M","USD","6M",$B$8,FALSE,MarketData!$B$4) -> USD-LIBOR-6M#0000 | C17: =_xll.ohRangeRetrieveError(B17) | D17: =_xll.qlIndexName(B17) -> USDLibor6M Actual/360 | E17: =_xll.qlIndexFixingCalendar(B17) -> London stock exchange | F17: =_xll.qlInterestRateIndexFixingDays(B17) -> 2 | G17: =_xll.qlInterestRateIndexDayCounter(B17) -> Actual/360 | H17: =_xll.qlInterestRateIndexValueDate(B17,DATE(2019,8,1)) -> 43682
A18: EUR-EURIBOR-3M | B18: =_xll.qlEuribor("EUR-EURIBOR-3M","3M",$B$10,FALSE,MarketData!$B$4) -> EUR-EURIBOR-3M#0000 | C18: =_xll.ohRangeRetrieveError(B18) | D18: =_xll.qlIndexName(B18) -> Euribor3M Actual/360 | E18: =_xll.qlIndexFixingCalendar(B18) -> TARGET | F18: =_xll.qlInterestRateIndexFixingDays(B18) -> 2 | G18: =_xll.qlInterestRateIndexDayCounter(B18) -> Actual/360 | H18: =_xll.qlInterestRateIndexValueDate(B18,DATE(2019,8,1)) -> 43682
A19: EUR-EURIBOR-6M | B19: =_xll.qlEuribor("EUR-EURIBOR-6M","6M",$B$9,FALSE,MarketData!$B$4) -> EUR-EURIBOR-6M#0000 | C19: =_xll.ohRangeRetrieveError(B19) | D19: =_xll.qlIndexName(B19) -> Euribor6M Actual/360 | E19: =_xll.qlIndexFixingCalendar(B19) -> TARGET | F19: =_xll.qlInterestRateIndexFixingDays(B19) -> 2 | G19: =_xll.qlInterestRateIndexDayCounter(B19) -> Actual/360 | H19: =_xll.qlInterestRateIndexValueDate(B19,DATE(2019,8,1)) -> 43682
A21: FX index | B21: Object | C21: Error | D21: Name | E21: Source | F21: Target
A22: FX-ECB-EUR-USD | B22: =_xll.qlFxIndex("FX-ECB-EUR-USD","ECB",2,"EUR","USD","TARGET",MarketData!$E$93,$B$11,$B$5,TRUE,FALSE,MarketData!$B$4) -> FX-ECB-EUR-USD#0000 | C22: =_xll.ohRangeRetrieveError(B22) | D22: =_xll.qlIndexName(B22) -> ECB EUR/USD | E22: =_xll.qlFxIndexSourceCurrency(B22) -> EUR | F22: =_xll.qlFxIndexTargetCurrency(B22) -> USD | H22: Inverse spot quote | I22: =_xll.qlSimpleQuote("FX_RATE_USD_EUR",1/MarketData!$D$93,0,FALSE,MarketData!$B$4) -> FX_RATE_USD_EUR#0000
A23: FX-ECB-USD-EUR (inverse, reads EUR/USD fixings) | B23: =_xll.qlFxIndex("FX-ECB-USD-EUR","ECB",2,"USD","EUR","TARGET",I22,$B$5,$B$11,TRUE,FALSE,MarketData!$B$4) -> FX-ECB-USD-EUR#0000 | C23: =_xll.ohRangeRetrieveError(B23) | D23: =_xll.qlIndexName(B23) -> ECB USD/EUR | E23: =_xll.qlFxIndexSourceCurrency(B23) -> USD | F23: =_xll.qlFxIndexTargetCurrency(B23) -> EUR | H23: USD/EUR fixing 2019-08-01 | I23: =_xll.qlIndexFixing(B23,DATE(2019,8,1),FALSE,B31) -> 0.90604331 | J23: =I23-1/1.1037 -> 0
A25: Fixing date | B25: Index | C25: Value | D25: Add fixing | E25: Error | F25: Read back | G25: Difference
A26: =MarketData!H7 -> 43678 | B26: =MarketData!I7 -> FX-ECB-EUR-USD | C26: =MarketData!J7 -> 1.1037 | D26: =IF(WEEKDAY(A26,2)>5,"skipped (weekend)",_xll.qlIndexAddFixings(INDEX($B$14:$B$22,MATCH(B26,$A$14:$A$22,0)),A26,C26,TRUE)) -> TRUE | E26: =IF(WEEKDAY(A26,2)>5,"",_xll.ohRangeRetrieveError(D26)) | F26: =IF(WEEKDAY(A26,2)>5,"",_xll.qlIndexFixing(INDEX($B$14:$B$22,MATCH(B26,$A$14:$A$22,0)),A26,FALSE,D26)) -> 1.1037 | G26: =IF(WEEKDAY(A26,2)>5,"",F26-C26) -> 0
A27: =MarketData!H8 -> 43680 | B27: =MarketData!I8 -> USD-LIBOR-6M | C27: =MarketData!J8 -> 0.0222688 | D27: =IF(WEEKDAY(A27,2)>5,"skipped (weekend)",_xll.qlIndexAddFixings(INDEX($B$14:$B$22,MATCH(B27,$A$14:$A$22,0)),A27,C27,TRUE)) -> skipped (weekend) | E27: =IF(WEEKDAY(A27,2)>5,"",_xll.ohRangeRetrieveError(D27)) | F27: =IF(WEEKDAY(A27,2)>5,"",_xll.qlIndexFixing(INDEX($B$14:$B$22,MATCH(B27,$A$14:$A$22,0)),A27,FALSE,D27)) | G27: =IF(WEEKDAY(A27,2)>5,"",F27-C27)
A28: =MarketData!H9 -> 43678 | B28: =MarketData!I9 -> USD-LIBOR-6M | C28: =MarketData!J9 -> 0.0222688 | D28: =IF(WEEKDAY(A28,2)>5,"skipped (weekend)",_xll.qlIndexAddFixings(INDEX($B$14:$B$22,MATCH(B28,$A$14:$A$22,0)),A28,C28,TRUE)) -> TRUE | E28: =IF(WEEKDAY(A28,2)>5,"",_xll.ohRangeRetrieveError(D28)) | F28: =IF(WEEKDAY(A28,2)>5,"",_xll.qlIndexFixing(INDEX($B$14:$B$22,MATCH(B28,$A$14:$A$22,0)),A28,FALSE,D28)) -> 0.0222688 | G28: =IF(WEEKDAY(A28,2)>5,"",F28-C28) -> 0
A29: =MarketData!H10 -> 43678 | B29: =MarketData!I10 -> EUR-EURIBOR-6M | C29: =MarketData!J10 -> -0.00363 | D29: =IF(WEEKDAY(A29,2)>5,"skipped (weekend)",_xll.qlIndexAddFixings(INDEX($B$14:$B$22,MATCH(B29,$A$14:$A$22,0)),A29,C29,TRUE)) -> TRUE | E29: =IF(WEEKDAY(A29,2)>5,"",_xll.ohRangeRetrieveError(D29)) | F29: =IF(WEEKDAY(A29,2)>5,"",_xll.qlIndexFixing(INDEX($B$14:$B$22,MATCH(B29,$A$14:$A$22,0)),A29,FALSE,D29)) -> -0.00363 | G29: =IF(WEEKDAY(A29,2)>5,"",F29-C29) -> 0
A31: Trigger (indexes and fixings ready) | B31: =AND(COUNTIF(D26:D29,TRUE)=3,SUMPRODUCT(--(C14:C20<>""))=0,C22="",C23="") -> TRUE

Sheet USD-FedFunds
A1: USD-FedFunds: Discount/LogLinear, A365, extrapolation; deposit 1D, OIS 1W-1Y (USD-OIS), average OIS 2Y-30Y (USD-AVERAGE-OIS)
A2: Average OIS: FedFunds compounded 3M + spread vs 6M 30/360 fixed (US calendar, MF), spot lag 2D, rate cutoff 2. Quote = 3M LIBOR swap rate, spread = 3M/1D basis.
A4: Segment | B4: Quote | C4: Rate | D4: Spread | E4: Helper | F4: Error
A5: Deposit | B5: MM/RATE/USD/0D/1D | C5: =MarketData!$E$126 -> USD-FedFunds_MM_RATE_USD_0D_1D#0000 | E5: =_xll.qlDepositRateHelper2("FF_DEP_1D",C5,"1D",0,"UnitedStates::FederalReserve","Following",FALSE,"Actual/360",FALSE,Indexes!$B$31) -> FF_DEP_1D#0000 | F5: =_xll.ohRangeRetrieveError(E5)
A6: OIS | B6: IR_SWAP/RATE/USD/2D/1D/1W | C6: =MarketData!$E$127 -> USD-FedFunds_IR_SWAP_RATE_USD_2D_1D_1W#0000 | E6: =_xll.qlQxOISRateHelper("FF_OIS_1W",2,"1W",C6,Indexes!$B$14,"Actual/360","UnitedStates::FederalReserve",2,"Annual","Following","Following","Backward","",TRUE,FALSE,FALSE,Indexes!$B$31) -> FF_OIS_1W#0000 | F6: =_xll.ohRangeRetrieveError(E6)
A7: OIS | B7: IR_SWAP/RATE/USD/2D/1D/2W | C7: =MarketData!$E$128 -> USD-FedFunds_IR_SWAP_RATE_USD_2D_1D_2W#0000 | E7: =_xll.qlQxOISRateHelper("FF_OIS_2W",2,"2W",C7,Indexes!$B$14,"Actual/360","UnitedStates::FederalReserve",2,"Annual","Following","Following","Backward","",TRUE,FALSE,FALSE,Indexes!$B$31) -> FF_OIS_2W#0000 | F7: =_xll.ohRangeRetrieveError(E7)
A8: OIS | B8: IR_SWAP/RATE/USD/2D/1D/3W | C8: =MarketData!$E$129 -> USD-FedFunds_IR_SWAP_RATE_USD_2D_1D_3W#0000 | E8: =_xll.qlQxOISRateHelper("FF_OIS_3W",2,"3W",C8,Indexes!$B$14,"Actual/360","UnitedStates::FederalReserve",2,"Annual","Following","Following","Backward","",TRUE,FALSE,FALSE,Indexes!$B$31) -> FF_OIS_3W#0000 | F8: =_xll.ohRangeRetrieveError(E8)
A9: OIS | B9: IR_SWAP/RATE/USD/2D/1D/1M | C9: =MarketData!$E$130 -> USD-FedFunds_IR_SWAP_RATE_USD_2D_1D_1M#0000 | E9: =_xll.qlQxOISRateHelper("FF_OIS_1M",2,"1M",C9,Indexes!$B$14,"Actual/360","UnitedStates::FederalReserve",2,"Annual","Following","Following","Backward","",TRUE,FALSE,FALSE,Indexes!$B$31) -> FF_OIS_1M#0000 | F9: =_xll.ohRangeRetrieveError(E9)
A10: OIS | B10: IR_SWAP/RATE/USD/2D/1D/2M | C10: =MarketData!$E$131 -> USD-FedFunds_IR_SWAP_RATE_USD_2D_1D_2M#0000 | E10: =_xll.qlQxOISRateHelper("FF_OIS_2M",2,"2M",C10,Indexes!$B$14,"Actual/360","UnitedStates::FederalReserve",2,"Annual","Following","Following","Backward","",TRUE,FALSE,FALSE,Indexes!$B$31) -> FF_OIS_2M#0000 | F10: =_xll.ohRangeRetrieveError(E10)
A11: OIS | B11: IR_SWAP/RATE/USD/2D/1D/3M | C11: =MarketData!$E$132 -> USD-FedFunds_IR_SWAP_RATE_USD_2D_1D_3M#0000 | E11: =_xll.qlQxOISRateHelper("FF_OIS_3M",2,"3M",C11,Indexes!$B$14,"Actual/360","UnitedStates::FederalReserve",2,"Annual","Following","Following","Backward","",TRUE,FALSE,FALSE,Indexes!$B$31) -> FF_OIS_3M#0000 | F11: =_xll.ohRangeRetrieveError(E11)
A12: OIS | B12: IR_SWAP/RATE/USD/2D/1D/4M | C12: =MarketData!$E$133 -> USD-FedFunds_IR_SWAP_RATE_USD_2D_1D_4M#0000 | E12: =_xll.qlQxOISRateHelper("FF_OIS_4M",2,"4M",C12,Indexes!$B$14,"Actual/360","UnitedStates::FederalReserve",2,"Annual","Following","Following","Backward","",TRUE,FALSE,FALSE,Indexes!$B$31) -> FF_OIS_4M#0000 | F12: =_xll.ohRangeRetrieveError(E12)
A13: OIS | B13: IR_SWAP/RATE/USD/2D/1D/5M | C13: =MarketData!$E$134 -> USD-FedFunds_IR_SWAP_RATE_USD_2D_1D_5M#0000 | E13: =_xll.qlQxOISRateHelper("FF_OIS_5M",2,"5M",C13,Indexes!$B$14,"Actual/360","UnitedStates::FederalReserve",2,"Annual","Following","Following","Backward","",TRUE,FALSE,FALSE,Indexes!$B$31) -> FF_OIS_5M#0000 | F13: =_xll.ohRangeRetrieveError(E13)
A14: OIS | B14: IR_SWAP/RATE/USD/2D/1D/6M | C14: =MarketData!$E$135 -> USD-FedFunds_IR_SWAP_RATE_USD_2D_1D_6M#0000 | E14: =_xll.qlQxOISRateHelper("FF_OIS_6M",2,"6M",C14,Indexes!$B$14,"Actual/360","UnitedStates::FederalReserve",2,"Annual","Following","Following","Backward","",TRUE,FALSE,FALSE,Indexes!$B$31) -> FF_OIS_6M#0000 | F14: =_xll.ohRangeRetrieveError(E14)
A15: OIS | B15: IR_SWAP/RATE/USD/2D/1D/7M | C15: =MarketData!$E$136 -> USD-FedFunds_IR_SWAP_RATE_USD_2D_1D_7M#0000 | E15: =_xll.qlQxOISRateHelper("FF_OIS_7M",2,"7M",C15,Indexes!$B$14,"Actual/360","UnitedStates::FederalReserve",2,"Annual","Following","Following","Backward","",TRUE,FALSE,FALSE,Indexes!$B$31) -> FF_OIS_7M#0000 | F15: =_xll.ohRangeRetrieveError(E15)
A16: OIS | B16: IR_SWAP/RATE/USD/2D/1D/8M | C16: =MarketData!$E$137 -> USD-FedFunds_IR_SWAP_RATE_USD_2D_1D_8M#0000 | E16: =_xll.qlQxOISRateHelper("FF_OIS_8M",2,"8M",C16,Indexes!$B$14,"Actual/360","UnitedStates::FederalReserve",2,"Annual","Following","Following","Backward","",TRUE,FALSE,FALSE,Indexes!$B$31) -> FF_OIS_8M#0000 | F16: =_xll.ohRangeRetrieveError(E16)
A17: OIS | B17: IR_SWAP/RATE/USD/2D/1D/9M | C17: =MarketData!$E$138 -> USD-FedFunds_IR_SWAP_RATE_USD_2D_1D_9M#0000 | E17: =_xll.qlQxOISRateHelper("FF_OIS_9M",2,"9M",C17,Indexes!$B$14,"Actual/360","UnitedStates::FederalReserve",2,"Annual","Following","Following","Backward","",TRUE,FALSE,FALSE,Indexes!$B$31) -> FF_OIS_9M#0000 | F17: =_xll.ohRangeRetrieveError(E17)
A18: OIS | B18: IR_SWAP/RATE/USD/2D/1D/10M | C18: =MarketData!$E$139 -> USD-FedFunds_IR_SWAP_RATE_USD_2D_1D_10M#0000 | E18: =_xll.qlQxOISRateHelper("FF_OIS_10M",2,"10M",C18,Indexes!$B$14,"Actual/360","UnitedStates::FederalReserve",2,"Annual","Following","Following","Backward","",TRUE,FALSE,FALSE,Indexes!$B$31) -> FF_OIS_10M#0000 | F18: =_xll.ohRangeRetrieveError(E18)
A19: OIS | B19: IR_SWAP/RATE/USD/2D/1D/11M | C19: =MarketData!$E$140 -> USD-FedFunds_IR_SWAP_RATE_USD_2D_1D_11M#0000 | E19: =_xll.qlQxOISRateHelper("FF_OIS_11M",2,"11M",C19,Indexes!$B$14,"Actual/360","UnitedStates::FederalReserve",2,"Annual","Following","Following","Backward","",TRUE,FALSE,FALSE,Indexes!$B$31) -> FF_OIS_11M#0000 | F19: =_xll.ohRangeRetrieveError(E19)
A20: OIS | B20: IR_SWAP/RATE/USD/2D/1D/1Y | C20: =MarketData!$E$141 -> USD-FedFunds_IR_SWAP_RATE_USD_2D_1D_1Y#0000 | E20: =_xll.qlQxOISRateHelper("FF_OIS_1Y",2,"1Y",C20,Indexes!$B$14,"Actual/360","UnitedStates::FederalReserve",2,"Annual","Following","Following","Backward","",TRUE,FALSE,FALSE,Indexes!$B$31) -> FF_OIS_1Y#0000 | F20: =_xll.ohRangeRetrieveError(E20)
A21: Average OIS | B21: IR_SWAP/RATE/USD/2D/3M/2Y + BASIS_SWAP/BASIS_SPREAD/3M/1D/USD/2Y | C21: =MarketData!$E$143 -> USD-FedFunds_IR_SWAP_RATE_USD_2D_3M_2Y#0000 | D21: =MarketData!$E$142 -> USD-FedFunds_BASIS_SWAP_BASIS_SPREAD_3M_1D_USD_2Y#0000 | E21: =_xll.qlAverageOISRateHelper("FF_AVGOIS_2Y",C21,"2D","2Y","6M","30/360","UnitedStates::Settlement","Modified Following","Modified Following",Indexes!$B$14,"3M",D21,2,"",FALSE,FALSE,Indexes!$B$31) -> FF_AVGOIS_2Y#0000 | F21: =_xll.ohRangeRetrieveError(E21)
A22: Average OIS | B22: IR_SWAP/RATE/USD/2D/3M/3Y + BASIS_SWAP/BASIS_SPREAD/3M/1D/USD/3Y | C22: =MarketData!$E$145 -> USD-FedFunds_IR_SWAP_RATE_USD_2D_3M_3Y#0000 | D22: =MarketData!$E$144 -> USD-FedFunds_BASIS_SWAP_BASIS_SPREAD_3M_1D_USD_3Y#0000 | E22: =_xll.qlAverageOISRateHelper("FF_AVGOIS_3Y",C22,"2D","3Y","6M","30/360","UnitedStates::Settlement","Modified Following","Modified Following",Indexes!$B$14,"3M",D22,2,"",FALSE,FALSE,Indexes!$B$31) -> FF_AVGOIS_3Y#0000 | F22: =_xll.ohRangeRetrieveError(E22)
A23: Average OIS | B23: IR_SWAP/RATE/USD/2D/3M/4Y + BASIS_SWAP/BASIS_SPREAD/3M/1D/USD/4Y | C23: =MarketData!$E$147 -> USD-FedFunds_IR_SWAP_RATE_USD_2D_3M_4Y#0000 | D23: =MarketData!$E$146 -> USD-FedFunds_BASIS_SWAP_BASIS_SPREAD_3M_1D_USD_4Y#0000 | E23: =_xll.qlAverageOISRateHelper("FF_AVGOIS_4Y",C23,"2D","4Y","6M","30/360","UnitedStates::Settlement","Modified Following","Modified Following",Indexes!$B$14,"3M",D23,2,"",FALSE,FALSE,Indexes!$B$31) -> FF_AVGOIS_4Y#0000 | F23: =_xll.ohRangeRetrieveError(E23)
A24: Average OIS | B24: IR_SWAP/RATE/USD/2D/3M/5Y + BASIS_SWAP/BASIS_SPREAD/3M/1D/USD/5Y | C24: =MarketData!$E$149 -> USD-FedFunds_IR_SWAP_RATE_USD_2D_3M_5Y#0000 | D24: =MarketData!$E$148 -> USD-FedFunds_BASIS_SWAP_BASIS_SPREAD_3M_1D_USD_5Y#0000 | E24: =_xll.qlAverageOISRateHelper("FF_AVGOIS_5Y",C24,"2D","5Y","6M","30/360","UnitedStates::Settlement","Modified Following","Modified Following",Indexes!$B$14,"3M",D24,2,"",FALSE,FALSE,Indexes!$B$31) -> FF_AVGOIS_5Y#0000 | F24: =_xll.ohRangeRetrieveError(E24)
A25: Average OIS | B25: IR_SWAP/RATE/USD/2D/3M/7Y + BASIS_SWAP/BASIS_SPREAD/3M/1D/USD/7Y | C25: =MarketData!$E$151 -> USD-FedFunds_IR_SWAP_RATE_USD_2D_3M_7Y#0000 | D25: =MarketData!$E$150 -> USD-FedFunds_BASIS_SWAP_BASIS_SPREAD_3M_1D_USD_7Y#0000 | E25: =_xll.qlAverageOISRateHelper("FF_AVGOIS_7Y",C25,"2D","7Y","6M","30/360","UnitedStates::Settlement","Modified Following","Modified Following",Indexes!$B$14,"3M",D25,2,"",FALSE,FALSE,Indexes!$B$31) -> FF_AVGOIS_7Y#0000 | F25: =_xll.ohRangeRetrieveError(E25)
A26: Average OIS | B26: IR_SWAP/RATE/USD/2D/3M/10Y + BASIS_SWAP/BASIS_SPREAD/3M/1D/USD/10Y | C26: =MarketData!$E$153 -> USD-FedFunds_IR_SWAP_RATE_USD_2D_3M_10Y#0000 | D26: =MarketData!$E$152 -> USD-FedFunds_BASIS_SWAP_BASIS_SPREAD_3M_1D_USD_10Y#0000 | E26: =_xll.qlAverageOISRateHelper("FF_AVGOIS_10Y",C26,"2D","10Y","6M","30/360","UnitedStates::Settlement","Modified Following","Modified Following",Indexes!$B$14,"3M",D26,2,"",FALSE,FALSE,Indexes!$B$31) -> FF_AVGOIS_10Y#0000 | F26: =_xll.ohRangeRetrieveError(E26)
A27: Average OIS | B27: IR_SWAP/RATE/USD/2D/3M/15Y + BASIS_SWAP/BASIS_SPREAD/3M/1D/USD/15Y | C27: =MarketData!$E$155 -> USD-FedFunds_IR_SWAP_RATE_USD_2D_3M_15Y#0000 | D27: =MarketData!$E$154 -> USD-FedFunds_BASIS_SWAP_BASIS_SPREAD_3M_1D_USD_15Y#0000 | E27: =_xll.qlAverageOISRateHelper("FF_AVGOIS_15Y",C27,"2D","15Y","6M","30/360","UnitedStates::Settlement","Modified Following","Modified Following",Indexes!$B$14,"3M",D27,2,"",FALSE,FALSE,Indexes!$B$31) -> FF_AVGOIS_15Y#0000 | F27: =_xll.ohRangeRetrieveError(E27)
A28: Average OIS | B28: IR_SWAP/RATE/USD/2D/3M/20Y + BASIS_SWAP/BASIS_SPREAD/3M/1D/USD/20Y | C28: =MarketData!$E$157 -> USD-FedFunds_IR_SWAP_RATE_USD_2D_3M_20Y#0000 | D28: =MarketData!$E$156 -> USD-FedFunds_BASIS_SWAP_BASIS_SPREAD_3M_1D_USD_20Y#0000 | E28: =_xll.qlAverageOISRateHelper("FF_AVGOIS_20Y",C28,"2D","20Y","6M","30/360","UnitedStates::Settlement","Modified Following","Modified Following",Indexes!$B$14,"3M",D28,2,"",FALSE,FALSE,Indexes!$B$31) -> FF_AVGOIS_20Y#0000 | F28: =_xll.ohRangeRetrieveError(E28)
A29: Average OIS | B29: IR_SWAP/RATE/USD/2D/3M/30Y + BASIS_SWAP/BASIS_SPREAD/3M/1D/USD/30Y | C29: =MarketData!$E$159 -> USD-FedFunds_IR_SWAP_RATE_USD_2D_3M_30Y#0000 | D29: =MarketData!$E$158 -> USD-FedFunds_BASIS_SWAP_BASIS_SPREAD_3M_1D_USD_30Y#0000 | E29: =_xll.qlAverageOISRateHelper("FF_AVGOIS_30Y",C29,"2D","30Y","6M","30/360","UnitedStates::Settlement","Modified Following","Modified Following",Indexes!$B$14,"3M",D29,2,"",FALSE,FALSE,Indexes!$B$31) -> FF_AVGOIS_30Y#0000 | F29: =_xll.ohRangeRetrieveError(E29)
A31: Curve | B31: =_xll.qlPiecewiseYieldCurve("C_USD-FedFunds",0,"UnitedStates::FederalReserve",E5:E29,"Actual/365 (Fixed)",,,"Discount","LogLinear",FALSE,Indexes!$B$31) -> C_USD-FedFunds#0000 | C31: =_xll.ohRangeRetrieveError(B31) | D31: =_xll.qlExtrapolatorEnableExtrapolation(B31,TRUE) -> TRUE
A32: Link handle H_USD-FedFunds | B32: =_xll.qlRelinkableHandleLinkTo(Indexes!$B$5,B31,D31) -> TRUE | C32: =_xll.ohRangeRetrieveError(B32)
A34: Date | B34: ORE discount factor | C34: Excel discount factor | D34: Difference | E34: Rel. difference
A35: =DATE(2019,12,31) -> 43830 | B35: 0.99995695 | C35: =_xll.qlYieldTSDiscount($B$31,A35,TRUE,$B$32) -> 0.99995695 | D35: =C35-B35 -> 0 | E35: =D35/B35 -> 0
A36: =DATE(2020,1,13) -> 43843 | B36: 0.99939864 | C36: =_xll.qlYieldTSDiscount($B$31,A36,TRUE,$B$32) -> 0.99939864 | D36: =C36-B36 -> 0 | E36: =D36/B36 -> 0
A37: =DATE(2020,1,21) -> 43851 | B37: 0.99905298 | C37: =_xll.qlYieldTSDiscount($B$31,A37,TRUE,$B$32) -> 0.99905298 | D37: =C37-B37 -> 0 | E37: =D37/B37 -> 0
A38: =DATE(2020,1,27) -> 43857 | B38: 0.99879972 | C38: =_xll.qlYieldTSDiscount($B$31,A38,TRUE,$B$32) -> 0.99879972 | D38: =C38-B38 -> 0 | E38: =D38/B38 -> 0
A39: =DATE(2020,2,5) -> 43866 | B39: 0.9984045 | C39: =_xll.qlYieldTSDiscount($B$31,A39,TRUE,$B$32) -> 0.9984045 | D39: =C39-B39 -> 0 | E39: =D39/B39 -> 0
A40: =DATE(2020,3,4) -> 43894 | B40: 0.99719027 | C40: =_xll.qlYieldTSDiscount($B$31,A40,TRUE,$B$32) -> 0.99719027 | D40: =C40-B40 -> 0 | E40: =D40/B40 -> 0
A41: =DATE(2020,4,6) -> 43927 | B41: 0.9957676 | C41: =_xll.qlYieldTSDiscount($B$31,A41,TRUE,$B$32) -> 0.9957676 | D41: =C41-B41 -> 0 | E41: =D41/B41 -> 0
A42: =DATE(2020,5,6) -> 43957 | B42: 0.99448666 | C42: =_xll.qlYieldTSDiscount($B$31,A42,TRUE,$B$32) -> 0.99448666 | D42: =C42-B42 -> 0 | E42: =D42/B42 -> 0
A43: =DATE(2020,6,4) -> 43986 | B43: 0.99325778 | C43: =_xll.qlYieldTSDiscount($B$31,A43,TRUE,$B$32) -> 0.99325778 | D43: =C43-B43 -> 0 | E43: =D43/B43 -> 0
A44: =DATE(2020,7,6) -> 44018 | B44: 0.99192088 | C44: =_xll.qlYieldTSDiscount($B$31,A44,TRUE,$B$32) -> 0.99192088 | D44: =C44-B44 -> 0 | E44: =D44/B44 -> 0
A45: =DATE(2020,8,5) -> 44048 | B45: 0.99068271 | C45: =_xll.qlYieldTSDiscount($B$31,A45,TRUE,$B$32) -> 0.99068271 | D45: =C45-B45 -> 0 | E45: =D45/B45 -> 0
A46: =DATE(2020,9,4) -> 44078 | B46: 0.98946741 | C46: =_xll.qlYieldTSDiscount($B$31,A46,TRUE,$B$32) -> 0.98946741 | D46: =C46-B46 -> 0 | E46: =D46/B46 -> 0
A47: =DATE(2020,10,6) -> 44110 | B47: 0.98818584 | C47: =_xll.qlYieldTSDiscount($B$31,A47,TRUE,$B$32) -> 0.98818584 | D47: =C47-B47 -> 0 | E47: =D47/B47 -> 0
A48: =DATE(2020,11,4) -> 44139 | B48: 0.98704444 | C48: =_xll.qlYieldTSDiscount($B$31,A48,TRUE,$B$32) -> 0.98704444 | D48: =C48-B48 -> 0 | E48: =D48/B48 -> 0
A49: =DATE(2020,12,4) -> 44169 | B49: 0.98588748 | C49: =_xll.qlYieldTSDiscount($B$31,A49,TRUE,$B$32) -> 0.98588748 | D49: =C49-B49 -> 0 | E49: =D49/B49 -> 0
A50: =DATE(2021,1,6) -> 44202 | B50: 0.98462537 | C50: =_xll.qlYieldTSDiscount($B$31,A50,TRUE,$B$32) -> 0.98462537 | D50: =C50-B50 -> 0 | E50: =D50/B50 -> 0
A51: =DATE(2022,1,3) -> 44564 | B51: 0.9714391 | C51: =_xll.qlYieldTSDiscount($B$31,A51,TRUE,$B$32) -> 0.9714391 | D51: =C51-B51 -> 0 | E51: =D51/B51 -> 0
A52: =DATE(2023,1,3) -> 44929 | B52: 0.95786833 | C52: =_xll.qlYieldTSDiscount($B$31,A52,TRUE,$B$32) -> 0.95786833 | D52: =C52-B52 -> 0 | E52: =D52/B52 -> 0
A53: =DATE(2024,1,2) -> 45293 | B53: 0.9437763 | C53: =_xll.qlYieldTSDiscount($B$31,A53,TRUE,$B$32) -> 0.9437763 | D53: =C53-B53 -> 0 | E53: =D53/B53 -> 0
A54: =DATE(2025,1,2) -> 45659 | B54: 0.92968345 | C54: =_xll.qlYieldTSDiscount($B$31,A54,TRUE,$B$32) -> 0.92968345 | D54: =C54-B54 -> 0 | E54: =D54/B54 -> 0
A55: =DATE(2027,1,4) -> 46391 | B55: 0.89886529 | C55: =_xll.qlYieldTSDiscount($B$31,A55,TRUE,$B$32) -> 0.89886529 | D55: =C55-B55 -> 0 | E55: =D55/B55 -> 0
A56: =DATE(2030,1,2) -> 47485 | B56: 0.85035627 | C56: =_xll.qlYieldTSDiscount($B$31,A56,TRUE,$B$32) -> 0.85035627 | D56: =C56-B56 -> 0 | E56: =D56/B56 -> 0
A57: =DATE(2035,1,2) -> 49311 | B57: 0.77207516 | C57: =_xll.qlYieldTSDiscount($B$31,A57,TRUE,$B$32) -> 0.77207516 | D57: =C57-B57 -> -2.6645353e-15 | E57: =D57/B57 -> -3.4511345e-15
A58: =DATE(2040,1,3) -> 51138 | B58: 0.69976193 | C58: =_xll.qlYieldTSDiscount($B$31,A58,TRUE,$B$32) -> 0.69976193 | D58: =C58-B58 -> 3.3306691e-15 | E58: =D58/B58 -> 4.7597175e-15
A59: =DATE(2050,1,3) -> 54791 | B59: 0.58161507 | C59: =_xll.qlYieldTSDiscount($B$31,A59,TRUE,$B$32) -> 0.58161507 | D59: =C59-B59 -> 5.5511151e-15 | E59: =D59/B59 -> 9.544311e-15
A61: Max abs difference | D61: =MAX(ABS(MIN(D35:D59)),ABS(MAX(D35:D59))) -> 5.5511151e-15

Sheet EUR-EONIA
A1: EUR-EONIA: Discount/LogLinear, A365, extrapolation; deposit 1D (EUR-ON-DEPOSIT), OIS 1W-30Y (EUR-OIS)
A2: EUR-OIS: spot lag 2, fixed A360, TARGET, payment lag 1, Annual, Following/Following, Backward, EOM false.
A4: Segment | B4: Quote | C4: Rate | E4: Helper | F4: Error
A5: Deposit | B5: MM/RATE/EUR/0D/1D | C5: =MarketData!$E$7 -> EUR-EONIA_MM_RATE_EUR_0D_1D#0000 | E5: =_xll.qlDepositRateHelper2("EONIA_DEP_1D",C5,"1D",0,"TARGET","Following",FALSE,"Actual/360",FALSE,Indexes!$B$31) -> EONIA_DEP_1D#0000 | F5: =_xll.ohRangeRetrieveError(E5)
A6: OIS | B6: IR_SWAP/RATE/EUR/2D/1D/1W | C6: =MarketData!$E$8 -> EUR-EONIA_IR_SWAP_RATE_EUR_2D_1D_1W#0000 | E6: =_xll.qlQxOISRateHelper("EONIA_OIS_1W",2,"1W",C6,Indexes!$B$15,"Actual/360","TARGET",1,"Annual","Following","Following","Backward","",TRUE,FALSE,FALSE,Indexes!$B$31) -> EONIA_OIS_1W#0000 | F6: =_xll.ohRangeRetrieveError(E6)
A7: OIS | B7: IR_SWAP/RATE/EUR/2D/1D/2W | C7: =MarketData!$E$9 -> EUR-EONIA_IR_SWAP_RATE_EUR_2D_1D_2W#0000 | E7: =_xll.qlQxOISRateHelper("EONIA_OIS_2W",2,"2W",C7,Indexes!$B$15,"Actual/360","TARGET",1,"Annual","Following","Following","Backward","",TRUE,FALSE,FALSE,Indexes!$B$31) -> EONIA_OIS_2W#0000 | F7: =_xll.ohRangeRetrieveError(E7)
A8: OIS | B8: IR_SWAP/RATE/EUR/2D/1D/3W | C8: =MarketData!$E$10 -> EUR-EONIA_IR_SWAP_RATE_EUR_2D_1D_3W#0000 | E8: =_xll.qlQxOISRateHelper("EONIA_OIS_3W",2,"3W",C8,Indexes!$B$15,"Actual/360","TARGET",1,"Annual","Following","Following","Backward","",TRUE,FALSE,FALSE,Indexes!$B$31) -> EONIA_OIS_3W#0000 | F8: =_xll.ohRangeRetrieveError(E8)
A9: OIS | B9: IR_SWAP/RATE/EUR/2D/1D/1M | C9: =MarketData!$E$11 -> EUR-EONIA_IR_SWAP_RATE_EUR_2D_1D_1M#0000 | E9: =_xll.qlQxOISRateHelper("EONIA_OIS_1M",2,"1M",C9,Indexes!$B$15,"Actual/360","TARGET",1,"Annual","Following","Following","Backward","",TRUE,FALSE,FALSE,Indexes!$B$31) -> EONIA_OIS_1M#0000 | F9: =_xll.ohRangeRetrieveError(E9)
A10: OIS | B10: IR_SWAP/RATE/EUR/2D/1D/2M | C10: =MarketData!$E$12 -> EUR-EONIA_IR_SWAP_RATE_EUR_2D_1D_2M#0000 | E10: =_xll.qlQxOISRateHelper("EONIA_OIS_2M",2,"2M",C10,Indexes!$B$15,"Actual/360","TARGET",1,"Annual","Following","Following","Backward","",TRUE,FALSE,FALSE,Indexes!$B$31) -> EONIA_OIS_2M#0000 | F10: =_xll.ohRangeRetrieveError(E10)
A11: OIS | B11: IR_SWAP/RATE/EUR/2D/1D/3M | C11: =MarketData!$E$13 -> EUR-EONIA_IR_SWAP_RATE_EUR_2D_1D_3M#0000 | E11: =_xll.qlQxOISRateHelper("EONIA_OIS_3M",2,"3M",C11,Indexes!$B$15,"Actual/360","TARGET",1,"Annual","Following","Following","Backward","",TRUE,FALSE,FALSE,Indexes!$B$31) -> EONIA_OIS_3M#0000 | F11: =_xll.ohRangeRetrieveError(E11)
A12: OIS | B12: IR_SWAP/RATE/EUR/2D/1D/4M | C12: =MarketData!$E$14 -> EUR-EONIA_IR_SWAP_RATE_EUR_2D_1D_4M#0000 | E12: =_xll.qlQxOISRateHelper("EONIA_OIS_4M",2,"4M",C12,Indexes!$B$15,"Actual/360","TARGET",1,"Annual","Following","Following","Backward","",TRUE,FALSE,FALSE,Indexes!$B$31) -> EONIA_OIS_4M#0000 | F12: =_xll.ohRangeRetrieveError(E12)
A13: OIS | B13: IR_SWAP/RATE/EUR/2D/1D/5M | C13: =MarketData!$E$15 -> EUR-EONIA_IR_SWAP_RATE_EUR_2D_1D_5M#0000 | E13: =_xll.qlQxOISRateHelper("EONIA_OIS_5M",2,"5M",C13,Indexes!$B$15,"Actual/360","TARGET",1,"Annual","Following","Following","Backward","",TRUE,FALSE,FALSE,Indexes!$B$31) -> EONIA_OIS_5M#0000 | F13: =_xll.ohRangeRetrieveError(E13)
A14: OIS | B14: IR_SWAP/RATE/EUR/2D/1D/6M | C14: =MarketData!$E$16 -> EUR-EONIA_IR_SWAP_RATE_EUR_2D_1D_6M#0000 | E14: =_xll.qlQxOISRateHelper("EONIA_OIS_6M",2,"6M",C14,Indexes!$B$15,"Actual/360","TARGET",1,"Annual","Following","Following","Backward","",TRUE,FALSE,FALSE,Indexes!$B$31) -> EONIA_OIS_6M#0000 | F14: =_xll.ohRangeRetrieveError(E14)
A15: OIS | B15: IR_SWAP/RATE/EUR/2D/1D/7M | C15: =MarketData!$E$17 -> EUR-EONIA_IR_SWAP_RATE_EUR_2D_1D_7M#0000 | E15: =_xll.qlQxOISRateHelper("EONIA_OIS_7M",2,"7M",C15,Indexes!$B$15,"Actual/360","TARGET",1,"Annual","Following","Following","Backward","",TRUE,FALSE,FALSE,Indexes!$B$31) -> EONIA_OIS_7M#0000 | F15: =_xll.ohRangeRetrieveError(E15)
A16: OIS | B16: IR_SWAP/RATE/EUR/2D/1D/8M | C16: =MarketData!$E$18 -> EUR-EONIA_IR_SWAP_RATE_EUR_2D_1D_8M#0000 | E16: =_xll.qlQxOISRateHelper("EONIA_OIS_8M",2,"8M",C16,Indexes!$B$15,"Actual/360","TARGET",1,"Annual","Following","Following","Backward","",TRUE,FALSE,FALSE,Indexes!$B$31) -> EONIA_OIS_8M#0000 | F16: =_xll.ohRangeRetrieveError(E16)
A17: OIS | B17: IR_SWAP/RATE/EUR/2D/1D/9M | C17: =MarketData!$E$19 -> EUR-EONIA_IR_SWAP_RATE_EUR_2D_1D_9M#0000 | E17: =_xll.qlQxOISRateHelper("EONIA_OIS_9M",2,"9M",C17,Indexes!$B$15,"Actual/360","TARGET",1,"Annual","Following","Following","Backward","",TRUE,FALSE,FALSE,Indexes!$B$31) -> EONIA_OIS_9M#0000 | F17: =_xll.ohRangeRetrieveError(E17)
A18: OIS | B18: IR_SWAP/RATE/EUR/2D/1D/10M | C18: =MarketData!$E$20 -> EUR-EONIA_IR_SWAP_RATE_EUR_2D_1D_10M#0000 | E18: =_xll.qlQxOISRateHelper("EONIA_OIS_10M",2,"10M",C18,Indexes!$B$15,"Actual/360","TARGET",1,"Annual","Following","Following","Backward","",TRUE,FALSE,FALSE,Indexes!$B$31) -> EONIA_OIS_10M#0000 | F18: =_xll.ohRangeRetrieveError(E18)
A19: OIS | B19: IR_SWAP/RATE/EUR/2D/1D/11M | C19: =MarketData!$E$21 -> EUR-EONIA_IR_SWAP_RATE_EUR_2D_1D_11M#0000 | E19: =_xll.qlQxOISRateHelper("EONIA_OIS_11M",2,"11M",C19,Indexes!$B$15,"Actual/360","TARGET",1,"Annual","Following","Following","Backward","",TRUE,FALSE,FALSE,Indexes!$B$31) -> EONIA_OIS_11M#0000 | F19: =_xll.ohRangeRetrieveError(E19)
A20: OIS | B20: IR_SWAP/RATE/EUR/2D/1D/1Y | C20: =MarketData!$E$22 -> EUR-EONIA_IR_SWAP_RATE_EUR_2D_1D_1Y#0000 | E20: =_xll.qlQxOISRateHelper("EONIA_OIS_1Y",2,"1Y",C20,Indexes!$B$15,"Actual/360","TARGET",1,"Annual","Following","Following","Backward","",TRUE,FALSE,FALSE,Indexes!$B$31) -> EONIA_OIS_1Y#0000 | F20: =_xll.ohRangeRetrieveError(E20)
A21: OIS | B21: IR_SWAP/RATE/EUR/2D/1D/15M | C21: =MarketData!$E$23 -> EUR-EONIA_IR_SWAP_RATE_EUR_2D_1D_15M#0000 | E21: =_xll.qlQxOISRateHelper("EONIA_OIS_15M",2,"15M",C21,Indexes!$B$15,"Actual/360","TARGET",1,"Annual","Following","Following","Backward","",TRUE,FALSE,FALSE,Indexes!$B$31) -> EONIA_OIS_15M#0000 | F21: =_xll.ohRangeRetrieveError(E21)
A22: OIS | B22: IR_SWAP/RATE/EUR/2D/1D/18M | C22: =MarketData!$E$24 -> EUR-EONIA_IR_SWAP_RATE_EUR_2D_1D_18M#0000 | E22: =_xll.qlQxOISRateHelper("EONIA_OIS_18M",2,"18M",C22,Indexes!$B$15,"Actual/360","TARGET",1,"Annual","Following","Following","Backward","",TRUE,FALSE,FALSE,Indexes!$B$31) -> EONIA_OIS_18M#0000 | F22: =_xll.ohRangeRetrieveError(E22)
A23: OIS | B23: IR_SWAP/RATE/EUR/2D/1D/21M | C23: =MarketData!$E$25 -> EUR-EONIA_IR_SWAP_RATE_EUR_2D_1D_21M#0000 | E23: =_xll.qlQxOISRateHelper("EONIA_OIS_21M",2,"21M",C23,Indexes!$B$15,"Actual/360","TARGET",1,"Annual","Following","Following","Backward","",TRUE,FALSE,FALSE,Indexes!$B$31) -> EONIA_OIS_21M#0000 | F23: =_xll.ohRangeRetrieveError(E23)
A24: OIS | B24: IR_SWAP/RATE/EUR/2D/1D/2Y | C24: =MarketData!$E$26 -> EUR-EONIA_IR_SWAP_RATE_EUR_2D_1D_2Y#0000 | E24: =_xll.qlQxOISRateHelper("EONIA_OIS_2Y",2,"2Y",C24,Indexes!$B$15,"Actual/360","TARGET",1,"Annual","Following","Following","Backward","",TRUE,FALSE,FALSE,Indexes!$B$31) -> EONIA_OIS_2Y#0000 | F24: =_xll.ohRangeRetrieveError(E24)
A25: OIS | B25: IR_SWAP/RATE/EUR/2D/1D/3Y | C25: =MarketData!$E$27 -> EUR-EONIA_IR_SWAP_RATE_EUR_2D_1D_3Y#0000 | E25: =_xll.qlQxOISRateHelper("EONIA_OIS_3Y",2,"3Y",C25,Indexes!$B$15,"Actual/360","TARGET",1,"Annual","Following","Following","Backward","",TRUE,FALSE,FALSE,Indexes!$B$31) -> EONIA_OIS_3Y#0000 | F25: =_xll.ohRangeRetrieveError(E25)
A26: OIS | B26: IR_SWAP/RATE/EUR/2D/1D/4Y | C26: =MarketData!$E$28 -> EUR-EONIA_IR_SWAP_RATE_EUR_2D_1D_4Y#0000 | E26: =_xll.qlQxOISRateHelper("EONIA_OIS_4Y",2,"4Y",C26,Indexes!$B$15,"Actual/360","TARGET",1,"Annual","Following","Following","Backward","",TRUE,FALSE,FALSE,Indexes!$B$31) -> EONIA_OIS_4Y#0000 | F26: =_xll.ohRangeRetrieveError(E26)
A27: OIS | B27: IR_SWAP/RATE/EUR/2D/1D/5Y | C27: =MarketData!$E$29 -> EUR-EONIA_IR_SWAP_RATE_EUR_2D_1D_5Y#0000 | E27: =_xll.qlQxOISRateHelper("EONIA_OIS_5Y",2,"5Y",C27,Indexes!$B$15,"Actual/360","TARGET",1,"Annual","Following","Following","Backward","",TRUE,FALSE,FALSE,Indexes!$B$31) -> EONIA_OIS_5Y#0000 | F27: =_xll.ohRangeRetrieveError(E27)
A28: OIS | B28: IR_SWAP/RATE/EUR/2D/1D/6Y | C28: =MarketData!$E$30 -> EUR-EONIA_IR_SWAP_RATE_EUR_2D_1D_6Y#0000 | E28: =_xll.qlQxOISRateHelper("EONIA_OIS_6Y",2,"6Y",C28,Indexes!$B$15,"Actual/360","TARGET",1,"Annual","Following","Following","Backward","",TRUE,FALSE,FALSE,Indexes!$B$31) -> EONIA_OIS_6Y#0000 | F28: =_xll.ohRangeRetrieveError(E28)
A29: OIS | B29: IR_SWAP/RATE/EUR/2D/1D/7Y | C29: =MarketData!$E$31 -> EUR-EONIA_IR_SWAP_RATE_EUR_2D_1D_7Y#0000 | E29: =_xll.qlQxOISRateHelper("EONIA_OIS_7Y",2,"7Y",C29,Indexes!$B$15,"Actual/360","TARGET",1,"Annual","Following","Following","Backward","",TRUE,FALSE,FALSE,Indexes!$B$31) -> EONIA_OIS_7Y#0000 | F29: =_xll.ohRangeRetrieveError(E29)
A30: OIS | B30: IR_SWAP/RATE/EUR/2D/1D/8Y | C30: =MarketData!$E$32 -> EUR-EONIA_IR_SWAP_RATE_EUR_2D_1D_8Y#0000 | E30: =_xll.qlQxOISRateHelper("EONIA_OIS_8Y",2,"8Y",C30,Indexes!$B$15,"Actual/360","TARGET",1,"Annual","Following","Following","Backward","",TRUE,FALSE,FALSE,Indexes!$B$31) -> EONIA_OIS_8Y#0000 | F30: =_xll.ohRangeRetrieveError(E30)
A31: OIS | B31: IR_SWAP/RATE/EUR/2D/1D/9Y | C31: =MarketData!$E$33 -> EUR-EONIA_IR_SWAP_RATE_EUR_2D_1D_9Y#0000 | E31: =_xll.qlQxOISRateHelper("EONIA_OIS_9Y",2,"9Y",C31,Indexes!$B$15,"Actual/360","TARGET",1,"Annual","Following","Following","Backward","",TRUE,FALSE,FALSE,Indexes!$B$31) -> EONIA_OIS_9Y#0000 | F31: =_xll.ohRangeRetrieveError(E31)
A32: OIS | B32: IR_SWAP/RATE/EUR/2D/1D/10Y | C32: =MarketData!$E$34 -> EUR-EONIA_IR_SWAP_RATE_EUR_2D_1D_10Y#0000 | E32: =_xll.qlQxOISRateHelper("EONIA_OIS_10Y",2,"10Y",C32,Indexes!$B$15,"Actual/360","TARGET",1,"Annual","Following","Following","Backward","",TRUE,FALSE,FALSE,Indexes!$B$31) -> EONIA_OIS_10Y#0000 | F32: =_xll.ohRangeRetrieveError(E32)
A33: OIS | B33: IR_SWAP/RATE/EUR/2D/1D/11Y | C33: =MarketData!$E$35 -> EUR-EONIA_IR_SWAP_RATE_EUR_2D_1D_11Y#0000 | E33: =_xll.qlQxOISRateHelper("EONIA_OIS_11Y",2,"11Y",C33,Indexes!$B$15,"Actual/360","TARGET",1,"Annual","Following","Following","Backward","",TRUE,FALSE,FALSE,Indexes!$B$31) -> EONIA_OIS_11Y#0000 | F33: =_xll.ohRangeRetrieveError(E33)
A34: OIS | B34: IR_SWAP/RATE/EUR/2D/1D/12Y | C34: =MarketData!$E$36 -> EUR-EONIA_IR_SWAP_RATE_EUR_2D_1D_12Y#0000 | E34: =_xll.qlQxOISRateHelper("EONIA_OIS_12Y",2,"12Y",C34,Indexes!$B$15,"Actual/360","TARGET",1,"Annual","Following","Following","Backward","",TRUE,FALSE,FALSE,Indexes!$B$31) -> EONIA_OIS_12Y#0000 | F34: =_xll.ohRangeRetrieveError(E34)
A35: OIS | B35: IR_SWAP/RATE/EUR/2D/1D/15Y | C35: =MarketData!$E$37 -> EUR-EONIA_IR_SWAP_RATE_EUR_2D_1D_15Y#0000 | E35: =_xll.qlQxOISRateHelper("EONIA_OIS_15Y",2,"15Y",C35,Indexes!$B$15,"Actual/360","TARGET",1,"Annual","Following","Following","Backward","",TRUE,FALSE,FALSE,Indexes!$B$31) -> EONIA_OIS_15Y#0000 | F35: =_xll.ohRangeRetrieveError(E35)
A36: OIS | B36: IR_SWAP/RATE/EUR/2D/1D/20Y | C36: =MarketData!$E$38 -> EUR-EONIA_IR_SWAP_RATE_EUR_2D_1D_20Y#0000 | E36: =_xll.qlQxOISRateHelper("EONIA_OIS_20Y",2,"20Y",C36,Indexes!$B$15,"Actual/360","TARGET",1,"Annual","Following","Following","Backward","",TRUE,FALSE,FALSE,Indexes!$B$31) -> EONIA_OIS_20Y#0000 | F36: =_xll.ohRangeRetrieveError(E36)
A37: OIS | B37: IR_SWAP/RATE/EUR/2D/1D/25Y | C37: =MarketData!$E$39 -> EUR-EONIA_IR_SWAP_RATE_EUR_2D_1D_25Y#0000 | E37: =_xll.qlQxOISRateHelper("EONIA_OIS_25Y",2,"25Y",C37,Indexes!$B$15,"Actual/360","TARGET",1,"Annual","Following","Following","Backward","",TRUE,FALSE,FALSE,Indexes!$B$31) -> EONIA_OIS_25Y#0000 | F37: =_xll.ohRangeRetrieveError(E37)
A38: OIS | B38: IR_SWAP/RATE/EUR/2D/1D/30Y | C38: =MarketData!$E$40 -> EUR-EONIA_IR_SWAP_RATE_EUR_2D_1D_30Y#0000 | E38: =_xll.qlQxOISRateHelper("EONIA_OIS_30Y",2,"30Y",C38,Indexes!$B$15,"Actual/360","TARGET",1,"Annual","Following","Following","Backward","",TRUE,FALSE,FALSE,Indexes!$B$31) -> EONIA_OIS_30Y#0000 | F38: =_xll.ohRangeRetrieveError(E38)
A40: Curve | B40: =_xll.qlPiecewiseYieldCurve("C_EUR-EONIA",0,"TARGET",E5:E38,"Actual/365 (Fixed)",,,"Discount","LogLinear",FALSE,Indexes!$B$31) -> C_EUR-EONIA#0000 | C40: =_xll.ohRangeRetrieveError(B40) | D40: =_xll.qlExtrapolatorEnableExtrapolation(B40,TRUE) -> TRUE
A41: Link handle H_EUR-EONIA | B41: =_xll.qlRelinkableHandleLinkTo(Indexes!$B$6,B40,D40) -> TRUE | C41: =_xll.ohRangeRetrieveError(B41)
A43: Date | B43: ORE discount factor | C43: Excel discount factor | D43: Difference | E43: Rel. difference
A44: =DATE(2019,12,31) -> 43830 | B44: 1.0000126 | C44: =_xll.qlYieldTSDiscount($B$40,A44,TRUE,$B$41) -> 1.0000126 | D44: =C44-B44 -> 0 | E44: =D44/B44 -> 0
A45: =DATE(2020,1,10) -> 43840 | B45: 1.0001426 | C45: =_xll.qlYieldTSDiscount($B$40,A45,TRUE,$B$41) -> 1.0001426 | D45: =C45-B45 -> 0 | E45: =D45/B45 -> 0
A46: =DATE(2020,1,17) -> 43847 | B46: 1.0002255 | C46: =_xll.qlYieldTSDiscount($B$40,A46,TRUE,$B$41) -> 1.0002255 | D46: =C46-B46 -> 0 | E46: =D46/B46 -> 0
A47: =DATE(2020,1,24) -> 43854 | B47: 1.0003254 | C47: =_xll.qlYieldTSDiscount($B$40,A47,TRUE,$B$41) -> 1.0003254 | D47: =C47-B47 -> 0 | E47: =D47/B47 -> 0
A48: =DATE(2020,2,4) -> 43865 | B48: 1.0004484 | C48: =_xll.qlYieldTSDiscount($B$40,A48,TRUE,$B$41) -> 1.0004484 | D48: =C48-B48 -> 0 | E48: =D48/B48 -> 0
A49: =DATE(2020,3,3) -> 43893 | B49: 1.000797 | C49: =_xll.qlYieldTSDiscount($B$40,A49,TRUE,$B$41) -> 1.000797 | D49: =C49-B49 -> 0 | E49: =D49/B49 -> 0
A50: =DATE(2020,4,3) -> 43924 | B50: 1.0011812 | C50: =_xll.qlYieldTSDiscount($B$40,A50,TRUE,$B$41) -> 1.0011812 | D50: =C50-B50 -> 0 | E50: =D50/B50 -> 0
A51: =DATE(2020,5,5) -> 43956 | B51: 1.001579 | C51: =_xll.qlYieldTSDiscount($B$40,A51,TRUE,$B$41) -> 1.001579 | D51: =C51-B51 -> 0 | E51: =D51/B51 -> 0
A52: =DATE(2020,6,3) -> 43985 | B52: 1.0019408 | C52: =_xll.qlYieldTSDiscount($B$40,A52,TRUE,$B$41) -> 1.0019408 | D52: =C52-B52 -> 0 | E52: =D52/B52 -> 0
A53: =DATE(2020,7,3) -> 44015 | B53: 1.0023372 | C53: =_xll.qlYieldTSDiscount($B$40,A53,TRUE,$B$41) -> 1.0023372 | D53: =C53-B53 -> 0 | E53: =D53/B53 -> 0
A54: =DATE(2020,8,4) -> 44047 | B54: 1.0027203 | C54: =_xll.qlYieldTSDiscount($B$40,A54,TRUE,$B$41) -> 1.0027203 | D54: =C54-B54 -> 0 | E54: =D54/B54 -> 0
A55: =DATE(2020,9,3) -> 44077 | B55: 1.0030998 | C55: =_xll.qlYieldTSDiscount($B$40,A55,TRUE,$B$41) -> 1.0030998 | D55: =C55-B55 -> 0 | E55: =D55/B55 -> 0
A56: =DATE(2020,10,5) -> 44109 | B56: 1.0035042 | C56: =_xll.qlYieldTSDiscount($B$40,A56,TRUE,$B$41) -> 1.0035042 | D56: =C56-B56 -> 0 | E56: =D56/B56 -> 0
A57: =DATE(2020,11,3) -> 44138 | B57: 1.0038726 | C57: =_xll.qlYieldTSDiscount($B$40,A57,TRUE,$B$41) -> 1.0038726 | D57: =C57-B57 -> 0 | E57: =D57/B57 -> 0
A58: =DATE(2020,12,3) -> 44168 | B58: 1.0042509 | C58: =_xll.qlYieldTSDiscount($B$40,A58,TRUE,$B$41) -> 1.0042509 | D58: =C58-B58 -> 0 | E58: =D58/B58 -> 0
A59: =DATE(2021,1,5) -> 44201 | B59: 1.0046675 | C59: =_xll.qlYieldTSDiscount($B$40,A59,TRUE,$B$41) -> 1.0046675 | D59: =C59-B59 -> 0 | E59: =D59/B59 -> 0
A60: =DATE(2021,4,7) -> 44293 | B60: 1.0058098 | C60: =_xll.qlYieldTSDiscount($B$40,A60,TRUE,$B$41) -> 1.0058098 | D60: =C60-B60 -> 0 | E60: =D60/B60 -> 0
A61: =DATE(2021,7,5) -> 44382 | B61: 1.0069197 | C61: =_xll.qlYieldTSDiscount($B$40,A61,TRUE,$B$41) -> 1.0069197 | D61: =C61-B61 -> 0 | E61: =D61/B61 -> 0
A62: =DATE(2021,10,5) -> 44474 | B62: 1.0079676 | C62: =_xll.qlYieldTSDiscount($B$40,A62,TRUE,$B$41) -> 1.0079676 | D62: =C62-B62 -> 0 | E62: =D62/B62 -> 0
A63: =DATE(2022,1,4) -> 44565 | B63: 1.0088713 | C63: =_xll.qlYieldTSDiscount($B$40,A63,TRUE,$B$41) -> 1.0088713 | D63: =C63-B63 -> 0 | E63: =D63/B63 -> 0
A64: =DATE(2023,1,3) -> 44929 | B64: 1.0122379 | C64: =_xll.qlYieldTSDiscount($B$40,A64,TRUE,$B$41) -> 1.0122379 | D64: =C64-B64 -> 0 | E64: =D64/B64 -> 0
A65: =DATE(2024,1,3) -> 45294 | B65: 1.014391 | C65: =_xll.qlYieldTSDiscount($B$40,A65,TRUE,$B$41) -> 1.014391 | D65: =C65-B65 -> 0 | E65: =D65/B65 -> 0
A66: =DATE(2025,1,3) -> 45660 | B66: 1.0150227 | C66: =_xll.qlYieldTSDiscount($B$40,A66,TRUE,$B$41) -> 1.0150227 | D66: =C66-B66 -> 0 | E66: =D66/B66 -> 0
A67: =DATE(2026,1,5) -> 46027 | B67: 1.0143848 | C67: =_xll.qlYieldTSDiscount($B$40,A67,TRUE,$B$41) -> 1.0143848 | D67: =C67-B67 -> 0 | E67: =D67/B67 -> 0
A68: =DATE(2027,1,5) -> 46392 | B68: 1.0119329 | C68: =_xll.qlYieldTSDiscount($B$40,A68,TRUE,$B$41) -> 1.0119329 | D68: =C68-B68 -> 0 | E68: =D68/B68 -> 0
A69: =DATE(2028,1,4) -> 46756 | B69: 1.0087333 | C69: =_xll.qlYieldTSDiscount($B$40,A69,TRUE,$B$41) -> 1.0087333 | D69: =C69-B69 -> 0 | E69: =D69/B69 -> 0
A70: =DATE(2029,1,3) -> 47121 | B70: 1.0038087 | C70: =_xll.qlYieldTSDiscount($B$40,A70,TRUE,$B$41) -> 1.0038087 | D70: =C70-B70 -> 0 | E70: =D70/B70 -> 0
A71: =DATE(2030,1,3) -> 47486 | B71: 0.99756355 | C71: =_xll.qlYieldTSDiscount($B$40,A71,TRUE,$B$41) -> 0.99756355 | D71: =C71-B71 -> 0 | E71: =D71/B71 -> 0
A72: =DATE(2031,1,3) -> 47851 | B72: 0.99034833 | C72: =_xll.qlYieldTSDiscount($B$40,A72,TRUE,$B$41) -> 0.99034833 | D72: =C72-B72 -> 0 | E72: =D72/B72 -> 0
A73: =DATE(2032,1,5) -> 48218 | B73: 0.98209998 | C73: =_xll.qlYieldTSDiscount($B$40,A73,TRUE,$B$41) -> 0.98209998 | D73: =C73-B73 -> 0 | E73: =D73/B73 -> 0
A74: =DATE(2035,1,3) -> 49312 | B74: 0.95509441 | C74: =_xll.qlYieldTSDiscount($B$40,A74,TRUE,$B$41) -> 0.95509441 | D74: =C74-B74 -> 0 | E74: =D74/B74 -> 0
A75: =DATE(2040,1,3) -> 51138 | B75: 0.9127954 | C75: =_xll.qlYieldTSDiscount($B$40,A75,TRUE,$B$41) -> 0.9127954 | D75: =C75-B75 -> 0 | E75: =D75/B75 -> 0
A76: =DATE(2045,1,3) -> 52965 | B76: 0.88154805 | C76: =_xll.qlYieldTSDiscount($B$40,A76,TRUE,$B$41) -> 0.88154805 | D76: =C76-B76 -> 0 | E76: =D76/B76 -> 0
A77: =DATE(2050,1,4) -> 54792 | B77: 0.85875032 | C77: =_xll.qlYieldTSDiscount($B$40,A77,TRUE,$B$41) -> 0.85875032 | D77: =C77-B77 -> 0 | E77: =D77/B77 -> 0
A79: Max abs difference | D79: =MAX(ABS(MIN(D44:D77)),ABS(MAX(D44:D77))) -> 0

Sheet USD-LIBOR-3M
A1: USD-LIBOR-3M: Discount/LogLinear, A365, extrapolation; discount curve USD-FedFunds; deposit 3M, FRAs 1x4..9x12, swaps 2Y-50Y
A2: USD-LIBOR-3M-SWAP: fixed calendar US+UK, Semiannual, MF, 30/360 (USA); float index USD-LIBOR-3M.
A4: Segment | B4: Quote | C4: Rate | E4: Helper | F4: Error
A5: Deposit | B5: MM/RATE/USD/2D/3M | C5: =MarketData!$E$160 -> USD-LIBOR-3M_MM_RATE_USD_2D_3M#0000 | E5: =_xll.qlDepositRateHelper2("LIBOR3M_DEP",C5,"3M",2,"UnitedKingdom::Exchange","Modified Following",TRUE,"Actual/360",FALSE,Indexes!$B$31) -> LIBOR3M_DEP#0000 | F5: =_xll.ohRangeRetrieveError(E5)
A6: FRA | B6: FRA/RATE/USD/1M/3M | C6: =MarketData!$E$161 -> USD-LIBOR-3M_FRA_RATE_USD_1M_3M#0000 | E6: =_xll.qlFraRateHelper("LIBOR3M_FRA_1M",C6,"1M",Indexes!$B$16,"LastRelevantDate",,FALSE,Indexes!$B$31) -> LIBOR3M_FRA_1M#0000 | F6: =_xll.ohRangeRetrieveError(E6)
A7: FRA | B7: FRA/RATE/USD/2M/3M | C7: =MarketData!$E$162 -> USD-LIBOR-3M_FRA_RATE_USD_2M_3M#0000 | E7: =_xll.qlFraRateHelper("LIBOR3M_FRA_2M",C7,"2M",Indexes!$B$16,"LastRelevantDate",,FALSE,Indexes!$B$31) -> LIBOR3M_FRA_2M#0000 | F7: =_xll.ohRangeRetrieveError(E7)
A8: FRA | B8: FRA/RATE/USD/3M/3M | C8: =MarketData!$E$163 -> USD-LIBOR-3M_FRA_RATE_USD_3M_3M#0000 | E8: =_xll.qlFraRateHelper("LIBOR3M_FRA_3M",C8,"3M",Indexes!$B$16,"LastRelevantDate",,FALSE,Indexes!$B$31) -> LIBOR3M_FRA_3M#0000 | F8: =_xll.ohRangeRetrieveError(E8)
A9: FRA | B9: FRA/RATE/USD/4M/3M | C9: =MarketData!$E$164 -> USD-LIBOR-3M_FRA_RATE_USD_4M_3M#0000 | E9: =_xll.qlFraRateHelper("LIBOR3M_FRA_4M",C9,"4M",Indexes!$B$16,"LastRelevantDate",,FALSE,Indexes!$B$31) -> LIBOR3M_FRA_4M#0000 | F9: =_xll.ohRangeRetrieveError(E9)
A10: FRA | B10: FRA/RATE/USD/5M/3M | C10: =MarketData!$E$165 -> USD-LIBOR-3M_FRA_RATE_USD_5M_3M#0000 | E10: =_xll.qlFraRateHelper("LIBOR3M_FRA_5M",C10,"5M",Indexes!$B$16,"LastRelevantDate",,FALSE,Indexes!$B$31) -> LIBOR3M_FRA_5M#0000 | F10: =_xll.ohRangeRetrieveError(E10)
A11: FRA | B11: FRA/RATE/USD/6M/3M | C11: =MarketData!$E$166 -> USD-LIBOR-3M_FRA_RATE_USD_6M_3M#0000 | E11: =_xll.qlFraRateHelper("LIBOR3M_FRA_6M",C11,"6M",Indexes!$B$16,"LastRelevantDate",,FALSE,Indexes!$B$31) -> LIBOR3M_FRA_6M#0000 | F11: =_xll.ohRangeRetrieveError(E11)
A12: FRA | B12: FRA/RATE/USD/7M/3M | C12: =MarketData!$E$167 -> USD-LIBOR-3M_FRA_RATE_USD_7M_3M#0000 | E12: =_xll.qlFraRateHelper("LIBOR3M_FRA_7M",C12,"7M",Indexes!$B$16,"LastRelevantDate",,FALSE,Indexes!$B$31) -> LIBOR3M_FRA_7M#0000 | F12: =_xll.ohRangeRetrieveError(E12)
A13: FRA | B13: FRA/RATE/USD/8M/3M | C13: =MarketData!$E$168 -> USD-LIBOR-3M_FRA_RATE_USD_8M_3M#0000 | E13: =_xll.qlFraRateHelper("LIBOR3M_FRA_8M",C13,"8M",Indexes!$B$16,"LastRelevantDate",,FALSE,Indexes!$B$31) -> LIBOR3M_FRA_8M#0000 | F13: =_xll.ohRangeRetrieveError(E13)
A14: FRA | B14: FRA/RATE/USD/9M/3M | C14: =MarketData!$E$169 -> USD-LIBOR-3M_FRA_RATE_USD_9M_3M#0000 | E14: =_xll.qlFraRateHelper("LIBOR3M_FRA_9M",C14,"9M",Indexes!$B$16,"LastRelevantDate",,FALSE,Indexes!$B$31) -> LIBOR3M_FRA_9M#0000 | F14: =_xll.ohRangeRetrieveError(E14)
A15: Swap | B15: IR_SWAP/RATE/USD/2D/3M/2Y | C15: =MarketData!$E$170 -> USD-LIBOR-3M_IR_SWAP_RATE_USD_2D_3M_2Y#0000 | E15: =_xll.qlSwapRateHelper2("LIBOR3M_SWAP_2Y",C15,,"2Y","JoinHolidays(UnitedStates::Settlement,UnitedKingdom::Settlement)","Semiannual","Modified Following","30/360 (USA)",Indexes!$B$16,0,"0D",Indexes!$B$5,"LastRelevantDate",,FALSE,'USD-FedFunds'!$B$32) -> LIBOR3M_SWAP_2Y#0000 | F15: =_xll.ohRangeRetrieveError(E15)
A16: Swap | B16: IR_SWAP/RATE/USD/2D/3M/3Y | C16: =MarketData!$E$171 -> USD-LIBOR-3M_IR_SWAP_RATE_USD_2D_3M_3Y#0000 | E16: =_xll.qlSwapRateHelper2("LIBOR3M_SWAP_3Y",C16,,"3Y","JoinHolidays(UnitedStates::Settlement,UnitedKingdom::Settlement)","Semiannual","Modified Following","30/360 (USA)",Indexes!$B$16,0,"0D",Indexes!$B$5,"LastRelevantDate",,FALSE,'USD-FedFunds'!$B$32) -> LIBOR3M_SWAP_3Y#0000 | F16: =_xll.ohRangeRetrieveError(E16)
A17: Swap | B17: IR_SWAP/RATE/USD/2D/3M/4Y | C17: =MarketData!$E$172 -> USD-LIBOR-3M_IR_SWAP_RATE_USD_2D_3M_4Y#0000 | E17: =_xll.qlSwapRateHelper2("LIBOR3M_SWAP_4Y",C17,,"4Y","JoinHolidays(UnitedStates::Settlement,UnitedKingdom::Settlement)","Semiannual","Modified Following","30/360 (USA)",Indexes!$B$16,0,"0D",Indexes!$B$5,"LastRelevantDate",,FALSE,'USD-FedFunds'!$B$32) -> LIBOR3M_SWAP_4Y#0000 | F17: =_xll.ohRangeRetrieveError(E17)
A18: Swap | B18: IR_SWAP/RATE/USD/2D/3M/5Y | C18: =MarketData!$E$173 -> USD-LIBOR-3M_IR_SWAP_RATE_USD_2D_3M_5Y#0000 | E18: =_xll.qlSwapRateHelper2("LIBOR3M_SWAP_5Y",C18,,"5Y","JoinHolidays(UnitedStates::Settlement,UnitedKingdom::Settlement)","Semiannual","Modified Following","30/360 (USA)",Indexes!$B$16,0,"0D",Indexes!$B$5,"LastRelevantDate",,FALSE,'USD-FedFunds'!$B$32) -> LIBOR3M_SWAP_5Y#0000 | F18: =_xll.ohRangeRetrieveError(E18)
A19: Swap | B19: IR_SWAP/RATE/USD/2D/3M/6Y | C19: =MarketData!$E$174 -> USD-LIBOR-3M_IR_SWAP_RATE_USD_2D_3M_6Y#0000 | E19: =_xll.qlSwapRateHelper2("LIBOR3M_SWAP_6Y",C19,,"6Y","JoinHolidays(UnitedStates::Settlement,UnitedKingdom::Settlement)","Semiannual","Modified Following","30/360 (USA)",Indexes!$B$16,0,"0D",Indexes!$B$5,"LastRelevantDate",,FALSE,'USD-FedFunds'!$B$32) -> LIBOR3M_SWAP_6Y#0000 | F19: =_xll.ohRangeRetrieveError(E19)
A20: Swap | B20: IR_SWAP/RATE/USD/2D/3M/7Y | C20: =MarketData!$E$175 -> USD-LIBOR-3M_IR_SWAP_RATE_USD_2D_3M_7Y#0000 | E20: =_xll.qlSwapRateHelper2("LIBOR3M_SWAP_7Y",C20,,"7Y","JoinHolidays(UnitedStates::Settlement,UnitedKingdom::Settlement)","Semiannual","Modified Following","30/360 (USA)",Indexes!$B$16,0,"0D",Indexes!$B$5,"LastRelevantDate",,FALSE,'USD-FedFunds'!$B$32) -> LIBOR3M_SWAP_7Y#0000 | F20: =_xll.ohRangeRetrieveError(E20)
A21: Swap | B21: IR_SWAP/RATE/USD/2D/3M/8Y | C21: =MarketData!$E$176 -> USD-LIBOR-3M_IR_SWAP_RATE_USD_2D_3M_8Y#0000 | E21: =_xll.qlSwapRateHelper2("LIBOR3M_SWAP_8Y",C21,,"8Y","JoinHolidays(UnitedStates::Settlement,UnitedKingdom::Settlement)","Semiannual","Modified Following","30/360 (USA)",Indexes!$B$16,0,"0D",Indexes!$B$5,"LastRelevantDate",,FALSE,'USD-FedFunds'!$B$32) -> LIBOR3M_SWAP_8Y#0000 | F21: =_xll.ohRangeRetrieveError(E21)
A22: Swap | B22: IR_SWAP/RATE/USD/2D/3M/9Y | C22: =MarketData!$E$177 -> USD-LIBOR-3M_IR_SWAP_RATE_USD_2D_3M_9Y#0000 | E22: =_xll.qlSwapRateHelper2("LIBOR3M_SWAP_9Y",C22,,"9Y","JoinHolidays(UnitedStates::Settlement,UnitedKingdom::Settlement)","Semiannual","Modified Following","30/360 (USA)",Indexes!$B$16,0,"0D",Indexes!$B$5,"LastRelevantDate",,FALSE,'USD-FedFunds'!$B$32) -> LIBOR3M_SWAP_9Y#0000 | F22: =_xll.ohRangeRetrieveError(E22)
A23: Swap | B23: IR_SWAP/RATE/USD/2D/3M/10Y | C23: =MarketData!$E$178 -> USD-LIBOR-3M_IR_SWAP_RATE_USD_2D_3M_10Y#0000 | E23: =_xll.qlSwapRateHelper2("LIBOR3M_SWAP_10Y",C23,,"10Y","JoinHolidays(UnitedStates::Settlement,UnitedKingdom::Settlement)","Semiannual","Modified Following","30/360 (USA)",Indexes!$B$16,0,"0D",Indexes!$B$5,"LastRelevantDate",,FALSE,'USD-FedFunds'!$B$32) -> LIBOR3M_SWAP_10Y#0000 | F23: =_xll.ohRangeRetrieveError(E23)
A24: Swap | B24: IR_SWAP/RATE/USD/2D/3M/12Y | C24: =MarketData!$E$179 -> USD-LIBOR-3M_IR_SWAP_RATE_USD_2D_3M_12Y#0000 | E24: =_xll.qlSwapRateHelper2("LIBOR3M_SWAP_12Y",C24,,"12Y","JoinHolidays(UnitedStates::Settlement,UnitedKingdom::Settlement)","Semiannual","Modified Following","30/360 (USA)",Indexes!$B$16,0,"0D",Indexes!$B$5,"LastRelevantDate",,FALSE,'USD-FedFunds'!$B$32) -> LIBOR3M_SWAP_12Y#0000 | F24: =_xll.ohRangeRetrieveError(E24)
A25: Swap | B25: IR_SWAP/RATE/USD/2D/3M/15Y | C25: =MarketData!$E$180 -> USD-LIBOR-3M_IR_SWAP_RATE_USD_2D_3M_15Y#0000 | E25: =_xll.qlSwapRateHelper2("LIBOR3M_SWAP_15Y",C25,,"15Y","JoinHolidays(UnitedStates::Settlement,UnitedKingdom::Settlement)","Semiannual","Modified Following","30/360 (USA)",Indexes!$B$16,0,"0D",Indexes!$B$5,"LastRelevantDate",,FALSE,'USD-FedFunds'!$B$32) -> LIBOR3M_SWAP_15Y#0000 | F25: =_xll.ohRangeRetrieveError(E25)
A26: Swap | B26: IR_SWAP/RATE/USD/2D/3M/20Y | C26: =MarketData!$E$181 -> USD-LIBOR-3M_IR_SWAP_RATE_USD_2D_3M_20Y#0000 | E26: =_xll.qlSwapRateHelper2("LIBOR3M_SWAP_20Y",C26,,"20Y","JoinHolidays(UnitedStates::Settlement,UnitedKingdom::Settlement)","Semiannual","Modified Following","30/360 (USA)",Indexes!$B$16,0,"0D",Indexes!$B$5,"LastRelevantDate",,FALSE,'USD-FedFunds'!$B$32) -> LIBOR3M_SWAP_20Y#0000 | F26: =_xll.ohRangeRetrieveError(E26)
A27: Swap | B27: IR_SWAP/RATE/USD/2D/3M/25Y | C27: =MarketData!$E$182 -> USD-LIBOR-3M_IR_SWAP_RATE_USD_2D_3M_25Y#0000 | E27: =_xll.qlSwapRateHelper2("LIBOR3M_SWAP_25Y",C27,,"25Y","JoinHolidays(UnitedStates::Settlement,UnitedKingdom::Settlement)","Semiannual","Modified Following","30/360 (USA)",Indexes!$B$16,0,"0D",Indexes!$B$5,"LastRelevantDate",,FALSE,'USD-FedFunds'!$B$32) -> LIBOR3M_SWAP_25Y#0000 | F27: =_xll.ohRangeRetrieveError(E27)
A28: Swap | B28: IR_SWAP/RATE/USD/2D/3M/30Y | C28: =MarketData!$E$183 -> USD-LIBOR-3M_IR_SWAP_RATE_USD_2D_3M_30Y#0000 | E28: =_xll.qlSwapRateHelper2("LIBOR3M_SWAP_30Y",C28,,"30Y","JoinHolidays(UnitedStates::Settlement,UnitedKingdom::Settlement)","Semiannual","Modified Following","30/360 (USA)",Indexes!$B$16,0,"0D",Indexes!$B$5,"LastRelevantDate",,FALSE,'USD-FedFunds'!$B$32) -> LIBOR3M_SWAP_30Y#0000 | F28: =_xll.ohRangeRetrieveError(E28)
A29: Swap | B29: IR_SWAP/RATE/USD/2D/3M/40Y | C29: =MarketData!$E$184 -> USD-LIBOR-3M_IR_SWAP_RATE_USD_2D_3M_40Y#0000 | E29: =_xll.qlSwapRateHelper2("LIBOR3M_SWAP_40Y",C29,,"40Y","JoinHolidays(UnitedStates::Settlement,UnitedKingdom::Settlement)","Semiannual","Modified Following","30/360 (USA)",Indexes!$B$16,0,"0D",Indexes!$B$5,"LastRelevantDate",,FALSE,'USD-FedFunds'!$B$32) -> LIBOR3M_SWAP_40Y#0000 | F29: =_xll.ohRangeRetrieveError(E29)
A30: Swap | B30: IR_SWAP/RATE/USD/2D/3M/50Y | C30: =MarketData!$E$185 -> USD-LIBOR-3M_IR_SWAP_RATE_USD_2D_3M_50Y#0000 | E30: =_xll.qlSwapRateHelper2("LIBOR3M_SWAP_50Y",C30,,"50Y","JoinHolidays(UnitedStates::Settlement,UnitedKingdom::Settlement)","Semiannual","Modified Following","30/360 (USA)",Indexes!$B$16,0,"0D",Indexes!$B$5,"LastRelevantDate",,FALSE,'USD-FedFunds'!$B$32) -> LIBOR3M_SWAP_50Y#0000 | F30: =_xll.ohRangeRetrieveError(E30)
A32: Curve | B32: =_xll.qlPiecewiseYieldCurve("C_USD-LIBOR-3M",0,"UnitedKingdom::Exchange",E5:E30,"Actual/365 (Fixed)",,,"Discount","LogLinear",FALSE,Indexes!$B$31) -> C_USD-LIBOR-3M#0000 | C32: =_xll.ohRangeRetrieveError(B32) | D32: =_xll.qlExtrapolatorEnableExtrapolation(B32,TRUE) -> TRUE
A33: Link handle H_USD-LIBOR-3M | B33: =_xll.qlRelinkableHandleLinkTo(Indexes!$B$7,B32,D32) -> TRUE | C33: =_xll.ohRangeRetrieveError(B33)
A35: Date | B35: ORE discount factor | C35: Excel discount factor | D35: Difference | E35: Rel. difference
A36: =DATE(2020,4,2) -> 43923 | B36: 0.99503874 | C36: =_xll.qlYieldTSDiscount($B$32,A36,TRUE,$B$33) -> 0.99503874 | D36: =C36-B36 -> 0 | E36: =D36/B36 -> 0
A37: =DATE(2020,5,4) -> 43955 | B37: 0.99368884 | C37: =_xll.qlYieldTSDiscount($B$32,A37,TRUE,$B$33) -> 0.99368884 | D37: =C37-B37 -> 0 | E37: =D37/B37 -> 0
A38: =DATE(2020,6,2) -> 43984 | B38: 0.9922574 | C38: =_xll.qlYieldTSDiscount($B$32,A38,TRUE,$B$33) -> 0.9922574 | D38: =C38-B38 -> 0 | E38: =D38/B38 -> 0
A39: =DATE(2020,7,2) -> 44014 | B39: 0.99073375 | C39: =_xll.qlYieldTSDiscount($B$32,A39,TRUE,$B$33) -> 0.99073375 | D39: =C39-B39 -> 0 | E39: =D39/B39 -> 0
A40: =DATE(2020,8,4) -> 44047 | B40: 0.98941566 | C40: =_xll.qlYieldTSDiscount($B$32,A40,TRUE,$B$33) -> 0.98941566 | D40: =C40-B40 -> 0 | E40: =D40/B40 -> 0
A41: =DATE(2020,9,2) -> 44076 | B41: 0.98801803 | C41: =_xll.qlYieldTSDiscount($B$32,A41,TRUE,$B$33) -> 0.98801803 | D41: =C41-B41 -> 0 | E41: =D41/B41 -> 0
A42: =DATE(2020,10,2) -> 44106 | B42: 0.986526 | C42: =_xll.qlYieldTSDiscount($B$32,A42,TRUE,$B$33) -> 0.986526 | D42: =C42-B42 -> 0 | E42: =D42/B42 -> 0
A43: =DATE(2020,11,3) -> 44138 | B43: 0.985336 | C43: =_xll.qlYieldTSDiscount($B$32,A43,TRUE,$B$33) -> 0.985336 | D43: =C43-B43 -> 0 | E43: =D43/B43 -> 0
A44: =DATE(2020,12,2) -> 44167 | B44: 0.98396631 | C44: =_xll.qlYieldTSDiscount($B$32,A44,TRUE,$B$33) -> 0.98396631 | D44: =C44-B44 -> 0 | E44: =D44/B44 -> 0
A45: =DATE(2021,1,4) -> 44200 | B45: 0.98240633 | C45: =_xll.qlYieldTSDiscount($B$32,A45,TRUE,$B$33) -> 0.98240633 | D45: =C45-B45 -> 0 | E45: =D45/B45 -> 0
A46: =DATE(2022,1,4) -> 44565 | B46: 0.96695267 | C46: =_xll.qlYieldTSDiscount($B$32,A46,TRUE,$B$33) -> 0.96695267 | D46: =C46-B46 -> 0 | E46: =D46/B46 -> 0
A47: =DATE(2023,1,3) -> 44929 | B47: 0.95143342 | C47: =_xll.qlYieldTSDiscount($B$32,A47,TRUE,$B$33) -> 0.95143342 | D47: =C47-B47 -> 0 | E47: =D47/B47 -> 0
A48: =DATE(2024,1,2) -> 45293 | B48: 0.93539992 | C48: =_xll.qlYieldTSDiscount($B$32,A48,TRUE,$B$33) -> 0.93539992 | D48: =C48-B48 -> 0 | E48: =D48/B48 -> 0
A49: =DATE(2025,1,2) -> 45659 | B49: 0.91944424 | C49: =_xll.qlYieldTSDiscount($B$32,A49,TRUE,$B$33) -> 0.91944424 | D49: =C49-B49 -> 0 | E49: =D49/B49 -> 0
A50: =DATE(2026,1,2) -> 46024 | B50: 0.90254017 | C50: =_xll.qlYieldTSDiscount($B$32,A50,TRUE,$B$33) -> 0.90254017 | D50: =C50-B50 -> 0 | E50: =D50/B50 -> 0
A51: =DATE(2027,1,4) -> 46391 | B51: 0.88513102 | C51: =_xll.qlYieldTSDiscount($B$32,A51,TRUE,$B$33) -> 0.88513102 | D51: =C51-B51 -> 0 | E51: =D51/B51 -> 0
A52: =DATE(2028,1,4) -> 46756 | B52: 0.86748155 | C52: =_xll.qlYieldTSDiscount($B$32,A52,TRUE,$B$33) -> 0.86748155 | D52: =C52-B52 -> 0 | E52: =D52/B52 -> 0
A53: =DATE(2029,1,2) -> 47120 | B53: 0.85064358 | C53: =_xll.qlYieldTSDiscount($B$32,A53,TRUE,$B$33) -> 0.85064358 | D53: =C53-B53 -> 0 | E53: =D53/B53 -> 0
A54: =DATE(2030,1,2) -> 47485 | B54: 0.83188445 | C54: =_xll.qlYieldTSDiscount($B$32,A54,TRUE,$B$33) -> 0.83188445 | D54: =C54-B54 -> 0 | E54: =D54/B54 -> 0
A55: =DATE(2032,1,2) -> 48215 | B55: 0.79755144 | C55: =_xll.qlYieldTSDiscount($B$32,A55,TRUE,$B$33) -> 0.79755144 | D55: =C55-B55 -> 0 | E55: =D55/B55 -> 0
A56: =DATE(2035,1,2) -> 49311 | B56: 0.74710844 | C56: =_xll.qlYieldTSDiscount($B$32,A56,TRUE,$B$33) -> 0.74710844 | D56: =C56-B56 -> 0 | E56: =D56/B56 -> 0
A57: =DATE(2040,1,3) -> 51138 | B57: 0.66962002 | C57: =_xll.qlYieldTSDiscount($B$32,A57,TRUE,$B$33) -> 0.66962002 | D57: =C57-B57 -> 0 | E57: =D57/B57 -> 0
A58: =DATE(2045,1,3) -> 52965 | B58: 0.60281798 | C58: =_xll.qlYieldTSDiscount($B$32,A58,TRUE,$B$33) -> 0.60281798 | D58: =C58-B58 -> 0 | E58: =D58/B58 -> 0
A59: =DATE(2050,1,4) -> 54792 | B59: 0.54429054 | C59: =_xll.qlYieldTSDiscount($B$32,A59,TRUE,$B$33) -> 0.54429054 | D59: =C59-B59 -> 0 | E59: =D59/B59 -> 0
A60: =DATE(2060,1,2) -> 58442 | B60: 0.4518057 | C60: =_xll.qlYieldTSDiscount($B$32,A60,TRUE,$B$33) -> 0.4518057 | D60: =C60-B60 -> 0 | E60: =D60/B60 -> 0
A61: =DATE(2070,1,2) -> 62095 | B61: 0.37953416 | C61: =_xll.qlYieldTSDiscount($B$32,A61,TRUE,$B$33) -> 0.37953416 | D61: =C61-B61 -> 0 | E61: =D61/B61 -> 0
A63: Max abs difference | D63: =MAX(ABS(MIN(D36:D61)),ABS(MAX(D36:D61))) -> 0

Sheet USD-LIBOR-6M
A1: USD-LIBOR-6M: Discount/LogLinear, A365, extrapolation; discount curve USD-FedFunds; deposit 6M, FRAs 1x7..12x18, 3M/6M tenor basis 2Y-30Y
A2: USD-LIBOR-3M-6M-BASIS: pay USD-LIBOR-6M (bootstrapped), receive USD-LIBOR-3M (given) compounded to 6M, spread on receive leg, telescopic dates.
A4: Segment | B4: Quote | C4: Rate | E4: Helper | F4: Error
A5: Deposit | B5: MM/RATE/USD/2D/6M | C5: =MarketData!$E$186 -> USD-LIBOR-6M_MM_RATE_USD_2D_6M#0000 | E5: =_xll.qlDepositRateHelper2("LIBOR6M_DEP",C5,"6M",2,"UnitedKingdom::Exchange","Modified Following",TRUE,"Actual/360",FALSE,Indexes!$B$31) -> LIBOR6M_DEP#0000 | F5: =_xll.ohRangeRetrieveError(E5)
A6: FRA | B6: FRA/RATE/USD/1M/6M | C6: =MarketData!$E$187 -> USD-LIBOR-6M_FRA_RATE_USD_1M_6M#0000 | E6: =_xll.qlFraRateHelper("LIBOR6M_FRA_1M",C6,"1M",Indexes!$B$17,"LastRelevantDate",,FALSE,Indexes!$B$31) -> LIBOR6M_FRA_1M#0000 | F6: =_xll.ohRangeRetrieveError(E6)
A7: FRA | B7: FRA/RATE/USD/2M/6M | C7: =MarketData!$E$188 -> USD-LIBOR-6M_FRA_RATE_USD_2M_6M#0000 | E7: =_xll.qlFraRateHelper("LIBOR6M_FRA_2M",C7,"2M",Indexes!$B$17,"LastRelevantDate",,FALSE,Indexes!$B$31) -> LIBOR6M_FRA_2M#0000 | F7: =_xll.ohRangeRetrieveError(E7)
A8: FRA | B8: FRA/RATE/USD/3M/6M | C8: =MarketData!$E$189 -> USD-LIBOR-6M_FRA_RATE_USD_3M_6M#0000 | E8: =_xll.qlFraRateHelper("LIBOR6M_FRA_3M",C8,"3M",Indexes!$B$17,"LastRelevantDate",,FALSE,Indexes!$B$31) -> LIBOR6M_FRA_3M#0000 | F8: =_xll.ohRangeRetrieveError(E8)
A9: FRA | B9: FRA/RATE/USD/4M/6M | C9: =MarketData!$E$190 -> USD-LIBOR-6M_FRA_RATE_USD_4M_6M#0000 | E9: =_xll.qlFraRateHelper("LIBOR6M_FRA_4M",C9,"4M",Indexes!$B$17,"LastRelevantDate",,FALSE,Indexes!$B$31) -> LIBOR6M_FRA_4M#0000 | F9: =_xll.ohRangeRetrieveError(E9)
A10: FRA | B10: FRA/RATE/USD/5M/6M | C10: =MarketData!$E$191 -> USD-LIBOR-6M_FRA_RATE_USD_5M_6M#0000 | E10: =_xll.qlFraRateHelper("LIBOR6M_FRA_5M",C10,"5M",Indexes!$B$17,"LastRelevantDate",,FALSE,Indexes!$B$31) -> LIBOR6M_FRA_5M#0000 | F10: =_xll.ohRangeRetrieveError(E10)
A11: FRA | B11: FRA/RATE/USD/6M/6M | C11: =MarketData!$E$192 -> USD-LIBOR-6M_FRA_RATE_USD_6M_6M#0000 | E11: =_xll.qlFraRateHelper("LIBOR6M_FRA_6M",C11,"6M",Indexes!$B$17,"LastRelevantDate",,FALSE,Indexes!$B$31) -> LIBOR6M_FRA_6M#0000 | F11: =_xll.ohRangeRetrieveError(E11)
A12: FRA | B12: FRA/RATE/USD/9M/6M | C12: =MarketData!$E$193 -> USD-LIBOR-6M_FRA_RATE_USD_9M_6M#0000 | E12: =_xll.qlFraRateHelper("LIBOR6M_FRA_9M",C12,"9M",Indexes!$B$17,"LastRelevantDate",,FALSE,Indexes!$B$31) -> LIBOR6M_FRA_9M#0000 | F12: =_xll.ohRangeRetrieveError(E12)
A13: FRA | B13: FRA/RATE/USD/12M/6M | C13: =MarketData!$E$194 -> USD-LIBOR-6M_FRA_RATE_USD_12M_6M#0000 | E13: =_xll.qlFraRateHelper("LIBOR6M_FRA_12M",C13,"12M",Indexes!$B$17,"LastRelevantDate",,FALSE,Indexes!$B$31) -> LIBOR6M_FRA_12M#0000 | F13: =_xll.ohRangeRetrieveError(E13)
A14: Tenor basis | B14: BASIS_SWAP/BASIS_SPREAD/3M/6M/USD/2Y | C14: =MarketData!$E$195 -> USD-LIBOR-6M_BASIS_SWAP_BASIS_SPREAD_3M_6M_USD_2Y#0000 | E14: =_xll.qlTenorBasisSwapHelper("LIBOR6M_TBS_2Y",C14,"2Y",Indexes!$B$17,Indexes!$B$16,Indexes!$B$5,TRUE,FALSE,"6M","6M",TRUE,"Compounding",FALSE,TRUE,FALSE,'USD-FedFunds'!$B$32) -> LIBOR6M_TBS_2Y#0000 | F14: =_xll.ohRangeRetrieveError(E14)
A15: Tenor basis | B15: BASIS_SWAP/BASIS_SPREAD/3M/6M/USD/3Y | C15: =MarketData!$E$196 -> USD-LIBOR-6M_BASIS_SWAP_BASIS_SPREAD_3M_6M_USD_3Y#0000 | E15: =_xll.qlTenorBasisSwapHelper("LIBOR6M_TBS_3Y",C15,"3Y",Indexes!$B$17,Indexes!$B$16,Indexes!$B$5,TRUE,FALSE,"6M","6M",TRUE,"Compounding",FALSE,TRUE,FALSE,'USD-FedFunds'!$B$32) -> LIBOR6M_TBS_3Y#0000 | F15: =_xll.ohRangeRetrieveError(E15)
A16: Tenor basis | B16: BASIS_SWAP/BASIS_SPREAD/3M/6M/USD/4Y | C16: =MarketData!$E$197 -> USD-LIBOR-6M_BASIS_SWAP_BASIS_SPREAD_3M_6M_USD_4Y#0000 | E16: =_xll.qlTenorBasisSwapHelper("LIBOR6M_TBS_4Y",C16,"4Y",Indexes!$B$17,Indexes!$B$16,Indexes!$B$5,TRUE,FALSE,"6M","6M",TRUE,"Compounding",FALSE,TRUE,FALSE,'USD-FedFunds'!$B$32) -> LIBOR6M_TBS_4Y#0000 | F16: =_xll.ohRangeRetrieveError(E16)
A17: Tenor basis | B17: BASIS_SWAP/BASIS_SPREAD/3M/6M/USD/5Y | C17: =MarketData!$E$198 -> USD-LIBOR-6M_BASIS_SWAP_BASIS_SPREAD_3M_6M_USD_5Y#0000 | E17: =_xll.qlTenorBasisSwapHelper("LIBOR6M_TBS_5Y",C17,"5Y",Indexes!$B$17,Indexes!$B$16,Indexes!$B$5,TRUE,FALSE,"6M","6M",TRUE,"Compounding",FALSE,TRUE,FALSE,'USD-FedFunds'!$B$32) -> LIBOR6M_TBS_5Y#0000 | F17: =_xll.ohRangeRetrieveError(E17)
A18: Tenor basis | B18: BASIS_SWAP/BASIS_SPREAD/3M/6M/USD/6Y | C18: =MarketData!$E$199 -> USD-LIBOR-6M_BASIS_SWAP_BASIS_SPREAD_3M_6M_USD_6Y#0000 | E18: =_xll.qlTenorBasisSwapHelper("LIBOR6M_TBS_6Y",C18,"6Y",Indexes!$B$17,Indexes!$B$16,Indexes!$B$5,TRUE,FALSE,"6M","6M",TRUE,"Compounding",FALSE,TRUE,FALSE,'USD-FedFunds'!$B$32) -> LIBOR6M_TBS_6Y#0000 | F18: =_xll.ohRangeRetrieveError(E18)
A19: Tenor basis | B19: BASIS_SWAP/BASIS_SPREAD/3M/6M/USD/7Y | C19: =MarketData!$E$200 -> USD-LIBOR-6M_BASIS_SWAP_BASIS_SPREAD_3M_6M_USD_7Y#0000 | E19: =_xll.qlTenorBasisSwapHelper("LIBOR6M_TBS_7Y",C19,"7Y",Indexes!$B$17,Indexes!$B$16,Indexes!$B$5,TRUE,FALSE,"6M","6M",TRUE,"Compounding",FALSE,TRUE,FALSE,'USD-FedFunds'!$B$32) -> LIBOR6M_TBS_7Y#0000 | F19: =_xll.ohRangeRetrieveError(E19)
A20: Tenor basis | B20: BASIS_SWAP/BASIS_SPREAD/3M/6M/USD/8Y | C20: =MarketData!$E$201 -> USD-LIBOR-6M_BASIS_SWAP_BASIS_SPREAD_3M_6M_USD_8Y#0000 | E20: =_xll.qlTenorBasisSwapHelper("LIBOR6M_TBS_8Y",C20,"8Y",Indexes!$B$17,Indexes!$B$16,Indexes!$B$5,TRUE,FALSE,"6M","6M",TRUE,"Compounding",FALSE,TRUE,FALSE,'USD-FedFunds'!$B$32) -> LIBOR6M_TBS_8Y#0000 | F20: =_xll.ohRangeRetrieveError(E20)
A21: Tenor basis | B21: BASIS_SWAP/BASIS_SPREAD/3M/6M/USD/9Y | C21: =MarketData!$E$202 -> USD-LIBOR-6M_BASIS_SWAP_BASIS_SPREAD_3M_6M_USD_9Y#0000 | E21: =_xll.qlTenorBasisSwapHelper("LIBOR6M_TBS_9Y",C21,"9Y",Indexes!$B$17,Indexes!$B$16,Indexes!$B$5,TRUE,FALSE,"6M","6M",TRUE,"Compounding",FALSE,TRUE,FALSE,'USD-FedFunds'!$B$32) -> LIBOR6M_TBS_9Y#0000 | F21: =_xll.ohRangeRetrieveError(E21)
A22: Tenor basis | B22: BASIS_SWAP/BASIS_SPREAD/3M/6M/USD/10Y | C22: =MarketData!$E$203 -> USD-LIBOR-6M_BASIS_SWAP_BASIS_SPREAD_3M_6M_USD_10Y#0000 | E22: =_xll.qlTenorBasisSwapHelper("LIBOR6M_TBS_10Y",C22,"10Y",Indexes!$B$17,Indexes!$B$16,Indexes!$B$5,TRUE,FALSE,"6M","6M",TRUE,"Compounding",FALSE,TRUE,FALSE,'USD-FedFunds'!$B$32) -> LIBOR6M_TBS_10Y#0000 | F22: =_xll.ohRangeRetrieveError(E22)
A23: Tenor basis | B23: BASIS_SWAP/BASIS_SPREAD/3M/6M/USD/11Y | C23: =MarketData!$E$204 -> USD-LIBOR-6M_BASIS_SWAP_BASIS_SPREAD_3M_6M_USD_11Y#0000 | E23: =_xll.qlTenorBasisSwapHelper("LIBOR6M_TBS_11Y",C23,"11Y",Indexes!$B$17,Indexes!$B$16,Indexes!$B$5,TRUE,FALSE,"6M","6M",TRUE,"Compounding",FALSE,TRUE,FALSE,'USD-FedFunds'!$B$32) -> LIBOR6M_TBS_11Y#0000 | F23: =_xll.ohRangeRetrieveError(E23)
A24: Tenor basis | B24: BASIS_SWAP/BASIS_SPREAD/3M/6M/USD/12Y | C24: =MarketData!$E$205 -> USD-LIBOR-6M_BASIS_SWAP_BASIS_SPREAD_3M_6M_USD_12Y#0000 | E24: =_xll.qlTenorBasisSwapHelper("LIBOR6M_TBS_12Y",C24,"12Y",Indexes!$B$17,Indexes!$B$16,Indexes!$B$5,TRUE,FALSE,"6M","6M",TRUE,"Compounding",FALSE,TRUE,FALSE,'USD-FedFunds'!$B$32) -> LIBOR6M_TBS_12Y#0000 | F24: =_xll.ohRangeRetrieveError(E24)
A25: Tenor basis | B25: BASIS_SWAP/BASIS_SPREAD/3M/6M/USD/15Y | C25: =MarketData!$E$206 -> USD-LIBOR-6M_BASIS_SWAP_BASIS_SPREAD_3M_6M_USD_15Y#0000 | E25: =_xll.qlTenorBasisSwapHelper("LIBOR6M_TBS_15Y",C25,"15Y",Indexes!$B$17,Indexes!$B$16,Indexes!$B$5,TRUE,FALSE,"6M","6M",TRUE,"Compounding",FALSE,TRUE,FALSE,'USD-FedFunds'!$B$32) -> LIBOR6M_TBS_15Y#0000 | F25: =_xll.ohRangeRetrieveError(E25)
A26: Tenor basis | B26: BASIS_SWAP/BASIS_SPREAD/3M/6M/USD/20Y | C26: =MarketData!$E$207 -> USD-LIBOR-6M_BASIS_SWAP_BASIS_SPREAD_3M_6M_USD_20Y#0000 | E26: =_xll.qlTenorBasisSwapHelper("LIBOR6M_TBS_20Y",C26,"20Y",Indexes!$B$17,Indexes!$B$16,Indexes!$B$5,TRUE,FALSE,"6M","6M",TRUE,"Compounding",FALSE,TRUE,FALSE,'USD-FedFunds'!$B$32) -> LIBOR6M_TBS_20Y#0000 | F26: =_xll.ohRangeRetrieveError(E26)
A27: Tenor basis | B27: BASIS_SWAP/BASIS_SPREAD/3M/6M/USD/25Y | C27: =MarketData!$E$208 -> USD-LIBOR-6M_BASIS_SWAP_BASIS_SPREAD_3M_6M_USD_25Y#0000 | E27: =_xll.qlTenorBasisSwapHelper("LIBOR6M_TBS_25Y",C27,"25Y",Indexes!$B$17,Indexes!$B$16,Indexes!$B$5,TRUE,FALSE,"6M","6M",TRUE,"Compounding",FALSE,TRUE,FALSE,'USD-FedFunds'!$B$32) -> LIBOR6M_TBS_25Y#0000 | F27: =_xll.ohRangeRetrieveError(E27)
A28: Tenor basis | B28: BASIS_SWAP/BASIS_SPREAD/3M/6M/USD/30Y | C28: =MarketData!$E$209 -> USD-LIBOR-6M_BASIS_SWAP_BASIS_SPREAD_3M_6M_USD_30Y#0000 | E28: =_xll.qlTenorBasisSwapHelper("LIBOR6M_TBS_30Y",C28,"30Y",Indexes!$B$17,Indexes!$B$16,Indexes!$B$5,TRUE,FALSE,"6M","6M",TRUE,"Compounding",FALSE,TRUE,FALSE,'USD-FedFunds'!$B$32) -> LIBOR6M_TBS_30Y#0000 | F28: =_xll.ohRangeRetrieveError(E28)
A30: Curve | B30: =_xll.qlPiecewiseYieldCurve("C_USD-LIBOR-6M",0,"UnitedKingdom::Exchange",E5:E28,"Actual/365 (Fixed)",,,"Discount","LogLinear",FALSE,Indexes!$B$31) -> C_USD-LIBOR-6M#0000 | C30: =_xll.ohRangeRetrieveError(B30) | D30: =_xll.qlExtrapolatorEnableExtrapolation(B30,TRUE) -> TRUE
A31: Link handle H_USD-LIBOR-6M | B31: =_xll.qlRelinkableHandleLinkTo(Indexes!$B$8,B30,D30) -> TRUE | C31: =_xll.ohRangeRetrieveError(B31)
A33: Date | B33: ORE discount factor | C33: Excel discount factor | D33: Difference | E33: Rel. difference
A34: =DATE(2020,7,2) -> 44014 | B34: 0.99028566 | C34: =_xll.qlYieldTSDiscount($B$30,A34,TRUE,$B$31) -> 0.99028566 | D34: =C34-B34 -> 0 | E34: =D34/B34 -> 0
A35: =DATE(2020,8,3) -> 44046 | B35: 0.98911889 | C35: =_xll.qlYieldTSDiscount($B$30,A35,TRUE,$B$31) -> 0.98911889 | D35: =C35-B35 -> 0 | E35: =D35/B35 -> 0
A36: =DATE(2020,9,2) -> 44076 | B36: 0.98780546 | C36: =_xll.qlYieldTSDiscount($B$30,A36,TRUE,$B$31) -> 0.98780546 | D36: =C36-B36 -> 0 | E36: =D36/B36 -> 0
A37: =DATE(2020,10,2) -> 44106 | B37: 0.9863182 | C37: =_xll.qlYieldTSDiscount($B$30,A37,TRUE,$B$31) -> 0.9863182 | D37: =C37-B37 -> 0 | E37: =D37/B37 -> 0
A38: =DATE(2020,11,4) -> 44139 | B38: 0.98473167 | C38: =_xll.qlYieldTSDiscount($B$30,A38,TRUE,$B$31) -> 0.98473167 | D38: =C38-B38 -> 0 | E38: =D38/B38 -> 0
A39: =DATE(2020,12,2) -> 44167 | B39: 0.98335173 | C39: =_xll.qlYieldTSDiscount($B$30,A39,TRUE,$B$31) -> 0.98335173 | D39: =C39-B39 -> 0 | E39: =D39/B39 -> 0
A40: =DATE(2021,1,4) -> 44200 | B40: 0.98172372 | C40: =_xll.qlYieldTSDiscount($B$30,A40,TRUE,$B$31) -> 0.98172372 | D40: =C40-B40 -> 0 | E40: =D40/B40 -> 0
A41: =DATE(2021,4,6) -> 44292 | B41: 0.97798092 | C41: =_xll.qlYieldTSDiscount($B$30,A41,TRUE,$B$31) -> 0.97798092 | D41: =C41-B41 -> 0 | E41: =D41/B41 -> 0
A42: =DATE(2021,7,5) -> 44382 | B42: 0.97374384 | C42: =_xll.qlYieldTSDiscount($B$30,A42,TRUE,$B$31) -> 0.97374384 | D42: =C42-B42 -> 0 | E42: =D42/B42 -> 0
A43: =DATE(2022,1,4) -> 44565 | B43: 0.96530276 | C43: =_xll.qlYieldTSDiscount($B$30,A43,TRUE,$B$31) -> 0.96530276 | D43: =C43-B43 -> 0 | E43: =D43/B43 -> 0
A44: =DATE(2023,1,3) -> 44929 | B44: 0.94972184 | C44: =_xll.qlYieldTSDiscount($B$30,A44,TRUE,$B$31) -> 0.94972184 | D44: =C44-B44 -> 0 | E44: =D44/B44 -> 0
A45: =DATE(2024,1,2) -> 45293 | B45: 0.93314267 | C45: =_xll.qlYieldTSDiscount($B$30,A45,TRUE,$B$31) -> 0.93314267 | D45: =C45-B45 -> 0 | E45: =D45/B45 -> 0
A46: =DATE(2025,1,2) -> 45659 | B46: 0.91655572 | C46: =_xll.qlYieldTSDiscount($B$30,A46,TRUE,$B$31) -> 0.91655572 | D46: =C46-B46 -> 0 | E46: =D46/B46 -> 0
A47: =DATE(2026,1,2) -> 46024 | B47: 0.89893411 | C47: =_xll.qlYieldTSDiscount($B$30,A47,TRUE,$B$31) -> 0.89893411 | D47: =C47-B47 -> 0 | E47: =D47/B47 -> 0
A48: =DATE(2027,1,4) -> 46391 | B48: 0.88070929 | C48: =_xll.qlYieldTSDiscount($B$30,A48,TRUE,$B$31) -> 0.88070929 | D48: =C48-B48 -> 0 | E48: =D48/B48 -> 0
A49: =DATE(2028,1,4) -> 46756 | B49: 0.8623682 | C49: =_xll.qlYieldTSDiscount($B$30,A49,TRUE,$B$31) -> 0.8623682 | D49: =C49-B49 -> 0 | E49: =D49/B49 -> 0
A50: =DATE(2029,1,2) -> 47120 | B50: 0.84493937 | C50: =_xll.qlYieldTSDiscount($B$30,A50,TRUE,$B$31) -> 0.84493937 | D50: =C50-B50 -> 0 | E50: =D50/B50 -> 0
A51: =DATE(2030,1,2) -> 47485 | B51: 0.82545812 | C51: =_xll.qlYieldTSDiscount($B$30,A51,TRUE,$B$31) -> 0.82545812 | D51: =C51-B51 -> 0 | E51: =D51/B51 -> 0
A52: =DATE(2031,1,2) -> 47850 | B52: 0.80739586 | C52: =_xll.qlYieldTSDiscount($B$30,A52,TRUE,$B$31) -> 0.80739586 | D52: =C52-B52 -> 0 | E52: =D52/B52 -> 0
A53: =DATE(2032,1,2) -> 48215 | B53: 0.78975114 | C53: =_xll.qlYieldTSDiscount($B$30,A53,TRUE,$B$31) -> 0.78975114 | D53: =C53-B53 -> 0 | E53: =D53/B53 -> 0
A54: =DATE(2035,1,2) -> 49311 | B54: 0.73774037 | C54: =_xll.qlYieldTSDiscount($B$30,A54,TRUE,$B$31) -> 0.73774037 | D54: =C54-B54 -> 0 | E54: =D54/B54 -> 0
A55: =DATE(2040,1,3) -> 51138 | B55: 0.65830882 | C55: =_xll.qlYieldTSDiscount($B$30,A55,TRUE,$B$31) -> 0.65830882 | D55: =C55-B55 -> 0 | E55: =D55/B55 -> 0
A56: =DATE(2045,1,3) -> 52965 | B56: 0.58962482 | C56: =_xll.qlYieldTSDiscount($B$30,A56,TRUE,$B$31) -> 0.58962482 | D56: =C56-B56 -> 0 | E56: =D56/B56 -> 0
A57: =DATE(2050,1,4) -> 54792 | B57: 0.52989254 | C57: =_xll.qlYieldTSDiscount($B$30,A57,TRUE,$B$31) -> 0.52989254 | D57: =C57-B57 -> -8.8817842e-16 | E57: =D57/B57 -> -1.6761482e-15
A59: Max abs difference | D59: =MAX(ABS(MIN(D34:D57)),ABS(MAX(D34:D57))) -> 8.8817842e-16

Sheet EUR-EURIBOR-6M
A1: EUR-EURIBOR-6M: Discount/LogLinear, A365, extrapolation; discount curve EUR-EONIA; deposit 6M, FRAs, swaps
A2: EUR-EURIBOR-6M-SWAP: fixed calendar TARGET, Annual, MF, 30/360 (USA); float index EUR-EURIBOR-6M.
A4: Segment | B4: Quote | C4: Rate | E4: Helper | F4: Error
A5: Deposit | B5: MM/RATE/EUR/2D/6M | C5: =MarketData!$E$68 -> EUR-EURIBOR-6M_MM_RATE_EUR_2D_6M#0000 | E5: =_xll.qlDepositRateHelper2("EURIBOR6M_DEP",C5,"6M",2,"TARGET","Modified Following",TRUE,"Actual/360",FALSE,Indexes!$B$31) -> EURIBOR6M_DEP#0000 | F5: =_xll.ohRangeRetrieveError(E5)
A6: FRA | B6: FRA/RATE/EUR/1M/6M | C6: =MarketData!$E$69 -> EUR-EURIBOR-6M_FRA_RATE_EUR_1M_6M#0000 | E6: =_xll.qlFraRateHelper("EURIBOR6M_FRA_1M",C6,"1M",Indexes!$B$19,"LastRelevantDate",,FALSE,Indexes!$B$31) -> EURIBOR6M_FRA_1M#0000 | F6: =_xll.ohRangeRetrieveError(E6)
A7: FRA | B7: FRA/RATE/EUR/2M/6M | C7: =MarketData!$E$70 -> EUR-EURIBOR-6M_FRA_RATE_EUR_2M_6M#0000 | E7: =_xll.qlFraRateHelper("EURIBOR6M_FRA_2M",C7,"2M",Indexes!$B$19,"LastRelevantDate",,FALSE,Indexes!$B$31) -> EURIBOR6M_FRA_2M#0000 | F7: =_xll.ohRangeRetrieveError(E7)
A8: FRA | B8: FRA/RATE/EUR/3M/6M | C8: =MarketData!$E$71 -> EUR-EURIBOR-6M_FRA_RATE_EUR_3M_6M#0000 | E8: =_xll.qlFraRateHelper("EURIBOR6M_FRA_3M",C8,"3M",Indexes!$B$19,"LastRelevantDate",,FALSE,Indexes!$B$31) -> EURIBOR6M_FRA_3M#0000 | F8: =_xll.ohRangeRetrieveError(E8)
A9: FRA | B9: FRA/RATE/EUR/4M/6M | C9: =MarketData!$E$72 -> EUR-EURIBOR-6M_FRA_RATE_EUR_4M_6M#0000 | E9: =_xll.qlFraRateHelper("EURIBOR6M_FRA_4M",C9,"4M",Indexes!$B$19,"LastRelevantDate",,FALSE,Indexes!$B$31) -> EURIBOR6M_FRA_4M#0000 | F9: =_xll.ohRangeRetrieveError(E9)
A10: FRA | B10: FRA/RATE/EUR/5M/6M | C10: =MarketData!$E$73 -> EUR-EURIBOR-6M_FRA_RATE_EUR_5M_6M#0000 | E10: =_xll.qlFraRateHelper("EURIBOR6M_FRA_5M",C10,"5M",Indexes!$B$19,"LastRelevantDate",,FALSE,Indexes!$B$31) -> EURIBOR6M_FRA_5M#0000 | F10: =_xll.ohRangeRetrieveError(E10)
A11: FRA | B11: FRA/RATE/EUR/6M/6M | C11: =MarketData!$E$74 -> EUR-EURIBOR-6M_FRA_RATE_EUR_6M_6M#0000 | E11: =_xll.qlFraRateHelper("EURIBOR6M_FRA_6M",C11,"6M",Indexes!$B$19,"LastRelevantDate",,FALSE,Indexes!$B$31) -> EURIBOR6M_FRA_6M#0000 | F11: =_xll.ohRangeRetrieveError(E11)
A12: FRA | B12: FRA/RATE/EUR/9M/6M | C12: =MarketData!$E$75 -> EUR-EURIBOR-6M_FRA_RATE_EUR_9M_6M#0000 | E12: =_xll.qlFraRateHelper("EURIBOR6M_FRA_9M",C12,"9M",Indexes!$B$19,"LastRelevantDate",,FALSE,Indexes!$B$31) -> EURIBOR6M_FRA_9M#0000 | F12: =_xll.ohRangeRetrieveError(E12)
A13: FRA | B13: FRA/RATE/EUR/12M/6M | C13: =MarketData!$E$76 -> EUR-EURIBOR-6M_FRA_RATE_EUR_12M_6M#0000 | E13: =_xll.qlFraRateHelper("EURIBOR6M_FRA_12M",C13,"12M",Indexes!$B$19,"LastRelevantDate",,FALSE,Indexes!$B$31) -> EURIBOR6M_FRA_12M#0000 | F13: =_xll.ohRangeRetrieveError(E13)
A14: Swap | B14: IR_SWAP/RATE/EUR/2D/6M/2Y | C14: =MarketData!$E$77 -> EUR-EURIBOR-6M_IR_SWAP_RATE_EUR_2D_6M_2Y#0000 | E14: =_xll.qlSwapRateHelper2("EURIBOR6M_SWAP_2Y",C14,,"2Y","TARGET","Annual","Modified Following","30/360 (USA)",Indexes!$B$19,0,"0D",Indexes!$B$6,"LastRelevantDate",,FALSE,'EUR-EONIA'!$B$41) -> EURIBOR6M_SWAP_2Y#0000 | F14: =_xll.ohRangeRetrieveError(E14)
A15: Swap | B15: IR_SWAP/RATE/EUR/2D/6M/3Y | C15: =MarketData!$E$78 -> EUR-EURIBOR-6M_IR_SWAP_RATE_EUR_2D_6M_3Y#0000 | E15: =_xll.qlSwapRateHelper2("EURIBOR6M_SWAP_3Y",C15,,"3Y","TARGET","Annual","Modified Following","30/360 (USA)",Indexes!$B$19,0,"0D",Indexes!$B$6,"LastRelevantDate",,FALSE,'EUR-EONIA'!$B$41) -> EURIBOR6M_SWAP_3Y#0000 | F15: =_xll.ohRangeRetrieveError(E15)
A16: Swap | B16: IR_SWAP/RATE/EUR/2D/6M/4Y | C16: =MarketData!$E$79 -> EUR-EURIBOR-6M_IR_SWAP_RATE_EUR_2D_6M_4Y#0000 | E16: =_xll.qlSwapRateHelper2("EURIBOR6M_SWAP_4Y",C16,,"4Y","TARGET","Annual","Modified Following","30/360 (USA)",Indexes!$B$19,0,"0D",Indexes!$B$6,"LastRelevantDate",,FALSE,'EUR-EONIA'!$B$41) -> EURIBOR6M_SWAP_4Y#0000 | F16: =_xll.ohRangeRetrieveError(E16)
A17: Swap | B17: IR_SWAP/RATE/EUR/2D/6M/5Y | C17: =MarketData!$E$80 -> EUR-EURIBOR-6M_IR_SWAP_RATE_EUR_2D_6M_5Y#0000 | E17: =_xll.qlSwapRateHelper2("EURIBOR6M_SWAP_5Y",C17,,"5Y","TARGET","Annual","Modified Following","30/360 (USA)",Indexes!$B$19,0,"0D",Indexes!$B$6,"LastRelevantDate",,FALSE,'EUR-EONIA'!$B$41) -> EURIBOR6M_SWAP_5Y#0000 | F17: =_xll.ohRangeRetrieveError(E17)
A18: Swap | B18: IR_SWAP/RATE/EUR/2D/6M/6Y | C18: =MarketData!$E$81 -> EUR-EURIBOR-6M_IR_SWAP_RATE_EUR_2D_6M_6Y#0000 | E18: =_xll.qlSwapRateHelper2("EURIBOR6M_SWAP_6Y",C18,,"6Y","TARGET","Annual","Modified Following","30/360 (USA)",Indexes!$B$19,0,"0D",Indexes!$B$6,"LastRelevantDate",,FALSE,'EUR-EONIA'!$B$41) -> EURIBOR6M_SWAP_6Y#0000 | F18: =_xll.ohRangeRetrieveError(E18)
A19: Swap | B19: IR_SWAP/RATE/EUR/2D/6M/7Y | C19: =MarketData!$E$82 -> EUR-EURIBOR-6M_IR_SWAP_RATE_EUR_2D_6M_7Y#0000 | E19: =_xll.qlSwapRateHelper2("EURIBOR6M_SWAP_7Y",C19,,"7Y","TARGET","Annual","Modified Following","30/360 (USA)",Indexes!$B$19,0,"0D",Indexes!$B$6,"LastRelevantDate",,FALSE,'EUR-EONIA'!$B$41) -> EURIBOR6M_SWAP_7Y#0000 | F19: =_xll.ohRangeRetrieveError(E19)
A20: Swap | B20: IR_SWAP/RATE/EUR/2D/6M/8Y | C20: =MarketData!$E$83 -> EUR-EURIBOR-6M_IR_SWAP_RATE_EUR_2D_6M_8Y#0000 | E20: =_xll.qlSwapRateHelper2("EURIBOR6M_SWAP_8Y",C20,,"8Y","TARGET","Annual","Modified Following","30/360 (USA)",Indexes!$B$19,0,"0D",Indexes!$B$6,"LastRelevantDate",,FALSE,'EUR-EONIA'!$B$41) -> EURIBOR6M_SWAP_8Y#0000 | F20: =_xll.ohRangeRetrieveError(E20)
A21: Swap | B21: IR_SWAP/RATE/EUR/2D/6M/9Y | C21: =MarketData!$E$84 -> EUR-EURIBOR-6M_IR_SWAP_RATE_EUR_2D_6M_9Y#0000 | E21: =_xll.qlSwapRateHelper2("EURIBOR6M_SWAP_9Y",C21,,"9Y","TARGET","Annual","Modified Following","30/360 (USA)",Indexes!$B$19,0,"0D",Indexes!$B$6,"LastRelevantDate",,FALSE,'EUR-EONIA'!$B$41) -> EURIBOR6M_SWAP_9Y#0000 | F21: =_xll.ohRangeRetrieveError(E21)
A22: Swap | B22: IR_SWAP/RATE/EUR/2D/6M/10Y | C22: =MarketData!$E$85 -> EUR-EURIBOR-6M_IR_SWAP_RATE_EUR_2D_6M_10Y#0000 | E22: =_xll.qlSwapRateHelper2("EURIBOR6M_SWAP_10Y",C22,,"10Y","TARGET","Annual","Modified Following","30/360 (USA)",Indexes!$B$19,0,"0D",Indexes!$B$6,"LastRelevantDate",,FALSE,'EUR-EONIA'!$B$41) -> EURIBOR6M_SWAP_10Y#0000 | F22: =_xll.ohRangeRetrieveError(E22)
A23: Swap | B23: IR_SWAP/RATE/EUR/2D/6M/12Y | C23: =MarketData!$E$86 -> EUR-EURIBOR-6M_IR_SWAP_RATE_EUR_2D_6M_12Y#0000 | E23: =_xll.qlSwapRateHelper2("EURIBOR6M_SWAP_12Y",C23,,"12Y","TARGET","Annual","Modified Following","30/360 (USA)",Indexes!$B$19,0,"0D",Indexes!$B$6,"LastRelevantDate",,FALSE,'EUR-EONIA'!$B$41) -> EURIBOR6M_SWAP_12Y#0000 | F23: =_xll.ohRangeRetrieveError(E23)
A24: Swap | B24: IR_SWAP/RATE/EUR/2D/6M/15Y | C24: =MarketData!$E$87 -> EUR-EURIBOR-6M_IR_SWAP_RATE_EUR_2D_6M_15Y#0000 | E24: =_xll.qlSwapRateHelper2("EURIBOR6M_SWAP_15Y",C24,,"15Y","TARGET","Annual","Modified Following","30/360 (USA)",Indexes!$B$19,0,"0D",Indexes!$B$6,"LastRelevantDate",,FALSE,'EUR-EONIA'!$B$41) -> EURIBOR6M_SWAP_15Y#0000 | F24: =_xll.ohRangeRetrieveError(E24)
A25: Swap | B25: IR_SWAP/RATE/EUR/2D/6M/20Y | C25: =MarketData!$E$88 -> EUR-EURIBOR-6M_IR_SWAP_RATE_EUR_2D_6M_20Y#0000 | E25: =_xll.qlSwapRateHelper2("EURIBOR6M_SWAP_20Y",C25,,"20Y","TARGET","Annual","Modified Following","30/360 (USA)",Indexes!$B$19,0,"0D",Indexes!$B$6,"LastRelevantDate",,FALSE,'EUR-EONIA'!$B$41) -> EURIBOR6M_SWAP_20Y#0000 | F25: =_xll.ohRangeRetrieveError(E25)
A26: Swap | B26: IR_SWAP/RATE/EUR/2D/6M/25Y | C26: =MarketData!$E$89 -> EUR-EURIBOR-6M_IR_SWAP_RATE_EUR_2D_6M_25Y#0000 | E26: =_xll.qlSwapRateHelper2("EURIBOR6M_SWAP_25Y",C26,,"25Y","TARGET","Annual","Modified Following","30/360 (USA)",Indexes!$B$19,0,"0D",Indexes!$B$6,"LastRelevantDate",,FALSE,'EUR-EONIA'!$B$41) -> EURIBOR6M_SWAP_25Y#0000 | F26: =_xll.ohRangeRetrieveError(E26)
A27: Swap | B27: IR_SWAP/RATE/EUR/2D/6M/30Y | C27: =MarketData!$E$90 -> EUR-EURIBOR-6M_IR_SWAP_RATE_EUR_2D_6M_30Y#0000 | E27: =_xll.qlSwapRateHelper2("EURIBOR6M_SWAP_30Y",C27,,"30Y","TARGET","Annual","Modified Following","30/360 (USA)",Indexes!$B$19,0,"0D",Indexes!$B$6,"LastRelevantDate",,FALSE,'EUR-EONIA'!$B$41) -> EURIBOR6M_SWAP_30Y#0000 | F27: =_xll.ohRangeRetrieveError(E27)
A28: Swap | B28: IR_SWAP/RATE/EUR/2D/6M/40Y | C28: =MarketData!$E$91 -> EUR-EURIBOR-6M_IR_SWAP_RATE_EUR_2D_6M_40Y#0000 | E28: =_xll.qlSwapRateHelper2("EURIBOR6M_SWAP_40Y",C28,,"40Y","TARGET","Annual","Modified Following","30/360 (USA)",Indexes!$B$19,0,"0D",Indexes!$B$6,"LastRelevantDate",,FALSE,'EUR-EONIA'!$B$41) -> EURIBOR6M_SWAP_40Y#0000 | F28: =_xll.ohRangeRetrieveError(E28)
A29: Swap | B29: IR_SWAP/RATE/EUR/2D/6M/50Y | C29: =MarketData!$E$92 -> EUR-EURIBOR-6M_IR_SWAP_RATE_EUR_2D_6M_50Y#0000 | E29: =_xll.qlSwapRateHelper2("EURIBOR6M_SWAP_50Y",C29,,"50Y","TARGET","Annual","Modified Following","30/360 (USA)",Indexes!$B$19,0,"0D",Indexes!$B$6,"LastRelevantDate",,FALSE,'EUR-EONIA'!$B$41) -> EURIBOR6M_SWAP_50Y#0000 | F29: =_xll.ohRangeRetrieveError(E29)
A31: Curve | B31: =_xll.qlPiecewiseYieldCurve("C_EUR-EURIBOR-6M",0,"TARGET",E5:E29,"Actual/365 (Fixed)",,,"Discount","LogLinear",FALSE,Indexes!$B$31) -> C_EUR-EURIBOR-6M#0000 | C31: =_xll.ohRangeRetrieveError(B31) | D31: =_xll.qlExtrapolatorEnableExtrapolation(B31,TRUE) -> TRUE
A32: Link handle H_EUR-EURIBOR-6M | B32: =_xll.qlRelinkableHandleLinkTo(Indexes!$B$9,B31,D31) -> TRUE | C32: =_xll.ohRangeRetrieveError(B32)
A34: Date | B34: ORE discount factor | C34: Excel discount factor | D34: Difference | E34: Rel. difference
A35: =DATE(2020,7,2) -> 44014 | B35: 1.0016729 | C35: =_xll.qlYieldTSDiscount($B$31,A35,TRUE,$B$32) -> 1.0016729 | D35: =C35-B35 -> 0 | E35: =D35/B35 -> 0
A36: =DATE(2020,8,3) -> 44046 | B36: 1.0019981 | C36: =_xll.qlYieldTSDiscount($B$31,A36,TRUE,$B$32) -> 1.0019981 | D36: =C36-B36 -> 0 | E36: =D36/B36 -> 0
A37: =DATE(2020,9,2) -> 44076 | B37: 1.0022547 | C37: =_xll.qlYieldTSDiscount($B$31,A37,TRUE,$B$32) -> 1.0022547 | D37: =C37-B37 -> 0 | E37: =D37/B37 -> 0
A38: =DATE(2020,10,2) -> 44106 | B38: 1.0025314 | C38: =_xll.qlYieldTSDiscount($B$31,A38,TRUE,$B$32) -> 1.0025314 | D38: =C38-B38 -> 0 | E38: =D38/B38 -> 0
A39: =DATE(2020,11,4) -> 44139 | B39: 1.0028203 | C39: =_xll.qlYieldTSDiscount($B$31,A39,TRUE,$B$32) -> 1.0028203 | D39: =C39-B39 -> 0 | E39: =D39/B39 -> 0
A40: =DATE(2020,12,2) -> 44167 | B40: 1.003033 | C40: =_xll.qlYieldTSDiscount($B$31,A40,TRUE,$B$32) -> 1.003033 | D40: =C40-B40 -> 0 | E40: =D40/B40 -> 0
A41: =DATE(2021,1,4) -> 44200 | B41: 1.0033318 | C41: =_xll.qlYieldTSDiscount($B$31,A41,TRUE,$B$32) -> 1.0033318 | D41: =C41-B41 -> 0 | E41: =D41/B41 -> 0
A42: =DATE(2021,4,6) -> 44292 | B42: 1.0041397 | C42: =_xll.qlYieldTSDiscount($B$31,A42,TRUE,$B$32) -> 1.0041397 | D42: =C42-B42 -> 0 | E42: =D42/B42 -> 0
A43: =DATE(2021,7,5) -> 44382 | B43: 1.0048049 | C43: =_xll.qlYieldTSDiscount($B$31,A43,TRUE,$B$32) -> 1.0048049 | D43: =C43-B43 -> 0 | E43: =D43/B43 -> 0
A44: =DATE(2022,1,3) -> 44564 | B44: 1.0060903 | C44: =_xll.qlYieldTSDiscount($B$31,A44,TRUE,$B$32) -> 1.0060903 | D44: =C44-B44 -> 0 | E44: =D44/B44 -> 0
A45: =DATE(2023,1,2) -> 44928 | B45: 1.007319 | C45: =_xll.qlYieldTSDiscount($B$31,A45,TRUE,$B$32) -> 1.007319 | D45: =C45-B45 -> 0 | E45: =D45/B45 -> 0
A46: =DATE(2024,1,2) -> 45293 | B46: 1.007726 | C46: =_xll.qlYieldTSDiscount($B$31,A46,TRUE,$B$32) -> 1.007726 | D46: =C46-B46 -> 0 | E46: =D46/B46 -> 0
A47: =DATE(2025,1,2) -> 45659 | B47: 1.00659 | C47: =_xll.qlYieldTSDiscount($B$31,A47,TRUE,$B$32) -> 1.00659 | D47: =C47-B47 -> 0 | E47: =D47/B47 -> 0
A48: =DATE(2026,1,2) -> 46024 | B48: 1.0041692 | C48: =_xll.qlYieldTSDiscount($B$31,A48,TRUE,$B$32) -> 1.0041692 | D48: =C48-B48 -> 0 | E48: =D48/B48 -> 0
A49: =DATE(2027,1,4) -> 46391 | B49: 0.99936249 | C49: =_xll.qlYieldTSDiscount($B$31,A49,TRUE,$B$32) -> 0.99936249 | D49: =C49-B49 -> 0 | E49: =D49/B49 -> 0
A50: =DATE(2028,1,3) -> 46755 | B50: 0.99513847 | C50: =_xll.qlYieldTSDiscount($B$31,A50,TRUE,$B$32) -> 0.99513847 | D50: =C50-B50 -> 0 | E50: =D50/B50 -> 0
A51: =DATE(2029,1,2) -> 47120 | B51: 0.98757992 | C51: =_xll.qlYieldTSDiscount($B$31,A51,TRUE,$B$32) -> 0.98757992 | D51: =C51-B51 -> 0 | E51: =D51/B51 -> 0
A52: =DATE(2030,1,2) -> 47485 | B52: 0.98006218 | C52: =_xll.qlYieldTSDiscount($B$31,A52,TRUE,$B$32) -> 0.98006218 | D52: =C52-B52 -> 0 | E52: =D52/B52 -> 0
A53: =DATE(2032,1,2) -> 48215 | B53: 0.96252159 | C53: =_xll.qlYieldTSDiscount($B$31,A53,TRUE,$B$32) -> 0.96252159 | D53: =C53-B53 -> 0 | E53: =D53/B53 -> 0
A54: =DATE(2035,1,2) -> 49311 | B54: 0.93261374 | C54: =_xll.qlYieldTSDiscount($B$31,A54,TRUE,$B$32) -> 0.93261374 | D54: =C54-B54 -> 0 | E54: =D54/B54 -> 0
A55: =DATE(2040,1,2) -> 51137 | B55: 0.88700653 | C55: =_xll.qlYieldTSDiscount($B$31,A55,TRUE,$B$32) -> 0.88700653 | D55: =C55-B55 -> 0 | E55: =D55/B55 -> 0
A56: =DATE(2045,1,2) -> 52964 | B56: 0.8521961 | C56: =_xll.qlYieldTSDiscount($B$31,A56,TRUE,$B$32) -> 0.8521961 | D56: =C56-B56 -> 0 | E56: =D56/B56 -> 0
A57: =DATE(2050,1,3) -> 54791 | B57: 0.82738321 | C57: =_xll.qlYieldTSDiscount($B$31,A57,TRUE,$B$32) -> 0.82738321 | D57: =C57-B57 -> 0 | E57: =D57/B57 -> 0
A58: =DATE(2060,1,2) -> 58442 | B58: 0.79397148 | C58: =_xll.qlYieldTSDiscount($B$31,A58,TRUE,$B$32) -> 0.79397148 | D58: =C58-B58 -> 0 | E58: =D58/B58 -> 0
A59: =DATE(2070,1,2) -> 62095 | B59: 0.77545202 | C59: =_xll.qlYieldTSDiscount($B$31,A59,TRUE,$B$32) -> 0.77545202 | D59: =C59-B59 -> 0 | E59: =D59/B59 -> 0
A61: Max abs difference | D61: =MAX(ABS(MIN(D35:D59)),ABS(MAX(D35:D59))) -> 0

Sheet EUR-EURIBOR-3M
A1: EUR-EURIBOR-3M: Discount/LogLinear, A365, extrapolation; discount curve EUR-EONIA; deposit 3M, FRAs, 3M/6M basis two swaps
A2: EURIBOR-3M-6M-BASIS: TARGET, Annual/MF/30/360 fixed on both swaps; long index EUR-EURIBOR-6M (given), short index EUR-EURIBOR-3M (bootstrapped), long minus short.
A4: Segment | B4: Quote | C4: Rate | E4: Helper | F4: Error
A5: Deposit | B5: MM/RATE/EUR/2D/3M | C5: =MarketData!$E$41 -> EUR-EURIBOR-3M_MM_RATE_EUR_2D_3M#0000 | E5: =_xll.qlDepositRateHelper2("EURIBOR3M_DEP",C5,"3M",2,"TARGET","Modified Following",TRUE,"Actual/360",FALSE,Indexes!$B$31) -> EURIBOR3M_DEP#0000 | F5: =_xll.ohRangeRetrieveError(E5)
A6: FRA | B6: FRA/RATE/EUR/1M/3M | C6: =MarketData!$E$42 -> EUR-EURIBOR-3M_FRA_RATE_EUR_1M_3M#0000 | E6: =_xll.qlFraRateHelper("EURIBOR3M_FRA_1M",C6,"1M",Indexes!$B$18,"LastRelevantDate",,FALSE,Indexes!$B$31) -> EURIBOR3M_FRA_1M#0000 | F6: =_xll.ohRangeRetrieveError(E6)
A7: FRA | B7: FRA/RATE/EUR/2M/3M | C7: =MarketData!$E$43 -> EUR-EURIBOR-3M_FRA_RATE_EUR_2M_3M#0000 | E7: =_xll.qlFraRateHelper("EURIBOR3M_FRA_2M",C7,"2M",Indexes!$B$18,"LastRelevantDate",,FALSE,Indexes!$B$31) -> EURIBOR3M_FRA_2M#0000 | F7: =_xll.ohRangeRetrieveError(E7)
A8: FRA | B8: FRA/RATE/EUR/3M/3M | C8: =MarketData!$E$44 -> EUR-EURIBOR-3M_FRA_RATE_EUR_3M_3M#0000 | E8: =_xll.qlFraRateHelper("EURIBOR3M_FRA_3M",C8,"3M",Indexes!$B$18,"LastRelevantDate",,FALSE,Indexes!$B$31) -> EURIBOR3M_FRA_3M#0000 | F8: =_xll.ohRangeRetrieveError(E8)
A9: FRA | B9: FRA/RATE/EUR/4M/3M | C9: =MarketData!$E$45 -> EUR-EURIBOR-3M_FRA_RATE_EUR_4M_3M#0000 | E9: =_xll.qlFraRateHelper("EURIBOR3M_FRA_4M",C9,"4M",Indexes!$B$18,"LastRelevantDate",,FALSE,Indexes!$B$31) -> EURIBOR3M_FRA_4M#0000 | F9: =_xll.ohRangeRetrieveError(E9)
A10: FRA | B10: FRA/RATE/EUR/5M/3M | C10: =MarketData!$E$46 -> EUR-EURIBOR-3M_FRA_RATE_EUR_5M_3M#0000 | E10: =_xll.qlFraRateHelper("EURIBOR3M_FRA_5M",C10,"5M",Indexes!$B$18,"LastRelevantDate",,FALSE,Indexes!$B$31) -> EURIBOR3M_FRA_5M#0000 | F10: =_xll.ohRangeRetrieveError(E10)
A11: FRA | B11: FRA/RATE/EUR/6M/3M | C11: =MarketData!$E$47 -> EUR-EURIBOR-3M_FRA_RATE_EUR_6M_3M#0000 | E11: =_xll.qlFraRateHelper("EURIBOR3M_FRA_6M",C11,"6M",Indexes!$B$18,"LastRelevantDate",,FALSE,Indexes!$B$31) -> EURIBOR3M_FRA_6M#0000 | F11: =_xll.ohRangeRetrieveError(E11)
A12: FRA | B12: FRA/RATE/EUR/7M/3M | C12: =MarketData!$E$48 -> EUR-EURIBOR-3M_FRA_RATE_EUR_7M_3M#0000 | E12: =_xll.qlFraRateHelper("EURIBOR3M_FRA_7M",C12,"7M",Indexes!$B$18,"LastRelevantDate",,FALSE,Indexes!$B$31) -> EURIBOR3M_FRA_7M#0000 | F12: =_xll.ohRangeRetrieveError(E12)
A13: FRA | B13: FRA/RATE/EUR/8M/3M | C13: =MarketData!$E$49 -> EUR-EURIBOR-3M_FRA_RATE_EUR_8M_3M#0000 | E13: =_xll.qlFraRateHelper("EURIBOR3M_FRA_8M",C13,"8M",Indexes!$B$18,"LastRelevantDate",,FALSE,Indexes!$B$31) -> EURIBOR3M_FRA_8M#0000 | F13: =_xll.ohRangeRetrieveError(E13)
A14: FRA | B14: FRA/RATE/EUR/9M/3M | C14: =MarketData!$E$50 -> EUR-EURIBOR-3M_FRA_RATE_EUR_9M_3M#0000 | E14: =_xll.qlFraRateHelper("EURIBOR3M_FRA_9M",C14,"9M",Indexes!$B$18,"LastRelevantDate",,FALSE,Indexes!$B$31) -> EURIBOR3M_FRA_9M#0000 | F14: =_xll.ohRangeRetrieveError(E14)
A15: FRA | B15: FRA/RATE/EUR/12M/3M | C15: =MarketData!$E$51 -> EUR-EURIBOR-3M_FRA_RATE_EUR_12M_3M#0000 | E15: =_xll.qlFraRateHelper("EURIBOR3M_FRA_12M",C15,"12M",Indexes!$B$18,"LastRelevantDate",,FALSE,Indexes!$B$31) -> EURIBOR3M_FRA_12M#0000 | F15: =_xll.ohRangeRetrieveError(E15)
A16: FRA | B16: FRA/RATE/EUR/15M/3M | C16: =MarketData!$E$52 -> EUR-EURIBOR-3M_FRA_RATE_EUR_15M_3M#0000 | E16: =_xll.qlFraRateHelper("EURIBOR3M_FRA_15M",C16,"15M",Indexes!$B$18,"LastRelevantDate",,FALSE,Indexes!$B$31) -> EURIBOR3M_FRA_15M#0000 | F16: =_xll.ohRangeRetrieveError(E16)
A17: FRA | B17: FRA/RATE/EUR/18M/3M | C17: =MarketData!$E$53 -> EUR-EURIBOR-3M_FRA_RATE_EUR_18M_3M#0000 | E17: =_xll.qlFraRateHelper("EURIBOR3M_FRA_18M",C17,"18M",Indexes!$B$18,"LastRelevantDate",,FALSE,Indexes!$B$31) -> EURIBOR3M_FRA_18M#0000 | F17: =_xll.ohRangeRetrieveError(E17)
A18: Basis two swaps | B18: BASIS_SWAP/BASIS_SPREAD/3M/6M/EUR/2Y | C18: =MarketData!$E$54 -> EUR-EURIBOR-3M_BASIS_SWAP_BASIS_SPREAD_3M_6M_EUR_2Y#0000 | E18: =_xll.qlBasisTwoSwapHelper("EURIBOR3M_B2S_2Y",C18,"2Y","TARGET","Annual","Modified Following","30/360 (USA)",Indexes!$B$19,"Annual","Modified Following","30/360 (USA)",Indexes!$B$18,TRUE,Indexes!$B$6,TRUE,FALSE,FALSE,'EUR-EURIBOR-6M'!$B$32) -> EURIBOR3M_B2S_2Y#0000 | F18: =_xll.ohRangeRetrieveError(E18)
A19: Basis two swaps | B19: BASIS_SWAP/BASIS_SPREAD/3M/6M/EUR/3Y | C19: =MarketData!$E$55 -> EUR-EURIBOR-3M_BASIS_SWAP_BASIS_SPREAD_3M_6M_EUR_3Y#0000 | E19: =_xll.qlBasisTwoSwapHelper("EURIBOR3M_B2S_3Y",C19,"3Y","TARGET","Annual","Modified Following","30/360 (USA)",Indexes!$B$19,"Annual","Modified Following","30/360 (USA)",Indexes!$B$18,TRUE,Indexes!$B$6,TRUE,FALSE,FALSE,'EUR-EURIBOR-6M'!$B$32) -> EURIBOR3M_B2S_3Y#0000 | F19: =_xll.ohRangeRetrieveError(E19)
A20: Basis two swaps | B20: BASIS_SWAP/BASIS_SPREAD/3M/6M/EUR/4Y | C20: =MarketData!$E$56 -> EUR-EURIBOR-3M_BASIS_SWAP_BASIS_SPREAD_3M_6M_EUR_4Y#0000 | E20: =_xll.qlBasisTwoSwapHelper("EURIBOR3M_B2S_4Y",C20,"4Y","TARGET","Annual","Modified Following","30/360 (USA)",Indexes!$B$19,"Annual","Modified Following","30/360 (USA)",Indexes!$B$18,TRUE,Indexes!$B$6,TRUE,FALSE,FALSE,'EUR-EURIBOR-6M'!$B$32) -> EURIBOR3M_B2S_4Y#0000 | F20: =_xll.ohRangeRetrieveError(E20)
A21: Basis two swaps | B21: BASIS_SWAP/BASIS_SPREAD/3M/6M/EUR/5Y | C21: =MarketData!$E$57 -> EUR-EURIBOR-3M_BASIS_SWAP_BASIS_SPREAD_3M_6M_EUR_5Y#0000 | E21: =_xll.qlBasisTwoSwapHelper("EURIBOR3M_B2S_5Y",C21,"5Y","TARGET","Annual","Modified Following","30/360 (USA)",Indexes!$B$19,"Annual","Modified Following","30/360 (USA)",Indexes!$B$18,TRUE,Indexes!$B$6,TRUE,FALSE,FALSE,'EUR-EURIBOR-6M'!$B$32) -> EURIBOR3M_B2S_5Y#0000 | F21: =_xll.ohRangeRetrieveError(E21)
A22: Basis two swaps | B22: BASIS_SWAP/BASIS_SPREAD/3M/6M/EUR/6Y | C22: =MarketData!$E$58 -> EUR-EURIBOR-3M_BASIS_SWAP_BASIS_SPREAD_3M_6M_EUR_6Y#0000 | E22: =_xll.qlBasisTwoSwapHelper("EURIBOR3M_B2S_6Y",C22,"6Y","TARGET","Annual","Modified Following","30/360 (USA)",Indexes!$B$19,"Annual","Modified Following","30/360 (USA)",Indexes!$B$18,TRUE,Indexes!$B$6,TRUE,FALSE,FALSE,'EUR-EURIBOR-6M'!$B$32) -> EURIBOR3M_B2S_6Y#0000 | F22: =_xll.ohRangeRetrieveError(E22)
A23: Basis two swaps | B23: BASIS_SWAP/BASIS_SPREAD/3M/6M/EUR/7Y | C23: =MarketData!$E$59 -> EUR-EURIBOR-3M_BASIS_SWAP_BASIS_SPREAD_3M_6M_EUR_7Y#0000 | E23: =_xll.qlBasisTwoSwapHelper("EURIBOR3M_B2S_7Y",C23,"7Y","TARGET","Annual","Modified Following","30/360 (USA)",Indexes!$B$19,"Annual","Modified Following","30/360 (USA)",Indexes!$B$18,TRUE,Indexes!$B$6,TRUE,FALSE,FALSE,'EUR-EURIBOR-6M'!$B$32) -> EURIBOR3M_B2S_7Y#0000 | F23: =_xll.ohRangeRetrieveError(E23)
A24: Basis two swaps | B24: BASIS_SWAP/BASIS_SPREAD/3M/6M/EUR/8Y | C24: =MarketData!$E$60 -> EUR-EURIBOR-3M_BASIS_SWAP_BASIS_SPREAD_3M_6M_EUR_8Y#0000 | E24: =_xll.qlBasisTwoSwapHelper("EURIBOR3M_B2S_8Y",C24,"8Y","TARGET","Annual","Modified Following","30/360 (USA)",Indexes!$B$19,"Annual","Modified Following","30/360 (USA)",Indexes!$B$18,TRUE,Indexes!$B$6,TRUE,FALSE,FALSE,'EUR-EURIBOR-6M'!$B$32) -> EURIBOR3M_B2S_8Y#0000 | F24: =_xll.ohRangeRetrieveError(E24)
A25: Basis two swaps | B25: BASIS_SWAP/BASIS_SPREAD/3M/6M/EUR/9Y | C25: =MarketData!$E$61 -> EUR-EURIBOR-3M_BASIS_SWAP_BASIS_SPREAD_3M_6M_EUR_9Y#0000 | E25: =_xll.qlBasisTwoSwapHelper("EURIBOR3M_B2S_9Y",C25,"9Y","TARGET","Annual","Modified Following","30/360 (USA)",Indexes!$B$19,"Annual","Modified Following","30/360 (USA)",Indexes!$B$18,TRUE,Indexes!$B$6,TRUE,FALSE,FALSE,'EUR-EURIBOR-6M'!$B$32) -> EURIBOR3M_B2S_9Y#0000 | F25: =_xll.ohRangeRetrieveError(E25)
A26: Basis two swaps | B26: BASIS_SWAP/BASIS_SPREAD/3M/6M/EUR/10Y | C26: =MarketData!$E$62 -> EUR-EURIBOR-3M_BASIS_SWAP_BASIS_SPREAD_3M_6M_EUR_10Y#0000 | E26: =_xll.qlBasisTwoSwapHelper("EURIBOR3M_B2S_10Y",C26,"10Y","TARGET","Annual","Modified Following","30/360 (USA)",Indexes!$B$19,"Annual","Modified Following","30/360 (USA)",Indexes!$B$18,TRUE,Indexes!$B$6,TRUE,FALSE,FALSE,'EUR-EURIBOR-6M'!$B$32) -> EURIBOR3M_B2S_10Y#0000 | F26: =_xll.ohRangeRetrieveError(E26)
A27: Basis two swaps | B27: BASIS_SWAP/BASIS_SPREAD/3M/6M/EUR/12Y | C27: =MarketData!$E$63 -> EUR-EURIBOR-3M_BASIS_SWAP_BASIS_SPREAD_3M_6M_EUR_12Y#0000 | E27: =_xll.qlBasisTwoSwapHelper("EURIBOR3M_B2S_12Y",C27,"12Y","TARGET","Annual","Modified Following","30/360 (USA)",Indexes!$B$19,"Annual","Modified Following","30/360 (USA)",Indexes!$B$18,TRUE,Indexes!$B$6,TRUE,FALSE,FALSE,'EUR-EURIBOR-6M'!$B$32) -> EURIBOR3M_B2S_12Y#0000 | F27: =_xll.ohRangeRetrieveError(E27)
A28: Basis two swaps | B28: BASIS_SWAP/BASIS_SPREAD/3M/6M/EUR/15Y | C28: =MarketData!$E$64 -> EUR-EURIBOR-3M_BASIS_SWAP_BASIS_SPREAD_3M_6M_EUR_15Y#0000 | E28: =_xll.qlBasisTwoSwapHelper("EURIBOR3M_B2S_15Y",C28,"15Y","TARGET","Annual","Modified Following","30/360 (USA)",Indexes!$B$19,"Annual","Modified Following","30/360 (USA)",Indexes!$B$18,TRUE,Indexes!$B$6,TRUE,FALSE,FALSE,'EUR-EURIBOR-6M'!$B$32) -> EURIBOR3M_B2S_15Y#0000 | F28: =_xll.ohRangeRetrieveError(E28)
A29: Basis two swaps | B29: BASIS_SWAP/BASIS_SPREAD/3M/6M/EUR/20Y | C29: =MarketData!$E$65 -> EUR-EURIBOR-3M_BASIS_SWAP_BASIS_SPREAD_3M_6M_EUR_20Y#0000 | E29: =_xll.qlBasisTwoSwapHelper("EURIBOR3M_B2S_20Y",C29,"20Y","TARGET","Annual","Modified Following","30/360 (USA)",Indexes!$B$19,"Annual","Modified Following","30/360 (USA)",Indexes!$B$18,TRUE,Indexes!$B$6,TRUE,FALSE,FALSE,'EUR-EURIBOR-6M'!$B$32) -> EURIBOR3M_B2S_20Y#0000 | F29: =_xll.ohRangeRetrieveError(E29)
A30: Basis two swaps | B30: BASIS_SWAP/BASIS_SPREAD/3M/6M/EUR/25Y | C30: =MarketData!$E$66 -> EUR-EURIBOR-3M_BASIS_SWAP_BASIS_SPREAD_3M_6M_EUR_25Y#0000 | E30: =_xll.qlBasisTwoSwapHelper("EURIBOR3M_B2S_25Y",C30,"25Y","TARGET","Annual","Modified Following","30/360 (USA)",Indexes!$B$19,"Annual","Modified Following","30/360 (USA)",Indexes!$B$18,TRUE,Indexes!$B$6,TRUE,FALSE,FALSE,'EUR-EURIBOR-6M'!$B$32) -> EURIBOR3M_B2S_25Y#0000 | F30: =_xll.ohRangeRetrieveError(E30)
A31: Basis two swaps | B31: BASIS_SWAP/BASIS_SPREAD/3M/6M/EUR/30Y | C31: =MarketData!$E$67 -> EUR-EURIBOR-3M_BASIS_SWAP_BASIS_SPREAD_3M_6M_EUR_30Y#0000 | E31: =_xll.qlBasisTwoSwapHelper("EURIBOR3M_B2S_30Y",C31,"30Y","TARGET","Annual","Modified Following","30/360 (USA)",Indexes!$B$19,"Annual","Modified Following","30/360 (USA)",Indexes!$B$18,TRUE,Indexes!$B$6,TRUE,FALSE,FALSE,'EUR-EURIBOR-6M'!$B$32) -> EURIBOR3M_B2S_30Y#0000 | F31: =_xll.ohRangeRetrieveError(E31)
A33: Curve | B33: =_xll.qlPiecewiseYieldCurve("C_EUR-EURIBOR-3M",0,"TARGET",E5:E31,"Actual/365 (Fixed)",,,"Discount","LogLinear",FALSE,Indexes!$B$31) -> C_EUR-EURIBOR-3M#0000 | C33: =_xll.ohRangeRetrieveError(B33) | D33: =_xll.qlExtrapolatorEnableExtrapolation(B33,TRUE) -> TRUE
A34: Link handle H_EUR-EURIBOR-3M | B34: =_xll.qlRelinkableHandleLinkTo(Indexes!$B$10,B33,D33) -> TRUE | C34: =_xll.ohRangeRetrieveError(B34)
A36: Date | B36: ORE discount factor | C36: Excel discount factor | D36: Difference | E36: Rel. difference
A37: =DATE(2020,4,2) -> 43923 | B37: 1.0010194 | C37: =_xll.qlYieldTSDiscount($B$33,A37,TRUE,$B$34) -> 1.0010194 | D37: =C37-B37 -> 0 | E37: =D37/B37 -> 0
A38: =DATE(2020,5,4) -> 43955 | B38: 1.0013793 | C38: =_xll.qlYieldTSDiscount($B$33,A38,TRUE,$B$34) -> 1.0013793 | D38: =C38-B38 -> 0 | E38: =D38/B38 -> 0
A39: =DATE(2020,6,2) -> 43984 | B39: 1.0016942 | C39: =_xll.qlYieldTSDiscount($B$33,A39,TRUE,$B$34) -> 1.0016942 | D39: =C39-B39 -> 0 | E39: =D39/B39 -> 0
A40: =DATE(2020,7,2) -> 44014 | B40: 1.0020198 | C40: =_xll.qlYieldTSDiscount($B$33,A40,TRUE,$B$34) -> 1.0020198 | D40: =C40-B40 -> 0 | E40: =D40/B40 -> 0
A41: =DATE(2020,8,4) -> 44047 | B41: 1.0023911 | C41: =_xll.qlYieldTSDiscount($B$33,A41,TRUE,$B$34) -> 1.0023911 | D41: =C41-B41 -> 0 | E41: =D41/B41 -> 0
A42: =DATE(2020,9,2) -> 44076 | B42: 1.0027064 | C42: =_xll.qlYieldTSDiscount($B$33,A42,TRUE,$B$34) -> 1.0027064 | D42: =C42-B42 -> 0 | E42: =D42/B42 -> 0
A43: =DATE(2020,10,2) -> 44106 | B43: 1.003028 | C43: =_xll.qlYieldTSDiscount($B$33,A43,TRUE,$B$34) -> 1.003028 | D43: =C43-B43 -> 0 | E43: =D43/B43 -> 0
A44: =DATE(2020,11,3) -> 44138 | B44: 1.0033799 | C44: =_xll.qlYieldTSDiscount($B$33,A44,TRUE,$B$34) -> 1.0033799 | D44: =C44-B44 -> 0 | E44: =D44/B44 -> 0
A45: =DATE(2020,12,2) -> 44167 | B45: 1.0036959 | C45: =_xll.qlYieldTSDiscount($B$33,A45,TRUE,$B$34) -> 1.0036959 | D45: =C45-B45 -> 0 | E45: =D45/B45 -> 0
A46: =DATE(2021,1,4) -> 44200 | B46: 1.0040504 | C46: =_xll.qlYieldTSDiscount($B$33,A46,TRUE,$B$34) -> 1.0040504 | D46: =C46-B46 -> 0 | E46: =D46/B46 -> 0
A47: =DATE(2021,4,6) -> 44292 | B47: 1.0050264 | C47: =_xll.qlYieldTSDiscount($B$33,A47,TRUE,$B$34) -> 1.0050264 | D47: =C47-B47 -> 0 | E47: =D47/B47 -> 0
A48: =DATE(2021,7,6) -> 44383 | B48: 1.0059673 | C48: =_xll.qlYieldTSDiscount($B$33,A48,TRUE,$B$34) -> 1.0059673 | D48: =C48-B48 -> 0 | E48: =D48/B48 -> 0
A49: =DATE(2021,10,4) -> 44473 | B49: 1.0068198 | C49: =_xll.qlYieldTSDiscount($B$33,A49,TRUE,$B$34) -> 1.0068198 | D49: =C49-B49 -> 0 | E49: =D49/B49 -> 0
A50: =DATE(2022,1,3) -> 44564 | B50: 1.0075144 | C50: =_xll.qlYieldTSDiscount($B$33,A50,TRUE,$B$34) -> 1.0075144 | D50: =C50-B50 -> 0 | E50: =D50/B50 -> 0
A51: =DATE(2023,1,2) -> 44928 | B51: 1.0095725 | C51: =_xll.qlYieldTSDiscount($B$33,A51,TRUE,$B$34) -> 1.0095725 | D51: =C51-B51 -> 0 | E51: =D51/B51 -> 0
A52: =DATE(2024,1,2) -> 45293 | B52: 1.0107316 | C52: =_xll.qlYieldTSDiscount($B$33,A52,TRUE,$B$34) -> 1.0107316 | D52: =C52-B52 -> 0 | E52: =D52/B52 -> 0
A53: =DATE(2025,1,2) -> 45659 | B53: 1.0103168 | C53: =_xll.qlYieldTSDiscount($B$33,A53,TRUE,$B$34) -> 1.0103168 | D53: =C53-B53 -> 0 | E53: =D53/B53 -> 0
A54: =DATE(2026,1,2) -> 46024 | B54: 1.0085431 | C54: =_xll.qlYieldTSDiscount($B$33,A54,TRUE,$B$34) -> 1.0085431 | D54: =C54-B54 -> 0 | E54: =D54/B54 -> 0
A55: =DATE(2027,1,4) -> 46391 | B55: 1.0043093 | C55: =_xll.qlYieldTSDiscount($B$33,A55,TRUE,$B$34) -> 1.0043093 | D55: =C55-B55 -> 0 | E55: =D55/B55 -> 0
A56: =DATE(2028,1,3) -> 46755 | B56: 1.0005728 | C56: =_xll.qlYieldTSDiscount($B$33,A56,TRUE,$B$34) -> 1.0005728 | D56: =C56-B56 -> 0 | E56: =D56/B56 -> 0
A57: =DATE(2029,1,2) -> 47120 | B57: 0.99342683 | C57: =_xll.qlYieldTSDiscount($B$33,A57,TRUE,$B$34) -> 0.99342683 | D57: =C57-B57 -> 0 | E57: =D57/B57 -> 0
A58: =DATE(2030,1,2) -> 47485 | B58: 0.98622212 | C58: =_xll.qlYieldTSDiscount($B$33,A58,TRUE,$B$34) -> 0.98622212 | D58: =C58-B58 -> 0 | E58: =D58/B58 -> 0
A59: =DATE(2032,1,2) -> 48215 | B59: 0.96909951 | C59: =_xll.qlYieldTSDiscount($B$33,A59,TRUE,$B$34) -> 0.96909951 | D59: =C59-B59 -> 0 | E59: =D59/B59 -> 0
A60: =DATE(2035,1,2) -> 49311 | B60: 0.93953092 | C60: =_xll.qlYieldTSDiscount($B$33,A60,TRUE,$B$34) -> 0.93953092 | D60: =C60-B60 -> 0 | E60: =D60/B60 -> 0
A61: =DATE(2040,1,2) -> 51137 | B61: 0.89385926 | C61: =_xll.qlYieldTSDiscount($B$33,A61,TRUE,$B$34) -> 0.89385926 | D61: =C61-B61 -> 0 | E61: =D61/B61 -> 0
A62: =DATE(2045,1,2) -> 52964 | B62: 0.85895982 | C62: =_xll.qlYieldTSDiscount($B$33,A62,TRUE,$B$34) -> 0.85895982 | D62: =C62-B62 -> 0 | E62: =D62/B62 -> 0
A63: =DATE(2050,1,3) -> 54791 | B63: 0.83394203 | C63: =_xll.qlYieldTSDiscount($B$33,A63,TRUE,$B$34) -> 0.83394203 | D63: =C63-B63 -> 0 | E63: =D63/B63 -> 0
A65: Max abs difference | D65: =MAX(ABS(MIN(D37:D63)),ABS(MAX(D37:D63))) -> 0

Sheet EUR-IN-USD
A1: EUR-IN-USD: EUR discount curve collateralised in USD. Discount/LogLinear, A365, extrapolation; FX forwards + non-resetting xccy basis swaps vs USD-FedFunds
A2: EUR-USD-FX: spot 2D, TARGET+US, Following, points factor 10000. USD-EUR-XCCY-BASIS: settle 2D TARGET+US+UK, MF; IsResettable unset (false): non-resetting; flat USD-LIBOR-3M (domestic), spread EUR-EURIBOR-3M; telescopic value dates.
A3: Helper trigger | B3: =CONCATENATE('USD-FedFunds'!$B$32,'USD-LIBOR-3M'!$B$33,'EUR-EURIBOR-3M'!$B$34) -> TRUETRUETRUE
A4: Segment | B4: Quote | C4: Quote object | D4: Value | E4: Helper | F4: Error
A5: FX forward | B5: FXFWD/RATE/EUR/USD/1W | C5: =MarketData!$E$94 -> EUR-IN-USD_FXFWD_RATE_EUR_USD_1W#0000 | D5: =MarketData!$D$94/10000 -> 0.00046 | E5: =_xll.qlFxSwapRateHelper("EURINUSD_FXFWD_1W",D5,MarketData!$E$93,"1W",2,"JoinHolidays(TARGET,UnitedStates::Settlement)","Following",FALSE,FALSE,Indexes!$B$5,FALSE,$B$3) -> EURINUSD_FXFWD_1W#0000 | F5: =_xll.ohRangeRetrieveError(E5)
A6: FX forward | B6: FXFWD/RATE/EUR/USD/2W | C6: =MarketData!$E$95 -> EUR-IN-USD_FXFWD_RATE_EUR_USD_2W#0000 | D6: =MarketData!$D$95/10000 -> 0.000937 | E6: =_xll.qlFxSwapRateHelper("EURINUSD_FXFWD_2W",D6,MarketData!$E$93,"2W",2,"JoinHolidays(TARGET,UnitedStates::Settlement)","Following",FALSE,FALSE,Indexes!$B$5,FALSE,$B$3) -> EURINUSD_FXFWD_2W#0000 | F6: =_xll.ohRangeRetrieveError(E6)
A7: FX forward | B7: FXFWD/RATE/EUR/USD/3W | C7: =MarketData!$E$96 -> EUR-IN-USD_FXFWD_RATE_EUR_USD_3W#0000 | D7: =MarketData!$D$96/10000 -> 0.001411 | E7: =_xll.qlFxSwapRateHelper("EURINUSD_FXFWD_3W",D7,MarketData!$E$93,"3W",2,"JoinHolidays(TARGET,UnitedStates::Settlement)","Following",FALSE,FALSE,Indexes!$B$5,FALSE,$B$3) -> EURINUSD_FXFWD_3W#0000 | F7: =_xll.ohRangeRetrieveError(E7)
A8: FX forward | B8: FXFWD/RATE/EUR/USD/1M | C8: =MarketData!$E$97 -> EUR-IN-USD_FXFWD_RATE_EUR_USD_1M#0000 | D8: =MarketData!$D$97/10000 -> 0.002197 | E8: =_xll.qlFxSwapRateHelper("EURINUSD_FXFWD_1M",D8,MarketData!$E$93,"1M",2,"JoinHolidays(TARGET,UnitedStates::Settlement)","Following",FALSE,FALSE,Indexes!$B$5,FALSE,$B$3) -> EURINUSD_FXFWD_1M#0000 | F8: =_xll.ohRangeRetrieveError(E8)
A9: FX forward | B9: FXFWD/RATE/EUR/USD/2M | C9: =MarketData!$E$98 -> EUR-IN-USD_FXFWD_RATE_EUR_USD_2M#0000 | D9: =MarketData!$D$98/10000 -> 0.004132 | E9: =_xll.qlFxSwapRateHelper("EURINUSD_FXFWD_2M",D9,MarketData!$E$93,"2M",2,"JoinHolidays(TARGET,UnitedStates::Settlement)","Following",FALSE,FALSE,Indexes!$B$5,FALSE,$B$3) -> EURINUSD_FXFWD_2M#0000 | F9: =_xll.ohRangeRetrieveError(E9)
A10: FX forward | B10: FXFWD/RATE/EUR/USD/3M | C10: =MarketData!$E$99 -> EUR-IN-USD_FXFWD_RATE_EUR_USD_3M#0000 | D10: =MarketData!$D$99/10000 -> 0.00633 | E10: =_xll.qlFxSwapRateHelper("EURINUSD_FXFWD_3M",D10,MarketData!$E$93,"3M",2,"JoinHolidays(TARGET,UnitedStates::Settlement)","Following",FALSE,FALSE,Indexes!$B$5,FALSE,$B$3) -> EURINUSD_FXFWD_3M#0000 | F10: =_xll.ohRangeRetrieveError(E10)
A11: FX forward | B11: FXFWD/RATE/EUR/USD/4M | C11: =MarketData!$E$100 -> EUR-IN-USD_FXFWD_RATE_EUR_USD_4M#0000 | D11: =MarketData!$D$100/10000 -> 0.008545 | E11: =_xll.qlFxSwapRateHelper("EURINUSD_FXFWD_4M",D11,MarketData!$E$93,"4M",2,"JoinHolidays(TARGET,UnitedStates::Settlement)","Following",FALSE,FALSE,Indexes!$B$5,FALSE,$B$3) -> EURINUSD_FXFWD_4M#0000 | F11: =_xll.ohRangeRetrieveError(E11)
A12: FX forward | B12: FXFWD/RATE/EUR/USD/5M | C12: =MarketData!$E$101 -> EUR-IN-USD_FXFWD_RATE_EUR_USD_5M#0000 | D12: =MarketData!$D$101/10000 -> 0.010613 | E12: =_xll.qlFxSwapRateHelper("EURINUSD_FXFWD_5M",D12,MarketData!$E$93,"5M",2,"JoinHolidays(TARGET,UnitedStates::Settlement)","Following",FALSE,FALSE,Indexes!$B$5,FALSE,$B$3) -> EURINUSD_FXFWD_5M#0000 | F12: =_xll.ohRangeRetrieveError(E12)
A13: FX forward | B13: FXFWD/RATE/EUR/USD/6M | C13: =MarketData!$E$102 -> EUR-IN-USD_FXFWD_RATE_EUR_USD_6M#0000 | D13: =MarketData!$D$102/10000 -> 0.012572 | E13: =_xll.qlFxSwapRateHelper("EURINUSD_FXFWD_6M",D13,MarketData!$E$93,"6M",2,"JoinHolidays(TARGET,UnitedStates::Settlement)","Following",FALSE,FALSE,Indexes!$B$5,FALSE,$B$3) -> EURINUSD_FXFWD_6M#0000 | F13: =_xll.ohRangeRetrieveError(E13)
A14: FX forward | B14: FXFWD/RATE/EUR/USD/7M | C14: =MarketData!$E$103 -> EUR-IN-USD_FXFWD_RATE_EUR_USD_7M#0000 | D14: =MarketData!$D$103/10000 -> 0.014805 | E14: =_xll.qlFxSwapRateHelper("EURINUSD_FXFWD_7M",D14,MarketData!$E$93,"7M",2,"JoinHolidays(TARGET,UnitedStates::Settlement)","Following",FALSE,FALSE,Indexes!$B$5,FALSE,$B$3) -> EURINUSD_FXFWD_7M#0000 | F14: =_xll.ohRangeRetrieveError(E14)
A15: FX forward | B15: FXFWD/RATE/EUR/USD/8M | C15: =MarketData!$E$104 -> EUR-IN-USD_FXFWD_RATE_EUR_USD_8M#0000 | D15: =MarketData!$D$104/10000 -> 0.016898 | E15: =_xll.qlFxSwapRateHelper("EURINUSD_FXFWD_8M",D15,MarketData!$E$93,"8M",2,"JoinHolidays(TARGET,UnitedStates::Settlement)","Following",FALSE,FALSE,Indexes!$B$5,FALSE,$B$3) -> EURINUSD_FXFWD_8M#0000 | F15: =_xll.ohRangeRetrieveError(E15)
A16: FX forward | B16: FXFWD/RATE/EUR/USD/9M | C16: =MarketData!$E$105 -> EUR-IN-USD_FXFWD_RATE_EUR_USD_9M#0000 | D16: =MarketData!$D$105/10000 -> 0.018774 | E16: =_xll.qlFxSwapRateHelper("EURINUSD_FXFWD_9M",D16,MarketData!$E$93,"9M",2,"JoinHolidays(TARGET,UnitedStates::Settlement)","Following",FALSE,FALSE,Indexes!$B$5,FALSE,$B$3) -> EURINUSD_FXFWD_9M#0000 | F16: =_xll.ohRangeRetrieveError(E16)
A17: FX forward | B17: FXFWD/RATE/EUR/USD/10M | C17: =MarketData!$E$106 -> EUR-IN-USD_FXFWD_RATE_EUR_USD_10M#0000 | D17: =MarketData!$D$106/10000 -> 0.02099 | E17: =_xll.qlFxSwapRateHelper("EURINUSD_FXFWD_10M",D17,MarketData!$E$93,"10M",2,"JoinHolidays(TARGET,UnitedStates::Settlement)","Following",FALSE,FALSE,Indexes!$B$5,FALSE,$B$3) -> EURINUSD_FXFWD_10M#0000 | F17: =_xll.ohRangeRetrieveError(E17)
A18: FX forward | B18: FXFWD/RATE/EUR/USD/11M | C18: =MarketData!$E$107 -> EUR-IN-USD_FXFWD_RATE_EUR_USD_11M#0000 | D18: =MarketData!$D$107/10000 -> 0.02309 | E18: =_xll.qlFxSwapRateHelper("EURINUSD_FXFWD_11M",D18,MarketData!$E$93,"11M",2,"JoinHolidays(TARGET,UnitedStates::Settlement)","Following",FALSE,FALSE,Indexes!$B$5,FALSE,$B$3) -> EURINUSD_FXFWD_11M#0000 | F18: =_xll.ohRangeRetrieveError(E18)
A19: FX forward | B19: FXFWD/RATE/EUR/USD/1Y | C19: =MarketData!$E$108 -> EUR-IN-USD_FXFWD_RATE_EUR_USD_1Y#0000 | D19: =MarketData!$D$108/10000 -> 0.025282 | E19: =_xll.qlFxSwapRateHelper("EURINUSD_FXFWD_1Y",D19,MarketData!$E$93,"1Y",2,"JoinHolidays(TARGET,UnitedStates::Settlement)","Following",FALSE,FALSE,Indexes!$B$5,FALSE,$B$3) -> EURINUSD_FXFWD_1Y#0000 | F19: =_xll.ohRangeRetrieveError(E19)
A20: FX forward | B20: FXFWD/RATE/EUR/USD/15M | C20: =MarketData!$E$109 -> EUR-IN-USD_FXFWD_RATE_EUR_USD_15M#0000 | D20: =MarketData!$D$109/10000 -> 0.031229 | E20: =_xll.qlFxSwapRateHelper("EURINUSD_FXFWD_15M",D20,MarketData!$E$93,"15M",2,"JoinHolidays(TARGET,UnitedStates::Settlement)","Following",FALSE,FALSE,Indexes!$B$5,FALSE,$B$3) -> EURINUSD_FXFWD_15M#0000 | F20: =_xll.ohRangeRetrieveError(E20)
A21: FX forward | B21: FXFWD/RATE/EUR/USD/18M | C21: =MarketData!$E$110 -> EUR-IN-USD_FXFWD_RATE_EUR_USD_18M#0000 | D21: =MarketData!$D$110/10000 -> 0.036687 | E21: =_xll.qlFxSwapRateHelper("EURINUSD_FXFWD_18M",D21,MarketData!$E$93,"18M",2,"JoinHolidays(TARGET,UnitedStates::Settlement)","Following",FALSE,FALSE,Indexes!$B$5,FALSE,$B$3) -> EURINUSD_FXFWD_18M#0000 | F21: =_xll.ohRangeRetrieveError(E21)
A22: FX forward | B22: FXFWD/RATE/EUR/USD/21M | C22: =MarketData!$E$111 -> EUR-IN-USD_FXFWD_RATE_EUR_USD_21M#0000 | D22: =MarketData!$D$111/10000 -> 0.04273 | E22: =_xll.qlFxSwapRateHelper("EURINUSD_FXFWD_21M",D22,MarketData!$E$93,"21M",2,"JoinHolidays(TARGET,UnitedStates::Settlement)","Following",FALSE,FALSE,Indexes!$B$5,FALSE,$B$3) -> EURINUSD_FXFWD_21M#0000 | F22: =_xll.ohRangeRetrieveError(E22)
A23: Xccy basis | B23: CC_BASIS_SWAP/BASIS_SPREAD/USD/3M/EUR/3M/2Y | C23: =MarketData!$E$112 -> EUR-IN-USD_CC_BASIS_SWAP_BASIS_SPREAD_USD_3M_EUR_3M_2Y#0000 | D23: =MarketData!$D$112 -> -0.001325 | E23: =_xll.qlCrossCcyBasisSwapHelper("EURINUSD_XCCY_2Y",C23,MarketData!$E$93,2,"JoinHolidays(TARGET,UnitedStates::Settlement,UnitedKingdom::Settlement)","2Y","Modified Following",Indexes!$B$16,Indexes!$B$18,Indexes!$B$5,,FALSE,TRUE,2,"JoinHolidays(TARGET,UnitedStates::Settlement)",TRUE,FALSE,$B$3) -> EURINUSD_XCCY_2Y#0000 | F23: =_xll.ohRangeRetrieveError(E23)
A24: Xccy basis | B24: CC_BASIS_SWAP/BASIS_SPREAD/USD/3M/EUR/3M/3Y | C24: =MarketData!$E$113 -> EUR-IN-USD_CC_BASIS_SWAP_BASIS_SPREAD_USD_3M_EUR_3M_3Y#0000 | D24: =MarketData!$D$113 -> -0.00145 | E24: =_xll.qlCrossCcyBasisSwapHelper("EURINUSD_XCCY_3Y",C24,MarketData!$E$93,2,"JoinHolidays(TARGET,UnitedStates::Settlement,UnitedKingdom::Settlement)","3Y","Modified Following",Indexes!$B$16,Indexes!$B$18,Indexes!$B$5,,FALSE,TRUE,2,"JoinHolidays(TARGET,UnitedStates::Settlement)",TRUE,FALSE,$B$3) -> EURINUSD_XCCY_3Y#0000 | F24: =_xll.ohRangeRetrieveError(E24)
A25: Xccy basis | B25: CC_BASIS_SWAP/BASIS_SPREAD/USD/3M/EUR/3M/4Y | C25: =MarketData!$E$114 -> EUR-IN-USD_CC_BASIS_SWAP_BASIS_SPREAD_USD_3M_EUR_3M_4Y#0000 | D25: =MarketData!$D$114 -> -0.0015375 | E25: =_xll.qlCrossCcyBasisSwapHelper("EURINUSD_XCCY_4Y",C25,MarketData!$E$93,2,"JoinHolidays(TARGET,UnitedStates::Settlement,UnitedKingdom::Settlement)","4Y","Modified Following",Indexes!$B$16,Indexes!$B$18,Indexes!$B$5,,FALSE,TRUE,2,"JoinHolidays(TARGET,UnitedStates::Settlement)",TRUE,FALSE,$B$3) -> EURINUSD_XCCY_4Y#0000 | F25: =_xll.ohRangeRetrieveError(E25)
A26: Xccy basis | B26: CC_BASIS_SWAP/BASIS_SPREAD/USD/3M/EUR/3M/5Y | C26: =MarketData!$E$115 -> EUR-IN-USD_CC_BASIS_SWAP_BASIS_SPREAD_USD_3M_EUR_3M_5Y#0000 | D26: =MarketData!$D$115 -> -0.0016 | E26: =_xll.qlCrossCcyBasisSwapHelper("EURINUSD_XCCY_5Y",C26,MarketData!$E$93,2,"JoinHolidays(TARGET,UnitedStates::Settlement,UnitedKingdom::Settlement)","5Y","Modified Following",Indexes!$B$16,Indexes!$B$18,Indexes!$B$5,,FALSE,TRUE,2,"JoinHolidays(TARGET,UnitedStates::Settlement)",TRUE,FALSE,$B$3) -> EURINUSD_XCCY_5Y#0000 | F26: =_xll.ohRangeRetrieveError(E26)
A27: Xccy basis | B27: CC_BASIS_SWAP/BASIS_SPREAD/USD/3M/EUR/3M/6Y | C27: =MarketData!$E$116 -> EUR-IN-USD_CC_BASIS_SWAP_BASIS_SPREAD_USD_3M_EUR_3M_6Y#0000 | D27: =MarketData!$D$116 -> -0.00165 | E27: =_xll.qlCrossCcyBasisSwapHelper("EURINUSD_XCCY_6Y",C27,MarketData!$E$93,2,"JoinHolidays(TARGET,UnitedStates::Settlement,UnitedKingdom::Settlement)","6Y","Modified Following",Indexes!$B$16,Indexes!$B$18,Indexes!$B$5,,FALSE,TRUE,2,"JoinHolidays(TARGET,UnitedStates::Settlement)",TRUE,FALSE,$B$3) -> EURINUSD_XCCY_6Y#0000 | F27: =_xll.ohRangeRetrieveError(E27)
A28: Xccy basis | B28: CC_BASIS_SWAP/BASIS_SPREAD/USD/3M/EUR/3M/7Y | C28: =MarketData!$E$117 -> EUR-IN-USD_CC_BASIS_SWAP_BASIS_SPREAD_USD_3M_EUR_3M_7Y#0000 | D28: =MarketData!$D$117 -> -0.00175 | E28: =_xll.qlCrossCcyBasisSwapHelper("EURINUSD_XCCY_7Y",C28,MarketData!$E$93,2,"JoinHolidays(TARGET,UnitedStates::Settlement,UnitedKingdom::Settlement)","7Y","Modified Following",Indexes!$B$16,Indexes!$B$18,Indexes!$B$5,,FALSE,TRUE,2,"JoinHolidays(TARGET,UnitedStates::Settlement)",TRUE,FALSE,$B$3) -> EURINUSD_XCCY_7Y#0000 | F28: =_xll.ohRangeRetrieveError(E28)
A29: Xccy basis | B29: CC_BASIS_SWAP/BASIS_SPREAD/USD/3M/EUR/3M/8Y | C29: =MarketData!$E$118 -> EUR-IN-USD_CC_BASIS_SWAP_BASIS_SPREAD_USD_3M_EUR_3M_8Y#0000 | D29: =MarketData!$D$118 -> -0.0017875 | E29: =_xll.qlCrossCcyBasisSwapHelper("EURINUSD_XCCY_8Y",C29,MarketData!$E$93,2,"JoinHolidays(TARGET,UnitedStates::Settlement,UnitedKingdom::Settlement)","8Y","Modified Following",Indexes!$B$16,Indexes!$B$18,Indexes!$B$5,,FALSE,TRUE,2,"JoinHolidays(TARGET,UnitedStates::Settlement)",TRUE,FALSE,$B$3) -> EURINUSD_XCCY_8Y#0000 | F29: =_xll.ohRangeRetrieveError(E29)
A30: Xccy basis | B30: CC_BASIS_SWAP/BASIS_SPREAD/USD/3M/EUR/3M/9Y | C30: =MarketData!$E$119 -> EUR-IN-USD_CC_BASIS_SWAP_BASIS_SPREAD_USD_3M_EUR_3M_9Y#0000 | D30: =MarketData!$D$119 -> -0.001825 | E30: =_xll.qlCrossCcyBasisSwapHelper("EURINUSD_XCCY_9Y",C30,MarketData!$E$93,2,"JoinHolidays(TARGET,UnitedStates::Settlement,UnitedKingdom::Settlement)","9Y","Modified Following",Indexes!$B$16,Indexes!$B$18,Indexes!$B$5,,FALSE,TRUE,2,"JoinHolidays(TARGET,UnitedStates::Settlement)",TRUE,FALSE,$B$3) -> EURINUSD_XCCY_9Y#0000 | F30: =_xll.ohRangeRetrieveError(E30)
A31: Xccy basis | B31: CC_BASIS_SWAP/BASIS_SPREAD/USD/3M/EUR/3M/10Y | C31: =MarketData!$E$120 -> EUR-IN-USD_CC_BASIS_SWAP_BASIS_SPREAD_USD_3M_EUR_3M_10Y#0000 | D31: =MarketData!$D$120 -> -0.0018625 | E31: =_xll.qlCrossCcyBasisSwapHelper("EURINUSD_XCCY_10Y",C31,MarketData!$E$93,2,"JoinHolidays(TARGET,UnitedStates::Settlement,UnitedKingdom::Settlement)","10Y","Modified Following",Indexes!$B$16,Indexes!$B$18,Indexes!$B$5,,FALSE,TRUE,2,"JoinHolidays(TARGET,UnitedStates::Settlement)",TRUE,FALSE,$B$3) -> EURINUSD_XCCY_10Y#0000 | F31: =_xll.ohRangeRetrieveError(E31)
A32: Xccy basis | B32: CC_BASIS_SWAP/BASIS_SPREAD/USD/3M/EUR/3M/12Y | C32: =MarketData!$E$121 -> EUR-IN-USD_CC_BASIS_SWAP_BASIS_SPREAD_USD_3M_EUR_3M_12Y#0000 | D32: =MarketData!$D$121 -> -0.0018375 | E32: =_xll.qlCrossCcyBasisSwapHelper("EURINUSD_XCCY_12Y",C32,MarketData!$E$93,2,"JoinHolidays(TARGET,UnitedStates::Settlement,UnitedKingdom::Settlement)","12Y","Modified Following",Indexes!$B$16,Indexes!$B$18,Indexes!$B$5,,FALSE,TRUE,2,"JoinHolidays(TARGET,UnitedStates::Settlement)",TRUE,FALSE,$B$3) -> EURINUSD_XCCY_12Y#0000 | F32: =_xll.ohRangeRetrieveError(E32)
A33: Xccy basis | B33: CC_BASIS_SWAP/BASIS_SPREAD/USD/3M/EUR/3M/15Y | C33: =MarketData!$E$122 -> EUR-IN-USD_CC_BASIS_SWAP_BASIS_SPREAD_USD_3M_EUR_3M_15Y#0000 | D33: =MarketData!$D$122 -> -0.0016375 | E33: =_xll.qlCrossCcyBasisSwapHelper("EURINUSD_XCCY_15Y",C33,MarketData!$E$93,2,"JoinHolidays(TARGET,UnitedStates::Settlement,UnitedKingdom::Settlement)","15Y","Modified Following",Indexes!$B$16,Indexes!$B$18,Indexes!$B$5,,FALSE,TRUE,2,"JoinHolidays(TARGET,UnitedStates::Settlement)",TRUE,FALSE,$B$3) -> EURINUSD_XCCY_15Y#0000 | F33: =_xll.ohRangeRetrieveError(E33)
A34: Xccy basis | B34: CC_BASIS_SWAP/BASIS_SPREAD/USD/3M/EUR/3M/20Y | C34: =MarketData!$E$123 -> EUR-IN-USD_CC_BASIS_SWAP_BASIS_SPREAD_USD_3M_EUR_3M_20Y#0000 | D34: =MarketData!$D$123 -> -0.00115 | E34: =_xll.qlCrossCcyBasisSwapHelper("EURINUSD_XCCY_20Y",C34,MarketData!$E$93,2,"JoinHolidays(TARGET,UnitedStates::Settlement,UnitedKingdom::Settlement)","20Y","Modified Following",Indexes!$B$16,Indexes!$B$18,Indexes!$B$5,,FALSE,TRUE,2,"JoinHolidays(TARGET,UnitedStates::Settlement)",TRUE,FALSE,$B$3) -> EURINUSD_XCCY_20Y#0000 | F34: =_xll.ohRangeRetrieveError(E34)
A35: Xccy basis | B35: CC_BASIS_SWAP/BASIS_SPREAD/USD/3M/EUR/3M/25Y | C35: =MarketData!$E$124 -> EUR-IN-USD_CC_BASIS_SWAP_BASIS_SPREAD_USD_3M_EUR_3M_25Y#0000 | D35: =MarketData!$D$124 -> -0.0006375 | E35: =_xll.qlCrossCcyBasisSwapHelper("EURINUSD_XCCY_25Y",C35,MarketData!$E$93,2,"JoinHolidays(TARGET,UnitedStates::Settlement,UnitedKingdom::Settlement)","25Y","Modified Following",Indexes!$B$16,Indexes!$B$18,Indexes!$B$5,,FALSE,TRUE,2,"JoinHolidays(TARGET,UnitedStates::Settlement)",TRUE,FALSE,$B$3) -> EURINUSD_XCCY_25Y#0000 | F35: =_xll.ohRangeRetrieveError(E35)
A36: Xccy basis | B36: CC_BASIS_SWAP/BASIS_SPREAD/USD/3M/EUR/3M/30Y | C36: =MarketData!$E$125 -> EUR-IN-USD_CC_BASIS_SWAP_BASIS_SPREAD_USD_3M_EUR_3M_30Y#0000 | D36: =MarketData!$D$125 -> -0.000225 | E36: =_xll.qlCrossCcyBasisSwapHelper("EURINUSD_XCCY_30Y",C36,MarketData!$E$93,2,"JoinHolidays(TARGET,UnitedStates::Settlement,UnitedKingdom::Settlement)","30Y","Modified Following",Indexes!$B$16,Indexes!$B$18,Indexes!$B$5,,FALSE,TRUE,2,"JoinHolidays(TARGET,UnitedStates::Settlement)",TRUE,FALSE,$B$3) -> EURINUSD_XCCY_30Y#0000 | F36: =_xll.ohRangeRetrieveError(E36)
A38: Curve | B38: =_xll.qlPiecewiseYieldCurve("C_EUR-IN-USD",0,"TARGET",E5:E36,"Actual/365 (Fixed)",,,"Discount","LogLinear",FALSE,Indexes!$B$31) -> C_EUR-IN-USD#0000 | C38: =_xll.ohRangeRetrieveError(B38) | D38: =_xll.qlExtrapolatorEnableExtrapolation(B38,TRUE) -> TRUE
A39: Link handle H_EUR-IN-USD | B39: =_xll.qlRelinkableHandleLinkTo(Indexes!$B$11,B38,D38) -> TRUE | C39: =_xll.ohRangeRetrieveError(B39)
A41: Date | B41: ORE discount factor | C41: Excel discount factor | D41: Difference | E41: Rel. difference
A42: =DATE(2020,1,9) -> 43839 | B42: 1.0001571 | C42: =_xll.qlYieldTSDiscount($B$38,A42,TRUE,$B$39) -> 1.0001571 | D42: =C42-B42 -> 0 | E42: =D42/B42 -> 0
A43: =DATE(2020,1,16) -> 43846 | B43: 1.0002812 | C43: =_xll.qlYieldTSDiscount($B$38,A43,TRUE,$B$39) -> 1.0002812 | D43: =C43-B43 -> 0 | E43: =D43/B43 -> 0
A44: =DATE(2020,1,23) -> 43853 | B44: 1.0004033 | C44: =_xll.qlYieldTSDiscount($B$38,A44,TRUE,$B$39) -> 1.0004033 | D44: =C44-B44 -> 0 | E44: =D44/B44 -> 0
A45: =DATE(2020,2,3) -> 43864 | B45: 1.0006273 | C45: =_xll.qlYieldTSDiscount($B$38,A45,TRUE,$B$39) -> 1.0006273 | D45: =C45-B45 -> 0 | E45: =D45/B45 -> 0
A46: =DATE(2020,3,2) -> 43892 | B46: 1.0011328 | C46: =_xll.qlYieldTSDiscount($B$38,A46,TRUE,$B$39) -> 1.0011328 | D46: =C46-B46 -> 0 | E46: =D46/B46 -> 0
A47: =DATE(2020,4,2) -> 43923 | B47: 1.0017457 | C47: =_xll.qlYieldTSDiscount($B$38,A47,TRUE,$B$39) -> 1.0017457 | D47: =C47-B47 -> 0 | E47: =D47/B47 -> 0
A48: =DATE(2020,5,4) -> 43955 | B48: 1.0023372 | C48: =_xll.qlYieldTSDiscount($B$38,A48,TRUE,$B$39) -> 1.0023372 | D48: =C48-B48 -> 0 | E48: =D48/B48 -> 0
A49: =DATE(2020,6,2) -> 43984 | B49: 1.0029327 | C49: =_xll.qlYieldTSDiscount($B$38,A49,TRUE,$B$39) -> 1.0029327 | D49: =C49-B49 -> 0 | E49: =D49/B49 -> 0
A50: =DATE(2020,7,2) -> 44014 | B50: 1.0034018 | C50: =_xll.qlYieldTSDiscount($B$38,A50,TRUE,$B$39) -> 1.0034018 | D50: =C50-B50 -> 0 | E50: =D50/B50 -> 0
A51: =DATE(2020,8,3) -> 44046 | B51: 1.0040398 | C51: =_xll.qlYieldTSDiscount($B$38,A51,TRUE,$B$39) -> 1.0040398 | D51: =C51-B51 -> 0 | E51: =D51/B51 -> 0
A52: =DATE(2020,9,2) -> 44076 | B52: 1.0046564 | C52: =_xll.qlYieldTSDiscount($B$38,A52,TRUE,$B$39) -> 1.0046564 | D52: =C52-B52 -> 0 | E52: =D52/B52 -> 0
A53: =DATE(2020,10,2) -> 44106 | B53: 1.0050916 | C53: =_xll.qlYieldTSDiscount($B$38,A53,TRUE,$B$39) -> 1.0050916 | D53: =C53-B53 -> 0 | E53: =D53/B53 -> 0
A54: =DATE(2020,11,2) -> 44137 | B54: 1.0058016 | C54: =_xll.qlYieldTSDiscount($B$38,A54,TRUE,$B$39) -> 1.0058016 | D54: =C54-B54 -> 0 | E54: =D54/B54 -> 0
A55: =DATE(2020,12,2) -> 44167 | B55: 1.0064703 | C55: =_xll.qlYieldTSDiscount($B$38,A55,TRUE,$B$39) -> 1.0064703 | D55: =C55-B55 -> 0 | E55: =D55/B55 -> 0
A56: =DATE(2021,1,4) -> 44200 | B56: 1.007109 | C56: =_xll.qlYieldTSDiscount($B$38,A56,TRUE,$B$39) -> 1.007109 | D56: =C56-B56 -> 0 | E56: =D56/B56 -> 0
A57: =DATE(2021,4,6) -> 44292 | B57: 1.0088729 | C57: =_xll.qlYieldTSDiscount($B$38,A57,TRUE,$B$39) -> 1.0088729 | D57: =C57-B57 -> 0 | E57: =D57/B57 -> 0
A58: =DATE(2021,7,2) -> 44379 | B58: 1.0103772 | C58: =_xll.qlYieldTSDiscount($B$38,A58,TRUE,$B$39) -> 1.0103772 | D58: =C58-B58 -> 0 | E58: =D58/B58 -> 0
A59: =DATE(2021,10,4) -> 44473 | B59: 1.0121067 | C59: =_xll.qlYieldTSDiscount($B$38,A59,TRUE,$B$39) -> 1.0121067 | D59: =C59-B59 -> 0 | E59: =D59/B59 -> 0
A60: =DATE(2022,1,4) -> 44565 | B60: 1.0147842 | C60: =_xll.qlYieldTSDiscount($B$38,A60,TRUE,$B$39) -> 1.0147842 | D60: =C60-B60 -> 0 | E60: =D60/B60 -> 0
A61: =DATE(2023,1,3) -> 44929 | B61: 1.0206879 | C61: =_xll.qlYieldTSDiscount($B$38,A61,TRUE,$B$39) -> 1.0206879 | D61: =C61-B61 -> 0 | E61: =D61/B61 -> 0
A62: =DATE(2024,1,2) -> 45293 | B62: 1.0257929 | C62: =_xll.qlYieldTSDiscount($B$38,A62,TRUE,$B$39) -> 1.0257929 | D62: =C62-B62 -> 0 | E62: =D62/B62 -> 0
A63: =DATE(2025,1,2) -> 45659 | B63: 1.0293283 | C63: =_xll.qlYieldTSDiscount($B$38,A63,TRUE,$B$39) -> 1.0293283 | D63: =C63-B63 -> 0 | E63: =D63/B63 -> 0
A64: =DATE(2026,1,2) -> 46024 | B64: 1.0311136 | C64: =_xll.qlYieldTSDiscount($B$38,A64,TRUE,$B$39) -> 1.0311136 | D64: =C64-B64 -> 0 | E64: =D64/B64 -> 0
A65: =DATE(2027,1,4) -> 46391 | B65: 1.0315745 | C65: =_xll.qlYieldTSDiscount($B$38,A65,TRUE,$B$39) -> 1.0315745 | D65: =C65-B65 -> 0 | E65: =D65/B65 -> 0
A66: =DATE(2028,1,4) -> 46756 | B66: 1.0313067 | C66: =_xll.qlYieldTSDiscount($B$38,A66,TRUE,$B$39) -> 1.0313067 | D66: =C66-B66 -> 0 | E66: =D66/B66 -> 0
A67: =DATE(2029,1,2) -> 47120 | B67: 1.027158 | C67: =_xll.qlYieldTSDiscount($B$38,A67,TRUE,$B$39) -> 1.027158 | D67: =C67-B67 -> 0 | E67: =D67/B67 -> 0
A68: =DATE(2030,1,2) -> 47485 | B68: 1.0252339 | C68: =_xll.qlYieldTSDiscount($B$38,A68,TRUE,$B$39) -> 1.0252339 | D68: =C68-B68 -> 0 | E68: =D68/B68 -> 0
A69: =DATE(2032,1,2) -> 48215 | B69: 1.0138672 | C69: =_xll.qlYieldTSDiscount($B$38,A69,TRUE,$B$39) -> 1.0138672 | D69: =C69-B69 -> 0 | E69: =D69/B69 -> 0
A70: =DATE(2035,1,2) -> 49311 | B70: 0.99117176 | C70: =_xll.qlYieldTSDiscount($B$38,A70,TRUE,$B$39) -> 0.99117176 | D70: =C70-B70 -> -2.7755576e-15 | E70: =D70/B70 -> -2.8002791e-15
A71: =DATE(2040,1,3) -> 51138 | B71: 0.94913288 | C71: =_xll.qlYieldTSDiscount($B$38,A71,TRUE,$B$39) -> 0.94913288 | D71: =C71-B71 -> 3.4416914e-15 | E71: =D71/B71 -> 3.6261428e-15
A72: =DATE(2045,1,3) -> 52965 | B72: 0.91305301 | C72: =_xll.qlYieldTSDiscount($B$38,A72,TRUE,$B$39) -> 0.91305301 | D72: =C72-B72 -> 4.1078252e-15 | E72: =D72/B72 -> 4.4989997e-15
A73: =DATE(2050,1,4) -> 54792 | B73: 0.88305909 | C73: =_xll.qlYieldTSDiscount($B$38,A73,TRUE,$B$39) -> 0.88305909 | D73: =C73-B73 -> 5.9952043e-15 | E73: =D73/B73 -> 6.7891316e-15
A75: Max abs difference | D75: =MAX(ABS(MIN(D42:D73)),ABS(MAX(D42:D73))) -> 5.9952043e-15

Sheet Trade
A1: XCCY_Swap_EUR_USD_RESET: receive USD-LIBOR-6M on USD 100m; pay EUR-EURIBOR-6M + 150bp on an FX-reset EUR notional (USD 100m via FX-ECB, 2 fixing days); +/-999.99 EUR flows on 2020-02-05.
A2: Legs (ORE order): 0 USD Ibor, 1 EUR cashflow, 2 EUR cashflow, 3 EUR Ibor FX-linked notional, 4 USD notional exchanges, 5 EUR FX-linked notional exchanges.
A3: Curve trigger | B3: =AND('USD-FedFunds'!$B$32,'USD-LIBOR-6M'!$B$31,'EUR-EURIBOR-6M'!$B$32,'EUR-IN-USD'!$B$39,Indexes!$B$31) -> TRUE
A5: Schedule | B5: =_xll.qlSchedule("TradeSchedule",DATE(2016,2,5),DATE(2026,2,5),"6M","TARGET","Modified Following","Modified Following","Forward",FALSE,,,FALSE,$B$3) -> TradeSchedule#0001 | C5: =_xll.ohRangeRetrieveError(B5)
A7: Period | B7: Start | C7: End | D7: FX fixing date | E7: Out flow amount | F7: In flow amount
A8: 0 | B8: =INDEX(_xll.qlScheduleDates($B$5),1) -> 42405 | C8: =INDEX(_xll.qlScheduleDates($B$5),2) -> 42587 | D8: =_xll.qlCalendarAdvance("TARGET",B8,"-2D","Preceding") -> 42403 | E8: -100000000 | F8: 100000000
A9: 1 | B9: =INDEX(_xll.qlScheduleDates($B$5),2) -> 42587 | C9: =INDEX(_xll.qlScheduleDates($B$5),3) -> 42772 | D9: =_xll.qlCalendarAdvance("TARGET",B9,"-2D","Preceding") -> 42585 | E9: -100000000 | F9: 100000000
A10: 2 | B10: =INDEX(_xll.qlScheduleDates($B$5),3) -> 42772 | C10: =INDEX(_xll.qlScheduleDates($B$5),4) -> 42954 | D10: =_xll.qlCalendarAdvance("TARGET",B10,"-2D","Preceding") -> 42768 | E10: -100000000 | F10: 100000000
A11: 3 | B11: =INDEX(_xll.qlScheduleDates($B$5),4) -> 42954 | C11: =INDEX(_xll.qlScheduleDates($B$5),5) -> 43136 | D11: =_xll.qlCalendarAdvance("TARGET",B11,"-2D","Preceding") -> 42950 | E11: -100000000 | F11: 100000000
A12: 4 | B12: =INDEX(_xll.qlScheduleDates($B$5),5) -> 43136 | C12: =INDEX(_xll.qlScheduleDates($B$5),6) -> 43318 | D12: =_xll.qlCalendarAdvance("TARGET",B12,"-2D","Preceding") -> 43132 | E12: -100000000 | F12: 100000000
A13: 5 | B13: =INDEX(_xll.qlScheduleDates($B$5),6) -> 43318 | C13: =INDEX(_xll.qlScheduleDates($B$5),7) -> 43501 | D13: =_xll.qlCalendarAdvance("TARGET",B13,"-2D","Preceding") -> 43314 | E13: -100000000 | F13: 100000000
A14: 6 | B14: =INDEX(_xll.qlScheduleDates($B$5),7) -> 43501 | C14: =INDEX(_xll.qlScheduleDates($B$5),8) -> 43682 | D14: =_xll.qlCalendarAdvance("TARGET",B14,"-2D","Preceding") -> 43497 | E14: -100000000 | F14: 100000000
A15: 7 | B15: =INDEX(_xll.qlScheduleDates($B$5),8) -> 43682 | C15: =INDEX(_xll.qlScheduleDates($B$5),9) -> 43866 | D15: =_xll.qlCalendarAdvance("TARGET",B15,"-2D","Preceding") -> 43678 | E15: -100000000 | F15: 100000000
A16: 8 | B16: =INDEX(_xll.qlScheduleDates($B$5),9) -> 43866 | C16: =INDEX(_xll.qlScheduleDates($B$5),10) -> 44048 | D16: =_xll.qlCalendarAdvance("TARGET",B16,"-2D","Preceding") -> 43864 | E16: -100000000 | F16: 100000000
A17: 9 | B17: =INDEX(_xll.qlScheduleDates($B$5),10) -> 44048 | C17: =INDEX(_xll.qlScheduleDates($B$5),11) -> 44232 | D17: =_xll.qlCalendarAdvance("TARGET",B17,"-2D","Preceding") -> 44046 | E17: -100000000 | F17: 100000000
A18: 10 | B18: =INDEX(_xll.qlScheduleDates($B$5),11) -> 44232 | C18: =INDEX(_xll.qlScheduleDates($B$5),12) -> 44413 | D18: =_xll.qlCalendarAdvance("TARGET",B18,"-2D","Preceding") -> 44230 | E18: -100000000 | F18: 100000000
A19: 11 | B19: =INDEX(_xll.qlScheduleDates($B$5),12) -> 44413 | C19: =INDEX(_xll.qlScheduleDates($B$5),13) -> 44599 | D19: =_xll.qlCalendarAdvance("TARGET",B19,"-2D","Preceding") -> 44411 | E19: -100000000 | F19: 100000000
A20: 12 | B20: =INDEX(_xll.qlScheduleDates($B$5),13) -> 44599 | C20: =INDEX(_xll.qlScheduleDates($B$5),14) -> 44778 | D20: =_xll.qlCalendarAdvance("TARGET",B20,"-2D","Preceding") -> 44595 | E20: -100000000 | F20: 100000000
A21: 13 | B21: =INDEX(_xll.qlScheduleDates($B$5),14) -> 44778 | C21: =INDEX(_xll.qlScheduleDates($B$5),15) -> 44963 | D21: =_xll.qlCalendarAdvance("TARGET",B21,"-2D","Preceding") -> 44776 | E21: -100000000 | F21: 100000000
A22: 14 | B22: =INDEX(_xll.qlScheduleDates($B$5),15) -> 44963 | C22: =INDEX(_xll.qlScheduleDates($B$5),16) -> 45145 | D22: =_xll.qlCalendarAdvance("TARGET",B22,"-2D","Preceding") -> 44959 | E22: -100000000 | F22: 100000000
A23: 15 | B23: =INDEX(_xll.qlScheduleDates($B$5),16) -> 45145 | C23: =INDEX(_xll.qlScheduleDates($B$5),17) -> 45327 | D23: =_xll.qlCalendarAdvance("TARGET",B23,"-2D","Preceding") -> 45141 | E23: -100000000 | F23: 100000000
A24: 16 | B24: =INDEX(_xll.qlScheduleDates($B$5),17) -> 45327 | C24: =INDEX(_xll.qlScheduleDates($B$5),18) -> 45509 | D24: =_xll.qlCalendarAdvance("TARGET",B24,"-2D","Preceding") -> 45323 | E24: -100000000 | F24: 100000000
A25: 17 | B25: =INDEX(_xll.qlScheduleDates($B$5),18) -> 45509 | C25: =INDEX(_xll.qlScheduleDates($B$5),19) -> 45693 | D25: =_xll.qlCalendarAdvance("TARGET",B25,"-2D","Preceding") -> 45505 | E25: -100000000 | F25: 100000000
A26: 18 | B26: =INDEX(_xll.qlScheduleDates($B$5),19) -> 45693 | C26: =INDEX(_xll.qlScheduleDates($B$5),20) -> 45874 | D26: =_xll.qlCalendarAdvance("TARGET",B26,"-2D","Preceding") -> 45691 | E26: -100000000 | F26: 100000000
A27: 19 | B27: =INDEX(_xll.qlScheduleDates($B$5),20) -> 45874 | C27: =INDEX(_xll.qlScheduleDates($B$5),21) -> 46058 | D27: =_xll.qlCalendarAdvance("TARGET",B27,"-2D","Preceding") -> 45870 | E27: -100000000 | F27: 100000000
A30: Leg | B30: Object | C30: Error | D30: Payer | E30: Currency
A31: 0 USD LIBOR-6M | B31: {=_xll.qlIborLeg("Leg0","Modified Following",100000000,$B$5,2,FALSE,"Actual/360",,1,Indexes!$B$17,0,,FALSE,$B$3)} -> Leg0#0000 | C31: =_xll.ohRangeRetrieveError(B31) | D31: FALSE | E31: USD
A32: 1 EUR cashflow | B32: {=_xll.qlLeg("Leg1",999.99,DATE(2020,2,5),TRUE,FALSE,$B$3)} -> Leg1#0001 | C32: =_xll.ohRangeRetrieveError(B32) | D32: TRUE | E32: EUR
A33: 2 EUR cashflow | B33: {=_xll.qlLeg("Leg2",-999.99,DATE(2020,2,5),TRUE,FALSE,$B$3)} -> Leg2#0001 | C33: =_xll.ohRangeRetrieveError(B33) | D33: TRUE | E33: EUR
A34: 3a EUR EURIBOR-6M+150bp (underlying) | B34: {=_xll.qlIborLeg("Leg3Underlying","Modified Following",88312931.57,$B$5,2,FALSE,"Actual/360",,1,Indexes!$B$19,0.015,,FALSE,$B$3)} -> Leg3Underlying#0000 | C34: =_xll.ohRangeRetrieveError(B34)
A35: 3 EUR FX-linked notional coupons | B35: {=_xll.qlFloatingRateFXLinkedNotionalLeg("Leg3",B34,D8:D27,100000000,Indexes!$B$23,FALSE,$B$3)} -> Leg3#0000 | C35: =_xll.ohRangeRetrieveError(B35) | D35: TRUE | E35: EUR
A36: 4 USD final notional | B36: {=_xll.qlLeg("Leg4",100000000,DATE(2026,2,5),TRUE,FALSE,$B$3)} -> Leg4#0001 | C36: =_xll.ohRangeRetrieveError(B36) | D36: FALSE | E36: USD
A37: 5 EUR FX-linked notional exchanges | B37: {=_xll.qlFXLinkedCashFlowLeg("Leg5",_xlfn.CHOOSECOLS(_xlfn.VSTACK(_xlfn.HSTACK(B9:B27,D9:D27,E9:E27),_xlfn.HSTACK(C8:C27,D8:D27,F8:F27)),1),_xlfn.CHOOSECOLS(_xlfn.VSTACK(_xlfn.HSTACK(B9:B27,D9:D27,E9:E27),_xlfn.HSTACK(C8:C27,D8:D27,F8:F27)),2),_xlfn.CHOOSECOLS(_xlfn.VSTACK(_xlfn.HSTACK(B9:B27,D9:D27,E9:E27),_xlfn.HSTACK(C8:C27,D8:D27,F8:F27)),3),Indexes!$B$23,FALSE,$B$3)} -> Leg5#0000 | C37: =_xll.ohRangeRetrieveError(B37) | D37: TRUE | E37: EUR
A39: Currency swap | B39: {=_xll.qlCurrencySwap("XCCY_Swap_EUR_USD_RESET",_xlfn.VSTACK(B31,B32,B33,B35,B36,B37),_xlfn.VSTACK(D31,D32,D33,D35,D36,D37),_xlfn.VSTACK(E31,E32,E33,E35,E36,E37),TRUE,TRUE,FALSE,$B$3)} -> XCCY_Swap_EUR_USD_RESET#0000 | C39: =_xll.ohRangeRetrieveError(B39)
A40: EUR/USD spot date | B40: =_xll.qlCalendarAdvance("JoinHolidays(TARGET,UnitedStates::Settlement)",MarketData!$B$4*0+DATE(2019,12,30),"2D") -> 43832
A41: EUR/USD today (spot x DF_USD/DF_EUR at spot date) | B41: =MarketData!$D$93*_xll.qlYieldTSDiscount(Indexes!$B$5,B40,TRUE,$B$3)/_xll.qlYieldTSDiscount(Indexes!$B$11,B40,TRUE,$B$3) -> 1.1197028
A42: FX quote EUR/USD today | B42: =_xll.qlSimpleQuote("FX_EURUSD_TODAY",B41,0,FALSE,$B$3) -> FX_EURUSD_TODAY#0000 | C42: =_xll.ohRangeRetrieveError(B42)
A43: FX quote USD/USD | B43: =_xll.qlSimpleQuote("FX_USDUSD",1,0,FALSE,$B$3) -> FX_USDUSD#0001
A44: Engine | B44: {=_xll.qlDiscountingCurrencySwapEngine("XccyEngine",_xlfn.VSTACK(Indexes!$B$5,Indexes!$B$11),_xlfn.VSTACK(B43,B42),{"USD";"EUR"},"USD",FALSE,$B$3)} -> XccyEngine#0000 | C44: =_xll.ohRangeRetrieveError(B44)
A45: Set engine | B45: =_xll.qlInstrumentSetPricingEngine(B39,B44) -> TRUE
A46: NPV (USD) | B46: =_xll.qlInstrumentNPV(B39,B45) -> -10860611 | C46: ORE | D46: -10860611 | E46: =B46-D46 -> 4.0791929e-07
A47: Leg | B47: NPV in leg ccy | C47: NPV (USD)
A48: 0 | B48: =_xll.qlCurrencySwapInCcyLegNPV($B$39,0,$B$45) -> 11315471 | C48: =_xll.qlCurrencySwapLegNPV($B$39,0,$B$45) -> 11315471
A49: 1 | B49: =_xll.qlCurrencySwapInCcyLegNPV($B$39,1,$B$45) -> -1000.6534 | C49: =_xll.qlCurrencySwapLegNPV($B$39,1,$B$45) -> -1120.4344
A50: 2 | B50: =_xll.qlCurrencySwapInCcyLegNPV($B$39,2,$B$45) -> 1000.6534 | C50: =_xll.qlCurrencySwapLegNPV($B$39,2,$B$45) -> 1120.4344
A51: 3 | B51: =_xll.qlCurrencySwapInCcyLegNPV($B$39,3,$B$45) -> -8056979.6 | C51: =_xll.qlCurrencySwapLegNPV($B$39,3,$B$45) -> -9021422.7
A52: 4 | B52: =_xll.qlCurrencySwapInCcyLegNPV($B$39,4,$B$45) -> 91275629 | C52: =_xll.qlCurrencySwapLegNPV($B$39,4,$B$45) -> 91275629
A53: 5 | B53: =_xll.qlCurrencySwapInCcyLegNPV($B$39,5,$B$45) -> -93266077 | C53: =_xll.qlCurrencySwapLegNPV($B$39,5,$B$45) -> -1.0443029e+08
A55: Flow analysis leg 0 (after 2019-12-30); payer=FALSE | AD55: Leg | AE55: Pay date | AF55: Excel amount (signed) | AG55: ORE amount | AH55: Difference | AI55: Excel row
A56: {=_xll.qlLegFlowAnalysis(B31,DATE(2019,12,30),$B$45)} -> Payment Date | B56: Amount | C56: Nominal | D56: Accrual Start Date | E56: Accrual End Date | F56: Accrual Days | G56: Index | H56: Fixing Days | I56: Fixing Dates | J56: Day Counter | K56: Accrual Period | L56: Effective Rate | M56: Floor | N56: Gearing | O56: Index Fixing | P56: Conv. Adj. | Q56: Spread | R56: Cap | S56: Call Digital Payoff | T56: Put Digital Payoff | AD56: 0 | AE56: =DATE(2020,2,5) -> 43866 | AF56: =1*B57 -> 1138183.1 | AG56: 1138183.1 | AH56: =AF56-AG56 -> 1.1110911e-05 | AI56: 57
A57: 43866 | B57: 1138183.1 | C57: 100000000 | D57: 43682 | E57: 43866 | F57: 184 | G57: USDLibor6M Actual/360 | H57: 2 | I57: 43678 | J57: Actual/360 | K57: 0.51111111 | L57: 0.0222688 | M57: #N/A | N57: 1 | O57: 0.0222688 | P57: 0 | Q57: 0 | R57: #N/A | S57: #N/A | T57: #N/A | AD57: 0 | AE57: =DATE(2020,8,5) -> 44048 | AF57: =1*B58 -> 911828.48 | AG57: 911828.48 | AH57: =AF57-AG57 -> -1.7578597e-05 | AI57: 58
A58: 44048 | B58: 911828.48 | C58: 100000000 | D58: 43866 | E58: 44048 | F58: 182 | G58: USDLibor6M Actual/360 | H58: 2 | I58: 43864 | J58: Actual/360 | K58: 0.50555556 | L58: 0.018036168 | M58: #N/A | N58: 1 | O58: 0.018036168 | P58: 0 | Q58: 0 | R58: #N/A | S58: #N/A | T58: #N/A | AD58: 0 | AE58: =DATE(2021,2,5) -> 44232 | AF58: =1*B59 -> 878298.34 | AG58: 878298.34 | AH58: =AF58-AG58 -> -4.0386221e-05 | AI58: 59
A59: 44232 | B59: 878298.34 | C59: 100000000 | D59: 44048 | E59: 44232 | F59: 184 | G59: USDLibor6M Actual/360 | H59: 2 | I59: 44046 | J59: Actual/360 | K59: 0.51111111 | L59: 0.017184098 | M59: #N/A | N59: 1 | O59: 0.017184098 | P59: 0 | Q59: 0 | R59: #N/A | S59: #N/A | T59: #N/A | AD59: 0 | AE59: =DATE(2021,8,5) -> 44413 | AF59: =1*B60 -> 834251.72 | AG59: 834251.72 | AH59: =AF59-AG59 -> -2.2967579e-05 | AI59: 60
A60: 44413 | B60: 834251.72 | C60: 100000000 | D60: 44232 | E60: 44413 | F60: 181 | G60: USDLibor6M Actual/360 | H60: 2 | I60: 44230 | J60: Actual/360 | K60: 0.50277778 | L60: 0.016592852 | M60: #N/A | N60: 1 | O60: 0.016592852 | P60: 0 | Q60: 0 | R60: #N/A | S60: #N/A | T60: #N/A | AD60: 0 | AE60: =DATE(2022,2,7) -> 44599 | AF60: =1*B61 -> 878999.02 | AG60: 878999.02 | AH60: =AF60-AG60 -> 4.3602195e-05 | AI60: 61
A61: 44599 | B61: 878999.02 | C61: 100000000 | D61: 44413 | E61: 44599 | F61: 186 | G61: USDLibor6M Actual/360 | H61: 2 | I61: 44411 | J61: Actual/360 | K61: 0.51666667 | L61: 0.017012884 | M61: #N/A | N61: 1 | O61: 0.017012884 | P61: 0 | Q61: 0 | R61: #N/A | S61: #N/A | T61: #N/A | AD61: 0 | AE61: =DATE(2022,8,5) -> 44778 | AF61: =1*B62 -> 803431.26 | AG61: 803431.26 | AH61: =AF61-AG61 -> -2.1375716e-05 | AI61: 62
A62: 44778 | B62: 803431.26 | C62: 100000000 | D62: 44599 | E62: 44778 | F62: 179 | G62: USDLibor6M Actual/360 | H62: 2 | I62: 44595 | J62: Actual/360 | K62: 0.49722222 | L62: 0.016158394 | M62: #N/A | N62: 1 | O62: 0.016158394 | P62: 0 | Q62: 0 | R62: #N/A | S62: #N/A | T62: #N/A | AD62: 0 | AE62: =DATE(2023,2,6) -> 44963 | AF62: =1*B63 -> 843079.43 | AG62: 843079.43 | AH62: =AF62-AG62 -> -2.0576641e-05 | AI62: 63
A63: 44963 | B63: 843079.43 | C63: 100000000 | D63: 44778 | E63: 44963 | F63: 185 | G63: USDLibor6M Actual/360 | H63: 2 | I63: 44776 | J63: Actual/360 | K63: 0.51388889 | L63: 0.01640587 | M63: #N/A | N63: 1 | O63: 0.01640587 | P63: 0 | Q63: 0 | R63: #N/A | S63: #N/A | T63: #N/A | AD63: 0 | AE63: =DATE(2023,8,7) -> 45145 | AF63: =1*B64 -> 884439.89 | AG63: 884439.89 | AH63: =AF63-AG63 -> 3.3980818e-05 | AI63: 64
A64: 45145 | B64: 884439.89 | C64: 100000000 | D64: 44963 | E64: 45145 | F64: 182 | G64: USDLibor6M Actual/360 | H64: 2 | I64: 44959 | J64: Actual/360 | K64: 0.50555556 | L64: 0.017494415 | M64: #N/A | N64: 1 | O64: 0.017494415 | P64: 0 | Q64: 0 | R64: #N/A | S64: #N/A | T64: #N/A | AD64: 0 | AE64: =DATE(2024,2,5) -> 45327 | AF64: =1*B65 -> 886571.55 | AG64: 886571.55 | AH64: =AF64-AG64 -> 2.9194052e-05 | AI64: 65
A65: 45327 | B65: 886571.55 | C65: 100000000 | D65: 45145 | E65: 45327 | F65: 182 | G65: USDLibor6M Actual/360 | H65: 2 | I65: 45141 | J65: Actual/360 | K65: 0.50555556 | L65: 0.01753658 | M65: #N/A | N65: 1 | O65: 0.01753658 | P65: 0 | Q65: 0 | R65: #N/A | S65: #N/A | T65: #N/A | AD65: 0 | AE65: =DATE(2024,8,5) -> 45509 | AF65: =1*B66 -> 895851.1 | AG65: 895851.1 | AH65: =AF65-AG65 -> -3.2083015e-05 | AI65: 66
A66: 45509 | B66: 895851.1 | C66: 100000000 | D66: 45327 | E66: 45509 | F66: 182 | G66: USDLibor6M Actual/360 | H66: 2 | I66: 45323 | J66: Actual/360 | K66: 0.50555556 | L66: 0.017720132 | M66: #N/A | N66: 1 | O66: 0.017720132 | P66: 0 | Q66: 0 | R66: #N/A | S66: #N/A | T66: #N/A | AD66: 0 | AE66: =DATE(2025,2,5) -> 45693 | AF66: =1*B67 -> 920092.85 | AG66: 920092.85 | AH66: =AF66-AG66 -> -1.4703139e-05 | AI66: 67
A67: 45693 | B67: 920092.85 | C67: 100000000 | D67: 45509 | E67: 45693 | F67: 184 | G67: USDLibor6M Actual/360 | H67: 2 | I67: 45505 | J67: Actual/360 | K67: 0.51111111 | L67: 0.018001817 | M67: #N/A | N67: 1 | O67: 0.018001817 | P67: 0 | Q67: 0 | R67: #N/A | S67: #N/A | T67: #N/A | AD67: 0 | AE67: =DATE(2025,8,5) -> 45874 | AF67: =1*B68 -> 967326.72 | AG67: 967326.72 | AH67: =AF67-AG67 -> 6.9000525e-06 | AI67: 68
A68: 45874 | B68: 967326.72 | C68: 100000000 | D68: 45693 | E68: 45874 | F68: 181 | G68: USDLibor6M Actual/360 | H68: 2 | I68: 45691 | J68: Actual/360 | K68: 0.50277778 | L68: 0.019239647 | M68: #N/A | N68: 1 | O68: 0.019239647 | P68: 0 | Q68: 0 | R68: #N/A | S68: #N/A | T68: #N/A | AD68: 0 | AE68: =DATE(2026,2,5) -> 46058 | AF68: =1*B69 -> 992444.77 | AG68: 992444.77 | AH68: =AF68-AG68 -> -1.023151e-05 | AI68: 69
A69: 46058 | B69: 992444.77 | C69: 100000000 | D69: 45874 | E69: 46058 | F69: 184 | G69: USDLibor6M Actual/360 | H69: 2 | I69: 45870 | J69: Actual/360 | K69: 0.51111111 | L69: 0.019417398 | M69: #N/A | N69: 1 | O69: 0.019417398 | P69: 0 | Q69: 0 | R69: #N/A | S69: #N/A | T69: #N/A | AD69: 1 | AE69: =DATE(2020,2,5) -> 43866 | AF69: =-1*B88 -> -999.99 | AG69: -999.99 | AH69: =AF69-AG69 -> 0 | AI69: 88
AD70: 2 | AE70: =DATE(2020,2,5) -> 43866 | AF70: =-1*B119 -> 999.99 | AG70: 999.99 | AH70: =AF70-AG70 -> 0 | AI70: 119
AD71: 3 | AE71: =DATE(2020,2,5) -> 43866 | AF71: =-1*B150 -> -526531.97 | AG71: -526531.97 | AH71: =AF71-AG71 -> -2.8081238e-05 | AI71: 150
AD72: 3 | AE72: =DATE(2020,8,5) -> 44048 | AF72: =-1*B151 -> -526260.36 | AG72: -526260.36 | AH72: =AF72-AG72 -> 4.083477e-05 | AI72: 151
AD73: 3 | AE73: =DATE(2021,2,5) -> 44232 | AF73: =-1*B152 -> -535305.87 | AG73: -535305.87 | AH73: =AF73-AG73 -> -1.8196879e-06 | AI73: 152
AD74: 3 | AE74: =DATE(2021,8,5) -> 44413 | AF74: =-1*B153 -> -534992.37 | AG74: -534992.37 | AH74: =AF74-AG74 -> -1.1797063e-05 | AI74: 153
AD75: 3 | AE75: =DATE(2022,2,7) -> 44599 | AF75: =-1*B154 -> -567211.11 | AG75: -567211.11 | AH75: =AF75-AG75 -> -8.3437189e-06 | AI75: 154
AD76: 3 | AE76: =DATE(2022,8,5) -> 44778 | AF76: =-1*B155 -> -585242.74 | AG76: -585242.74 | AH76: =AF76-AG76 -> 9.7592128e-06 | AI76: 155
AD77: 3 | AE77: =DATE(2023,2,6) -> 44963 | AF77: =-1*B156 -> -605630.56 | AG77: -605630.56 | AH77: =AF77-AG77 -> -3.5727164e-05 | AI77: 156
AD78: 3 | AE78: =DATE(2023,8,7) -> 45145 | AF78: =-1*B157 -> -617556.66 | AG78: -617556.66 | AH78: =AF78-AG78 -> -3.5501318e-05 | AI78: 157
AD79: 3 | AE79: =DATE(2024,2,5) -> 45327 | AF79: =-1*B158 -> -623263.78 | AG79: -623263.78 | AH79: =AF79-AG79 -> -6.8235677e-06 | AI79: 158
AD80: 3 | AE80: =DATE(2024,8,5) -> 45509 | AF80: =-1*B159 -> -668061.25 | AG80: -668061.25 | AH80: =AF80-AG80 -> 4.513422e-07 | AI80: 159
AD81: 3 | AE81: =DATE(2025,2,5) -> 45693 | AF81: =-1*B160 -> -678943.33 | AG81: -678943.33 | AH81: =AF81-AG81 -> -2.4224515e-05 | AI81: 160
AD82: 3 | AE82: =DATE(2025,8,5) -> 45874 | AF82: =-1*B161 -> -703496.86 | AG82: -703496.86 | AH82: =AF82-AG82 -> 2.4449313e-05 | AI82: 161
AD83: 3 | AE83: =DATE(2026,2,5) -> 46058 | AF83: =-1*B162 -> -726206.97 | AG83: -726206.97 | AH83: =AF83-AG83 -> -4.1547231e-05 | AI83: 162
AD84: 4 | AE84: =DATE(2026,2,5) -> 46058 | AF84: =1*B181 -> 100000000 | AG84: 100000000 | AH84: =AF84-AG84 -> 0 | AI84: 181
AD85: 5 | AE85: =DATE(2020,2,5) -> 43866 | AF85: =-1*B212 -> 89107803 | AG85: 89107803 | AH85: =AF85-AG85 -> 3.3453107e-05 | AI85: 212
A86: Flow analysis leg 1 (after 2019-12-30); payer=TRUE | AD86: 5 | AE86: =DATE(2020,8,5) -> 44048 | AF86: =-1*B213 -> 88117688 | AG86: 88117688 | AH86: =AF86-AG86 -> -3.8817525e-05 | AI86: 213
A87: {=_xll.qlLegFlowAnalysis(B32,DATE(2019,12,30),$B$45)} -> Payment Date | B87: Amount | C87: Nominal | D87: Accrual Start Date | E87: Accrual End Date | F87: Accrual Days | G87: Index | H87: Fixing Days | I87: Fixing Dates | J87: Day Counter | K87: Accrual Period | L87: Effective Rate | M87: Floor | N87: Gearing | O87: Index Fixing | P87: Conv. Adj. | Q87: Spread | R87: Cap | S87: Call Digital Payoff | T87: Put Digital Payoff | AD87: 5 | AE87: =DATE(2021,2,5) -> 44232 | AF87: =-1*B214 -> 87165007 | AG87: 87165007 | AH87: =AF87-AG87 -> 9.059906e-06 | AI87: 214
A88: 43866 | B88: 999.99 | C88: #N/A | D88: #N/A | E88: #N/A | F88: #N/A | G88: #N/A | H88: #N/A | I88: #N/A | J88: #N/A | K88: #N/A | L88: #N/A | M88: #N/A | N88: #N/A | O88: #N/A | P88: #N/A | Q88: #N/A | R88: #N/A | S88: #N/A | T88: #N/A | AD88: 5 | AE88: =DATE(2021,8,5) -> 44413 | AF88: =-1*B215 -> 86298467 | AG88: 86298467 | AH88: =AF88-AG88 -> 4.6089292e-05 | AI88: 215
AD89: 5 | AE89: =DATE(2022,2,7) -> 44599 | AF89: =-1*B216 -> 85333178 | AG89: 85333178 | AH89: =AF89-AG89 -> -1.7538667e-05 | AI89: 216
AD90: 5 | AE90: =DATE(2022,8,5) -> 44778 | AF90: =-1*B217 -> 84505068 | AG90: 84505068 | AH90: =AF90-AG90 -> -1.6435981e-05 | AI90: 217
AD91: 5 | AE91: =DATE(2023,2,6) -> 44963 | AF91: =-1*B218 -> 83657802 | AG91: 83657802 | AH91: =AF91-AG91 -> -7.8231096e-06 | AI91: 218
AD92: 5 | AE92: =DATE(2023,8,7) -> 45145 | AF92: =-1*B219 -> 82833252 | AG92: 82833252 | AH92: =AF92-AG92 -> 2.4065375e-05 | AI92: 219
AD93: 5 | AE93: =DATE(2024,2,5) -> 45327 | AF93: =-1*B220 -> 82027751 | AG93: 82027751 | AH93: =AF93-AG93 -> 1.2904406e-05 | AI93: 220
AD94: 5 | AE94: =DATE(2024,8,5) -> 45509 | AF94: =-1*B221 -> 81277186 | AG94: 81277186 | AH94: =AF94-AG94 -> 3.2141805e-05 | AI94: 221
AD95: 5 | AE95: =DATE(2025,2,5) -> 45693 | AF95: =-1*B222 -> 80524549 | AG95: 80524549 | AH95: =AF95-AG95 -> -4.0233135e-07 | AI95: 222
AD96: 5 | AE96: =DATE(2025,8,5) -> 45874 | AF96: =-1*B223 -> 79787521 | AG96: 79787521 | AH96: =AF96-AG96 -> 1.5094876e-05 | AI96: 223
AD97: 5 | AE97: =DATE(2020,2,5) -> 43866 | AF97: =-1*B224 -> -90604331 | AG97: -90604331 | AH97: =AF97-AG97 -> -1.6406178e-05 | AI97: 224
AD98: 5 | AE98: =DATE(2020,8,5) -> 44048 | AF98: =-1*B225 -> -89107803 | AG98: -89107803 | AH98: =AF98-AG98 -> -3.3453107e-05 | AI98: 225
AD99: 5 | AE99: =DATE(2021,2,5) -> 44232 | AF99: =-1*B226 -> -88117688 | AG99: -88117688 | AH99: =AF99-AG99 -> 3.8817525e-05 | AI99: 226
AD100: 5 | AE100: =DATE(2021,8,5) -> 44413 | AF100: =-1*B227 -> -87165007 | AG100: -87165007 | AH100: =AF100-AG100 -> -9.059906e-06 | AI100: 227
AD101: 5 | AE101: =DATE(2022,2,7) -> 44599 | AF101: =-1*B228 -> -86298467 | AG101: -86298467 | AH101: =AF101-AG101 -> -4.6089292e-05 | AI101: 228
AD102: 5 | AE102: =DATE(2022,8,5) -> 44778 | AF102: =-1*B229 -> -85333178 | AG102: -85333178 | AH102: =AF102-AG102 -> 1.7538667e-05 | AI102: 229
AD103: 5 | AE103: =DATE(2023,2,6) -> 44963 | AF103: =-1*B230 -> -84505068 | AG103: -84505068 | AH103: =AF103-AG103 -> 1.6435981e-05 | AI103: 230
AD104: 5 | AE104: =DATE(2023,8,7) -> 45145 | AF104: =-1*B231 -> -83657802 | AG104: -83657802 | AH104: =AF104-AG104 -> 7.8231096e-06 | AI104: 231
AD105: 5 | AE105: =DATE(2024,2,5) -> 45327 | AF105: =-1*B232 -> -82833252 | AG105: -82833252 | AH105: =AF105-AG105 -> -2.4065375e-05 | AI105: 232
AD106: 5 | AE106: =DATE(2024,8,5) -> 45509 | AF106: =-1*B233 -> -82027751 | AG106: -82027751 | AH106: =AF106-AG106 -> -1.2904406e-05 | AI106: 233
...
